Workbook

Sheet 评测集
E1: 序号 | F1: 需求name | G1: 需求描述 | H1: A | I1: B | J1: C | K1: A vs B | L1: B vs C | M1: A vs C | N1: A vs B | O1: B vs C | P1: A vs C | Q1: A vs B | R1: B vs C | S1: A vs C
E2: C01 | F2: BankAccount | G2: The following description of a bank is given. Create a suitable class diagram from the given informal description. A bank manages any number of customers. The first name and last name of type String are stored for each customer. A bank consists of any number of branches. A customer has at least one and at most five accounts. Each account has an owner who is a customer of the bank. There are two basic types of accounts: Current accounts and savings accounts. Each account has an account number of type int and a current account balance of type double. Current accounts also have an overdraft limit of type double. | H2: @startuml class Bank { bankName: String } class Branch { branchName: String } class Customer { firstName: String lastName: String } abstract class Account { accountNumber: int balance: double } class CurrentAccount { overdraftLimit: double } class SavingsAccount { } Bank *-- "0..*" Branch: operatesBranch Bank --> "0..*" Customer: manages 'opposite bank Customer --> "1" Bank: bank Customer --> "1..5" Account: account 'opposite owner Account --> "1" Customer: owner 'opposite account CurrentAccount --|> Account SavingsAccount --|> Account @enduml | I2: @startuml class Bank class Branch class Customer { firstName : String lastName : String } abstract class Account { accountNumber : int balance : double } class CurrentAccount { overdraftLimit : double } class SavingsAccount Bank "1" -- "0..*" Customer : manages Bank "1" -- "0..*" Branch : consists of Customer "1" -- "1..5" Account : owns Account <|-- CurrentAccount Account <|-- SavingsAccount @enduml | J2: @startuml class Bank { } class Branch { } class Customer { - firstName: String - lastName: String } class Account { - accountNumber: int - balance: double } class CurrentAccount { - overdraftLimit: double } class SavingsAccount { } Bank "1" --- "0..*" Customer : manages Bank "1" *-- "0..*" Branch : consists of Customer "1" --- "1..5" Account : has Account "0..*" --- "1" Customer : owner CurrentAccount --|> Account SavingsAccount --|> Account @enduml | K2: D（平局） | L2: B | M2: A | N2: D（平局） | O2: B | P2: A | Q2: D（平局） | R2: C | S2: C
E3: C02 | F3: EUScienceConnect | G3: Recently, the European Union made funds available to set-up a cross-national research database that stores information concerning scientific articles of researchers working at institutions in the EU. Science Connect is the company that will be setting up this database. The system will store information regarding scientific staff (persons) and research institutions. Bot hare uniquely identified by a person ID and an institution code, respectively. The following is also recorded for each person: a phone number, keywords that identify his/her keys research topics and the institution he/she works for. A person can be an author of one article and a reviewer of another peer-reviewed article at the same time. The database will store the following information concerning scientific articles. Each scientific article is uniquely identified by a DOI (a document object identifier), and the system also stores the title and the authors of the article. In the case of multiple authors, the position of each author is stored. Science Connect distinguishes between two types of scientific articles: a scientific article is either a peer-reviewed paper or a technical report. The system stores the citation count of peer-reviewed papers and who reviewed the paper. A technical report is always published by a single research institution, while research institutions can of course publish multiple technical reports. The system keeps track of the different scientific publishers (e.g., IEE, Elsevier). A publisher is identified by name. A publisher can publish multiple journals to which research institutions can subscribe. These journals are given a name by the publisher (e.g., Decision Support Systems). Publishers can have journals with the same name as other publishers; e.g., it is possible that both IEE and Elsevier have a journal with the title Management Science. The impact factor, which measures the scientific impact of a journal is also stored. Finally, only peer-reviewed papers are published in journals, not technical reports. | H3: @startuml skinparam classAttributeIconSize 0 skinparam linetype ortho ' === Entities === class Person { personId : String phoneNumber : String researchKeywords : List<String> } class ResearchInstitution { institutionCode : String } class Publisher { name : String } class Journal { name : String impactFactor : double } ' === Article Hierarchy === abstract class ScientificArticle { doi : String title : String } class PeerReviewedPaper { citationCount : int } class TechnicalReport { } ' === Role / Authorship === class Authorship { position : int } ' === Relationships === ' Person works for ResearchInstitution Person --> "1" ResearchInstitution : worksFor 'opposite employs ResearchInstitution --> "*" Person : employs 'opposite worksFor ' Institution publishes Technical Reports ResearchInstitution --> "*" TechnicalReport : publishes 'opposite publishedBy TechnicalReport --> "1" ResearchInstitution : publishedBy 'opposite publishes ' Publisher issues Journals Publisher --> "*" Journal : issues 'opposite issuedBy Journal --> "1" Publisher : issuedBy 'opposite issues ' Institution subscribes to Journals ResearchInstitution --> "*" Journal : subscribesTo 'opposite subscribedBy Journal --> "*" ResearchInstitution : subscribedBy 'opposite subscribesTo ' ScientificArticle hierarchy ScientificArticle <|-- PeerReviewedPaper ScientificArticle <|-- TechnicalReport ' Authorship (links Person, ScientificArticle with position) Authorship --> "1" Person : authoredBy 'opposite authors Person --> "*" Authorship : authors 'opposite authoredBy Authorship --> "1" ScientificArticle : writes 'opposite authorships ScientificArticle --> "1..*" Authorship : authorships 'opposite writes ' PeerReviewedPaper is reviewed by Persons PeerReviewedPaper --> "*" Person : reviewedBy 'opposite reviews Person --> "*" PeerReviewedPaper : reviews 'opposite reviewedBy ' PeerReviewedPaper is published in a Journal PeerReviewedPaper --> "1" Journal : publishedIn 'opposite features Journal --> "*" PeerReviewedPaper : features 'opposite publishedIn @enduml | I3: @startuml class Person { personID : String phoneNumber : String keywords : Set<String> } class Institution { institutionCode : String } abstract class ScientificArticle { DOI : String title : String } class PeerReviewedPaper { citationCount : int } class TechnicalReport { } class Publisher { name : String } class Journal { name : String impactFactor : double } class Authorship { position : int } ScientificArticle <|-- PeerReviewedPaper ScientificArticle <|-- TechnicalReport Person "1" -- "1" Institution : worksFor Authorship -- "1..*" Person : author Authorship -- "1" ScientificArticle : article Person "0..*" -- "0..*" PeerReviewedPaper : reviews Institution "1" -- "0..*" TechnicalReport : publishes Publisher "1" -- "0..*" Journal : publishes Journal "1" -- "0..*" PeerReviewedPaper : publishesIn Institution "0..*" -- "0..*" Journal : subscribesTo @enduml | J3: @startuml class Person { - personID : String - phoneNumber : String - researchKeywords : String } class ResearchInstitution { - institutionCode : String } class ScientificArticle { - DOI : String - title : String } class PeerReviewedPaper { - citationCount : int } class TechnicalReport { } class Publisher { - name : String } class Journal { - name : String - impactFactor : float } class Authorship { - position : int } ScientificArticle <|-- PeerReviewedPaper ScientificArticle <|-- TechnicalReport Person "1" -- "1" ResearchInstitution : works for Person "1" -- "*" Authorship : authors through ScientificArticle "1" -- "*" Authorship : has author Person "1" -- "*" PeerReviewedPaper : reviews TechnicalReport "*" -- "1" ResearchInstitution : published by Publisher "1" *-- "*" Journal : publishes ResearchInstitution "*" -- "*" Journal : subscribes to PeerReviewedPaper "*" -- "1" Journal : published in @enduml | K3: A | L3: C | M3: A | N3: A | O3: C | P3: A | Q3: A | R3: B | S3: A
E4: C03 | F4: Cruise | G4: A cruise is organized by a specific provider, each provider has a name and a location. A cruise is identified by a number and a name and has a start and end date. A cruise requires many employees, each of whom has a name and a social security number. Several guests take part in a cruise, each guest has a name and it is also noted whether they are a VIP or not. A guest can, of course, also take several cruises. The name of each ship, the number of decks, the length of the ship, and the number of passengers are known. A ship can be used for different cruises. A cruise is booked through a travel agency. Each booking has a unique booking number and a booking date. A travel agency has a name and an address. A cruise always heads for a specific destination area, each destination area has a name, and the name of the sea is also noted. On a cruise, guests are offered several shows, each show has a title and a certain duration. A cruise has several guests, and each guest can participate in several cruises. Several tickets are issued for each cruise. A ticket belongs to exactly one cruise. A guest can have any number of tickets, but only one ticket per cruise. | H4: @startuml class Provider { name: String location: String } class Cruise { number: int name: String startDate: Date endDate: Date } class Employee { name: String socialSecurityNumber: String } class Guest { name: String isVip: boolean } class Ship { name: String numberOfDecks: int length: double numberOfPassengers: int } class TravelAgency { name: String address: String } class Booking { bookingNumber: int bookingDate: Date } class DestinationArea { name: String seaName: String } class Show { title: String duration: double } class Ticket { ticketNumber: int } Cruise --> "1" Provider: organizedBy 'opposite cruises Provider --> "*" Cruise: cruises 'opposite organizedBy Cruise --> "1..*" Employee: employs 'opposite cruisesWorked Employee --> "*" Cruise: cruisesWorked 'opposite employs Cruise --> "*" Guest: hosts 'opposite cruisesAttended Guest --> "*" Cruise: cruisesAttended 'opposite hosts Cruise --> "1" Ship: uses 'opposite cruisesServed Ship --> "*" Cruise: cruisesServed 'opposite uses Booking --> "1" Cruise: bookedFor 'opposite cruiseBookings Cruise --> "*" Booking: cruiseBookings 'opposite bookedFor Booking --> "1" TravelAgency: managedBy 'opposite bookingsHandled TravelAgency --> "*" Booking: bookingsHandled 'opposite managedBy Booking --> "1" Guest: bookedBy 'opposite guestBookings Guest --> "*" Booking: guestBookings 'opposite bookedBy Cruise --> "1" DestinationArea: headsFor 'opposite cruisesToDestination DestinationArea --> "*" Cruise: cruisesToDestination 'opposite headsFor Cruise --> "*" Show: offers 'opposite cruisesOfferingShow Show --> "*" Cruise: cruisesOfferingShow 'opposite offers Ticket --> "1" Cruise: issuedFor 'opposite tickets Cruise --> "*" Ticket: tickets 'opposite issuedFor Ticket --> "1" Guest: ownedBy 'opposite tickets Guest --> "*" Ticket: tickets 'opposite ownedBy @enduml | I4: @startuml class Provider { name : String location : String } class Cruise { number : String name : String startDate : Date endDate : Date } class Employee { name : String socialSecurityNumber : String } class Guest { name : String isVIP : Boolean } class Ship { name : String numberOfDecks : Integer length : Double passengerCapacity : Integer } class TravelAgency { name : String address : String } class Booking { bookingNumber : String bookingDate : Date } class DestinationArea { name : String seaName : String } class Show { title : String duration : Duration } class Ticket { ticketId : String } Cruise "1" -- "1" Provider : organizedBy Cruise "*" -- "*" Employee : requires Cruise "*" -- "*" Guest : participates Cruise "*" -- "1" Ship : uses Cruise "*" -- "1" DestinationArea : headsFor Cruise "1" -- "*" Show : offers Booking "*" -- "1" TravelAgency : bookedThrough Booking "*" -- "1" Cruise : books Booking "*" -- "1" Guest : bookedBy Ticket "*" -- "1" Cruise : issuedFor Ticket "*" -- "1" Guest : issuedTo @enduml | J4: @startuml class Provider { +name: String +location: String } class Cruise { +number: String +name: String +startDate: Date +endDate: Date } class Employee { +name: String +socialSecurityNumber: String } class Guest { +name: String +isVIP: Boolean } class Ship { +name: String +numberOfDecks: Integer +length: Double +numberOfPassengers: Integer } class TravelAgency { +name: String +address: String } class Booking { +bookingNumber: String +bookingDate: Date } class DestinationArea { +name: String +seaName: String } class Show { +title: String +duration: Integer } class Ticket { +ticketNumber: String } Provider "1" -- "0..*" Cruise Cruise "1" -- "0..*" Employee Cruise "1" -- "0..*" Guest Cruise "1" -- "0..*" Ticket Cruise "1" -- "1" Ship Cruise "1" -- "1" DestinationArea Cruise "1" -- "0..*" Show TravelAgency "1" -- "0..*" Booking Booking "1" -- "1" Ticket Guest "0..*" -- "0..*" Ticket Guest "0..*" -- "0..*" Cruise @enduml | K4: A | L4: B | M4: A | N4: A | O4: B | P4: A | Q4: D（平局） | R4: B | S4: A
E5: C04 | F5: House | G5: The address and building material (wood, brick, or concrete) of each house are stored. A house may have a basement, the size and name of which are stored. There are exactly two different types of basements: earth basements and concrete basements. The humidity level of earth basements is also stored. A special type of house is the semi-detached house. Additional information stored for this type of house includes whether it has its own garden and how many windows it has. Each semi-detached house has either two carports or a garage. For carports, information stored includes whether they are double carports and whether they have a flat roof; for garages, information stored includes whether they have an automatic garage door. Each house is serviced by several companies, whose names and addresses are stored. Whenever a company carries out a job in a house, the number of hours and the agreed price are recorded in a job log. | H5: @startuml class House { address: String buildingMaterial: BuildingMaterial } class SemiDetachedHouse { hasGarden: boolean windowCount: int } enum BuildingMaterial { WOOD BRICK CONCRETE } class Basement { name: String size: double } class EarthBasement { humidityLevel: double } class ConcreteBasement { } class ParkingFacility { } class CarportParking { } class GarageParking { } class Carport { isDouble: boolean hasFlatRoof: boolean } class Garage { hasAutomaticDoor: boolean } class Company { name: String address: String } class Job { hours: int agreedPrice: double jobDate: Date } House <|-- SemiDetachedHouse Basement <|-- EarthBasement Basement <|-- ConcreteBasement House *-- "0..1" Basement : basement SemiDetachedHouse *-- "1" ParkingFacility : parkingFacility ParkingFacility <|-- CarportParking ParkingFacility <|-- GarageParking CarportParking *-- "2" Carport : carports GarageParking *-- "1" Garage : garage House "1" -- "1..*" Company : servicingCompanies 'opposite servicedHouses Job --> "1" House : performedAt Job --> "1" Company : performedBy @enduml | I5: @startuml enum BuildingMaterial { WOOD BRICK CONCRETE } class House { address: String buildingMaterial: BuildingMaterial } abstract class Basement { size: float name: String } class EarthBasement { humidityLevel: float } class ConcreteBasement class SemiDetachedHouse { hasOwnGarden: boolean numberOfWindows: int } class Carport { isDouble: boolean hasFlatRoof: boolean } class Garage { hasAutomaticDoor: boolean } class Company { name: String address: String } class JobLog { hours: float price: float } House "1" -- "0..1" Basement Basement <|-- EarthBasement Basement <|-- ConcreteBasement House <|-- SemiDetachedHouse SemiDetachedHouse "1" -- "0..2" Carport SemiDetachedHouse "1" -- "0..1" Garage House "1" -- "*" JobLog Company "1" -- "*" JobLog House "*" -- "*" Company note right of SemiDetachedHouse Has either exactly two Carports or exactly one Garage. end note @enduml | J5: @startuml class House { +address: String +buildingMaterial: String } class Basement { +size: String +name: String } class EarthBasement { +humidityLevel: Float } class ConcreteBasement {} class SemiDetachedHouse { +hasGarden: Boolean +numberOfWindows: Integer } class Carport { +isDouble: Boolean +hasFlatRoof: Boolean } class Garage { +hasAutomaticDoor: Boolean } class Company { +name: String +address: String } class JobLog { +hours: Float +agreedPrice: Float } House <|-- SemiDetachedHouse House o-- Basement Basement <|-- EarthBasement Basement <|-- ConcreteBasement SemiDetachedHouse o-- Carport SemiDetachedHouse o-- Garage House o-- Company Company o-- JobLog @enduml | K5: A | L5: B | M5: A | N5: A | O5: B | P5: A | Q5: B | R5: D（平局） | S5: C
E6: C05 | F6: CelO | G6: Celebrations Organization System The CelO application helps families and groups of friends to organize birthday celebrations and other events. Organizers can keep track of which tasks have been completed and who attends. Attendees can indicate what they are bringing to the event. For a small event, there is typically one organizer, but larger events require several organizers. An organizer provides their first and last name, their email address (which is also used as their username), their postal address, their phone number, and their password. Furthermore, an organizer indicates the kind of event that needs to be planned by selecting from a list of events (e.g., birthday party, graduation party…) or creating a new kind of event. The start date/time and end date/time of the event must be specified as well as the occasion and location of the event. The location can again be selected from a list, or a new one can be created by specifying the name of the location and its address. An organizer then invites the attendees by entering their first and last names as well as their email addresses. Sometimes, an organizer is only managing the event but not attending the event. Sometimes, an organizer also attends the event. When an attendee receives the email invitation, the attendee can create an account (if they do not yet have an account) with a new password and their email address from the invitation as their username. Afterwards, the attendee can indicate whether they will attend the event, maybe will attend the event, or cannot attend the event. An organizer can view the invitation status of an event, e.g., how many attendees have replied or have not yet replied and who is coming for sure or maybe will be coming. When an organizer selects an event, an event-specific checklist is presented to the organizer. For example, a birthday party may have a task to bring a birthday cake. For each task on the checklist, an organizer can indicate that the task needs to be done, has been done, or is not applicable for the event. An organizer can also add new tasks to the list, which will then also be available for the next event. For example, an organizer can add to bring birthday candles to the list for a birthday party and this task will then be available for the next birthday party, too. An organizer can also designate a task on the checklist for attendees to accomplish. For example, an organizer can indicate that the birthday cake should be brought to the event by an attendee. If this is the case, then the list of tasks to be accomplished by attendees is shown to attendees that have confirmed their attendance to the event. An attendee can then select their tasks, so that the organizer can see who is bringing what to the event. | H6: @startuml enum RsvpStatus { PENDING CONFIRMED MAYBE DECLINED } enum TaskStatus { TO_DO DONE NOT_APPLICABLE } class User { firstName: String lastName: String email: String password: String } class Organizer { postalAddress: String phoneNumber: String } class Attendee { } class EventKind { name: String } class Location { name: String address: String } class Event { startDateTime: Date endDateTime: Date occasion: String } class TaskTemplate { description: String } class EventTask { status: TaskStatus isAttendeeDesignated: boolean } class Invitation { rsvpStatus: RsvpStatus } note right of User email serves as username end note User <|-- Organizer User <|-- Attendee EventKind "1" *-- "0..*" TaskTemplate : defines 'opposite eventKind EventKind "1" --> "0..*" Event : categorizes 'opposite kind Event "1" --> "1" Location : heldAt 'opposite hostedEvents Event "1" *-- "0..*" EventTask : schedules 'opposite event Event "1" *-- "0..*" Invitation : issues 'opposite event TaskTemplate "0..*" --> "0..*" EventTask : instantiates 'opposite template Invitation "*" --> "1" Attendee : sentTo 'opposite receivedInvitations Attendee "0..*" --> "0..*" EventTask : volunteersFor 'opposite volunteeredBy Organizer "1..*" --> "1..*" Event : manages 'opposite managedBy @enduml | I6: @startuml enum RsvpStatus { PENDING ATTENDING MAYBE DECLINED } enum TaskStatus { TODO DONE NOT_APPLICABLE } class User { firstName: String lastName: String email: String password: String } class Organizer { postalAddress: String phoneNumber: String } class Attendee { } class Event { startDate: DateTime endDate: DateTime occasion: String } class EventType { name: String } class Location { name: String address: String } class Invitation { invitedEmail: String rsvpStatus: RsvpStatus } class TaskTemplate { description: String } class EventTask { status: TaskStatus isForAttendees: Boolean } User <|-- Organizer User <|-- Attendee Event "1" -- "1..*" Organizer : organized by > Event "1" -- "1" EventType : has type > Event "1" -- "1" Location : held at > Event "1" -- "*" Invitation : has > Invitation "*" -- "0..1" Attendee : claimed by > EventType "1" -- "*" TaskTemplate : defines > Event "1" -- "*" EventTask : tracks > EventTask "*" -- "1" TaskTemplate : instantiates > EventTask "*" -- "0..1" Invitation : assigned to > @enduml | J6: @startuml enum InvitationStatus { Attending Maybe NotAttending NotReplied } enum TaskStatus { NeedsToBeDone HasBeenDone NotApplicable } class Person { firstName: String lastName: String email: String password: String } class Organizer { postalAddress: String phoneNumber: String } class Attendee { } class Event { occasion: String startDateTime: DateTime endDateTime: DateTime } class EventType { name: String } class Location { name: String address: String } class Task { description: String } class Invitation { status: InvitationStatus } class EventTask { status: TaskStatus isForAttendees: boolean } Person <|-- Organizer Person <|-- Attendee Organizer "1..*" organizes "0..*" Event Organizer "0..*" attends "0..*" Event Event *-- "0..*" Invitation Attendee "0..*" receives "0..*" Invitation Event -- "1" EventType Event -- "1" Location EventType *-- "0..*" Task Event *-- "0..*" EventTask EventTask -- "1" Task Attendee "0..*" selects "0..*" EventTask @enduml | K6: B | L6: B | M6: A | N6: B | O6: B | P6: C | Q6: A | R6: B | S6: A
E7: C06 | F7: TileOGame | G7: The Tile-O application first allows a game designer to design a board game and then allows players to play the game. Only one game can be played at a time and it cannot be paused or saved. The objective of the game is to find a hidden tile on the board. Two to four players take turns by moving their playing pieces along connected tiles based on the roll of a die. Each playing piece has a different color. A designer first defines the whole game including the layout of the game board. The designer places the tiles on the board and connects them with connection pieces. A tile can be connected to other tiles on its right side, left side, top side, and bottom side. At the most one tile can be connected on each side. In addition, the designer indicates the hidden tile, the starting positions of each player, as well as the location of action tiles. The designer also defines a deck of 32 action cards by choosing from the following predefined choices: (i) roll the die for an extra turn, (ii) connect two adjacent tiles with a connection piece from the pile of 32 spare connection pieces, (iii) remove a connection piece from the board and place it in the pile of spare connection pieces, (iv) move your playing piece to an arbitrary tile that is not your current tile, and (v) lose your next turn. Players take turns, with Player 1 starting the game, followed by Player 2, Player 3 (if applicable), and Player 4 (if applicable). The player whose turn it is rolls the die and them moves their playing piece along connected tiles. If the player lands on any tile, the color of the tile changes from white to black to indicate that the tile has been visited during the game. If the player lands on the hidden tile, the game ends and the player wins the game. If the player lands on an action tile, the player takes the first action card from the deck of action cards and follows the instructions on the action card. In addition, the action tile turns into a regular tile for a number of turns as specified by the game designer. Players do not know whether a tile is an action tile until a player lands on it. | H7: @startuml enum GameState { SETUP PLAYING FINISHED } enum ActionCardType { EXTRA_TURN CONNECT_TILES REMOVE_CONNECTION MOVE_TO_TILE LOSE_TURN } class Designer { name: String } class Player { name: String turnOrder: int isNextTurnLost: boolean } class PlayingPiece { color: String } class Die { roll(): int } class Game { state: GameState maxPlayers: int spareConnectionPieces: int currentPlayerIndex: int ' Singleton constraint: Only one game can be played at a time } class Board { width: int height: int } class Tile { posX: int posY: int isVisited: boolean isHidden: boolean isStartingPosition: boolean color: String isConnectedRight: boolean isConnectedLeft: boolean isConnectedTop: boolean isConnectedBottom: boolean } class ActionTile { turnsAsRegular: int turnsRemaining: int isRevealed: boolean } class Deck { } class ActionCard { cardType: ActionCardType } Designer --> "1" Game : designs Game "1" *-- "1" Board : board Game "1" *-- "1" Deck : deck Game "1" *-- "2..4" Player : players Game --> "1" Player : currentPlayer Game --> "0..1" Player : winner Game "1" *-- "1" Die : die Board "1" *-- "1..*" Tile : tiles Player "1" *-- "1" PlayingPiece : playingPiece Player --> "1" Tile : startingTile Player --> "1" Tile : currentTile Tile --> "0..1" Tile : rightTile 'opposite leftTile Tile --> "0..1" Tile : leftTile 'opposite rightTile Tile --> "0..1" Tile : topTile 'opposite bottomTile Tile --> "0..1" Tile : bottomTile 'opposite topTile Tile <|-- ActionTile Deck "1" *-- "32" ActionCard : cards @enduml | I7: @startuml enum Side { LEFT RIGHT TOP BOTTOM } enum TileColor { WHITE BLACK } enum PlayingPieceColor { RED BLUE GREEN YELLOW } enum ActionCardType { ROLL_EXTRA_TURN CONNECT_TILES REMOVE_CONNECTION MOVE_TO_ARBITRARY_TILE LOSE_TURN } class Game { - currentPlayer : Player - isGameEnded : boolean - winner : Player + startGame() : void + endGame(winner : Player) : void + nextTurn() : void + rollDie() : int } class GameDesigner { - name : String + designBoard() : void + placeTile(tile : Tile) : void + connectTiles(tile1 : Tile, tile2 : Tile, side : Side) : void + setHiddenTile(tile : Tile) : void + setStartingPosition(player : Player, tile : Tile) : void + setActionTile(tile : Tile) : void + defineActionDeck() : void } class Player { - name : String - currentTile : Tile - skippedTurns : int - playerNumber : int + move(steps : int) : void + executeActionCard(card : ActionCard) : void + skipTurn() : void } class PlayingPiece { - color : PlayingPieceColor + getColor() : PlayingPieceColor } class GameBoard { - width : int - height : int + addTile(tile : Tile, x : int, y : int) : void + removeTile(tile : Tile) : void + addConnection(connection : ConnectionPiece) : void + removeConnection(connection : ConnectionPiece) : void } abstract class Tile { - color : TileColor - x : int - y : int + markVisited() : void + isVisited() : boolean } class RegularTile { } class ActionTile { - cooldownTurns : int - currentCooldown : int + triggerAction() : void + decreaseCooldown() : void } class HiddenTile { + isFound() : boolean } class ConnectionPiece { - side1 : Side - side2 : Side + connect(tile1 : Tile, tile2 : Tile) : void + disconnect() : void } class ActionCard { - type : ActionCardType + execute(player : Player) : void } class Deck { - cards : ActionCard[] - cardsRemaining : int + drawCard() : ActionCard + shuffle() : void } class ConnectionPiecePile { - sparePieces : ConnectionPiece[] - piecesRemaining : int + takePiece() : ConnectionPiece + returnPiece(piece : ConnectionPiece) : void } class Die { - currentValue : int + roll() : int + getValue() : int } Game *-- GameBoard : has Game *-- Deck : has Game *-- ConnectionPiecePile : has Game *-- Die : has Game o--> GameDesigner : designed by Game --> Player : has players Game --> Player : current player Game --> Player : winner Player *- PlayingPiece : owns Player --> Tile : current tile GameBoard *- Tile : contains GameBoard *- ConnectionPiece : contains ConnectionPiece --> Tile : connects ConnectionPiece --> Tile : connects Deck *- ActionCard : contains ConnectionPiecePile *- ConnectionPiece : contains Tile <|-- RegularTile Tile <|-- ActionTile Tile <|-- HiddenTile @enduml | J7: @startuml enum GameState { DESIGNING PLAYING ENDED } enum TileColor { WHITE BLACK } enum Direction { RIGHT LEFT TOP BOTTOM } enum PieceColor { RED BLUE GREEN YELLOW } class Game { state: GameState turnNumber: int spareConnectionPieces: int start() endGame(winner: Player) nextTurn() } class GameDesigner { name: String } class Board { } class Tile { color: TileColor x: int y: int markVisited() isVisited(): boolean } class RegularTile class HiddenTile class ActionTile { cooldownTurns: int remainingCooldown: int isActive(): boolean deactivate() tickCooldown() } class ConnectionPiece class Player { name: String order: int skipNextTurn: boolean } class PlayingPiece { color: PieceColor } class Deck { drawCard(): ActionCard isEmpty(): boolean } abstract class ActionCard { execute(game: Game, player: Player) } class ExtraTurnCard class ConnectTilesCard class RemoveConnectionCard class MoveToTileCard class LoseTurnCard class Die { roll(): int } Game "1" *-- "1" Board : board Game "1" *-- "1" Deck : deck Game "1" *-- "1" Die : die Game "1" o-- "2..4" Player : players Game "1" --> "0..1" Player : currentPlayer Game "1" --> "1" GameDesigner : designedBy Board "1" *-- "1..*" Tile : tiles Board "1" --> "1" HiddenTile : hiddenTile Tile <|-- RegularTile Tile <|-- HiddenTile Tile <|-- ActionTile Tile "1" o-- "0..1" ConnectionPiece : rightConnection Tile "1" o-- "0..1" ConnectionPiece : leftConnection Tile "1" o-- "0..1" ConnectionPiece : topConnection Tile "1" o-- "0..1" ConnectionPiece : bottomConnection ConnectionPiece --> "2" Tile : connects Player "1" *-- "1" PlayingPiece : playingPiece Player --> "1" Tile : startingPosition PlayingPiece --> "1" Tile : currentTile Deck "1" *-- "32" ActionCard : cards ActionCard <|-- ExtraTurnCard ActionCard <|-- ConnectTilesCard ActionCard <|-- RemoveConnectionCard ActionCard <|-- MoveToTileCard ActionCard <|-- LoseTurnCard @enduml | K7: A | L7: C | M7: C | N7: A | O7: C | P7: C | Q7: B | R7: C | S7: C
E8: C07 | F8: SellingGoods | G8: This exercise teaches you to build and re-evaluate your solution in an iterative manner to handle changing requirements. First, create a class diagram for the use case described in STEP 1, and add attributes, event types, non-default FSMs and constraints if necessary. For each step, revise your model and add, remove or change elments where necessary. STEP 1 Your brand new company sells goods to local supermarkets. You want to create a simple information system to keep track of your stock, your customers and their orders. When you register a new customer, you enter their address and VAT number. To keep track of your stock, you want to be able to register the products you offer and the current stock of each product. Your customers' orders consist of one or more order lines, with each order line recording the quantity ordered of a particular product. To minimise the overhead of managing payments and deliveries for your small business, your customers are required to pay for their order in full before it is sent out for delivery. Similarly, orders are always shipped in their entirety to keep shipping simple. To ensure that you have the information you need for your accounts, you want to record when orders are paid for and shipped. At the end of each working day, you manually adjust the stock levels of your products in the system based on the orders placed that day. STEP 2 As your business grows, you start to offer more exclusive products that are not always available. To ensure customer satisfaction, you want to start organising deliveries on a line-by-line basis so that available products can be shipped immediately and unavailable products can be shipped later. Of course, you need to adapt your information system to keep track of partially shipped orders so that you can record which order lines have been shipped and which are still on the to-be-shipped list. Orders that have been fully shipped will also be marked so that you know that they can be removed from your watchlist. STEP 3 As your products become more popular, you start supplying larger supermarkets. These supermarkets sometimes have several warehouses that they use for different locations. You want to start keeping track of both the customer's head office address and the addresses where the orders are delivered. To further professionalise your business, you want to send invoices to your customers for their orders. Customers can now choose to pay the invoice directly when they place the order, or after the order has been delivered. An order should still be paid in full. STEP 4 As your business grows, keeping track of shipments on a line-by-line basis becomes too cumbersome. You would prefer to do this for each group of order lines that are shipped together. In addition, you have recently noticed some problems with the delivery service you use, as customers have informed you that some deliveries are missing or damaged. You want to gather more information about the deliveries in order to decide whether you should switch to another delivery service or start delivering yourself. To do this, you want to know the status of each delivery (remember that partial deliveries of one or more order lines are possible). You want to track a shipment as it is packed, shipped and received by the customer. | H8: @startuml skinparam classAttributeIconSize 0 class Address { - street : String - city : String - postalCode : String - country : String } class Customer { - customerId : String - name : String - vatNumber : String - headOfficeAddress : Address + register() + placeOrder() } class Warehouse { - warehouseId : String - address : Address } class Product { - productId : String - name : String - description : String - price : Money - currentStock : Integer + adjustStock(quantity : Integer) } class Order { - orderId : String - orderDate : Date - paidDate : Date - status : OrderStatus + markPaid() + markFullyShipped() } class OrderLine { - lineId : String - quantity : Integer - unitPrice : Money } class Invoice { - invoiceId : String - invoiceNumber : String - issueDate : Date - paidDate : Date - totalAmount : Money + sendToCustomer() } class Shipment { - shipmentId : String - shipmentDate : Date - receivedDate : Date - status : ShipmentStatus - trackingNumber : String + pack() + ship() + markReceived() } enum OrderStatus { PLACED PAID PARTIALLY_SHIPPED FULLY_SHIPPED } enum ShipmentStatus { PACKED SHIPPED RECEIVED } Customer "1" -- "1" Address : head office > Customer "1" *-- "0..*" Warehouse : operates > Warehouse "1" -- "1" Address : located at > Customer "1" *-- "0..*" Order : places > Order "1" -- "1" Warehouse : delivers to > Order "1" *-- "1" Invoice : generates > Order "1" *-- "1..*" OrderLine : contains > OrderLine "*" -- "1" Product : refers to > Order "1" *-- "0..*" Shipment : ships > Shipment "1" o-- "1..*" OrderLine : groups > @enduml | I8: @startuml enum PaymentTiming { ON_ORDER ON_DELIVERY } enum PaymentStatus { UNPAID PAID } enum ShipmentStatus { PACKED SHIPPED RECEIVED MISSING DAMAGED } class Customer { vatNumber: String } class Address { street: String city: String postalCode: String } class Product { name: String currentStock: Integer } class Order { orderDate: Date paymentStatus: PaymentStatus paymentTiming: PaymentTiming } class OrderLine { orderedQuantity: Integer shippedQuantity: Integer } class Invoice { invoiceDate: Date totalAmount: Decimal isPaid: Boolean } class Shipment { shipmentDate: Date status: ShipmentStatus } class ShipmentLine { shippedQuantity: Integer } Customer "1" -- "1" Address : headOffice Customer "1" -- "0..*" Address : deliveryWarehouses Customer "1" -- "0..*" Order : places Order "1" -- "1" Address : deliveredTo Order "1" -- "1..*" OrderLine : contains Order "1" -- "0..1" Invoice : has Order "1" -- "0..*" Shipment : fulfilledBy OrderLine "0..*" -- "1" Product : refersTo Shipment "1" -- "1..*" ShipmentLine : contains ShipmentLine "0..*" -- "1" OrderLine : refersTo @enduml | J8: @startuml class Company { name: String } class Customer { vatNumber: String } class DeliveryAddress { address: String } class Product { name: String currentStock: int } class Order { orderDate: Date paymentStatus: PaymentStatus paymentMethod: PaymentMethod shippingStatus: ShippingStatus } class OrderLine { quantityOrdered: int } class Invoice { invoiceNumber: String issueDate: Date totalAmount: double } class Shipment { trackingNumber: String shipmentDate: Date status: ShipmentStatus } class Delivery { deliveryDate: Date conditionNotes: String status: DeliveryStatus } enum PaymentStatus { PENDING PAID } enum ShippingStatus { NOT_SHIPPED PARTIALLY_SHIPPED FULLY_SHIPPED } enum DeliveryStatus { PACKED SHIPPED RECEIVED DAMAGED MISSING } enum ShipmentStatus { PACKED SHIPPED RECEIVED } enum PaymentMethod { DIRECT POST_DELIVERY } Company "1" --> "*" Customer : registers 'opposite company Company "1" --> "*" Product : stocks 'opposite company Customer "1" --> "*" DeliveryAddress : hasWarehouses 'opposite customer Customer "1" --> "*" Order : places 'opposite customer Customer "1" --> "1" DeliveryAddress : headOfficeAddress 'opposite headOfficeCustomer Order "1" --> "1" DeliveryAddress : deliveredTo 'opposite deliveryOrder Order "1" --> "*" OrderLine : consistsOf 'opposite order Order "1" --> "1" Invoice : hasInvoice 'opposite order Invoice "*" --> "1" Customer : issuedTo 'opposite invoices OrderLine "*" --> "1" Product : references 'opposite orderLines Shipment "1" --> "*" Delivery : trackedAs 'opposite shipment Shipment "1" --> "*" OrderLine : ships 'opposite shipment Delivery "*" --> "*" OrderLine : deliversTo 'opposite deliveredIn Order "1" --> "*" Shipment : fulfilledBy 'opposite order @enduml | K8: D（平局） | L8: B | M8: A | N8: B | O8: B | P8: A | Q8: D（平局） | R8: B | S8: A
E9: C08 | F9: University | G9: A university consists of several faculties, which are made up of various institutes. Each faculty and institute has a name. The address of each institute is known. Each faculty is headed by a dean, who is an employee of the university. The total number of employees is known. Employees have a social security number, a name, and an email address. A distinction is made between research and administrative staff. Research assistants (RA) are assigned to at least one institute. The field of research of each RA is known. In addition, RAs can be involved in projects for a certain number of hours, whereby the name, start and end dates of the projects are known. Some RAs teach courses. In this case, they are referred to as lecturers. Courses have a unique number (ID), a name and a weekly duration in hours. | H9: @startuml class University { name : String totalEmployees : int } class Faculty { name : String } class Institute { name : String address : String } University *-- "1..*" Faculty : faculties Faculty *-- "1..*" Institute : institutes class Employee { socialSecurityNumber : String name : String email : String } class ResearchStaff { } class AdministrativeStaff { } class ResearchAssistant { fieldOfResearch : String } class Lecturer { } Employee <|-- ResearchStaff Employee <|-- AdministrativeStaff ResearchStaff <|-- ResearchAssistant ResearchAssistant <|-- Lecturer class Project { name : String startDate : Date endDate : Date } class ProjectInvolvement { hours : int } class Course { id : int name : String weeklyDurationHours : double } Faculty --> "1" Employee : dean 'opposite headedFaculty Employee --> "0..1" Faculty : headedFaculty 'opposite dean ResearchAssistant --> "1..*" Institute : assignedInstitutes 'opposite researchAssistants Institute --> "*" ResearchAssistant : researchAssistants 'opposite assignedInstitutes ResearchAssistant --> "0..*" ProjectInvolvement : involvements 'opposite researchAssistant ProjectInvolvement --> "1" Project : project 'opposite involvements Lecturer --> "0..*" Course : taughtCourses 'opposite lecturers Course --> "*" Lecturer : lecturers 'opposite taughtCourses University --> "*" Employee : employees 'opposite university Employee --> "1" University : university 'opposite employees @enduml | I9: @startuml class University { - totalEmployees : int } class Faculty { - name : String } class Institute { - name : String - address : String } class Employee { - socialSecurityNumber : String - name : String - email : String } class AdministrativeStaff { } class ResearchStaff { - fieldOfResearch : String } class Lecturer { } class Project { - name : String - startDate : Date - endDate : Date } class Course { - id : String - name : String - weeklyDurationHours : int } University "1" *-- "many" Faculty : contains Faculty "1" *-- "many" Institute : contains Faculty "1" --> "1" Employee : has dean Employee <|-- AdministrativeStaff Employee <|-- ResearchStaff ResearchStaff <|-- Lecturer ResearchStaff "many" --> "1..*" Institute : assigned to ResearchStaff "many" --> "0..*" Project : involved in (hours : int) Lecturer "many" --> "0..*" Course : teaches @enduml | J9: @startuml class University { totalEmployees : int } class Faculty { name : String } class Institute { name : String } class Address { street : String city : String zipCode : String } abstract class Employee { socialSecurityNumber : String name : String email : String } class AdministrativeStaff class ResearchStaff class ResearchAssistant { fieldOfResearch : String } class Lecturer class Project { name : String startDate : Date endDate : Date } class Course { id : String name : String weeklyDurationHours : int } class ProjectInvolvement { hours : int } University "1" *-- "0..*" Faculty Faculty "1" *-- "0..*" Institute Faculty "1" --> "1" Employee : dean Institute "1" *-- "1" Address Employee <|-- AdministrativeStaff Employee <|-- ResearchStaff ResearchStaff <|-- ResearchAssistant ResearchAssistant <|-- Lecturer ResearchAssistant "1..*" -- "0..*" Institute : assigned to ResearchAssistant "0..*" -- "0..*" ProjectInvolvement Project "1" -- "0..*" ProjectInvolvement Lecturer "0..*" -- "0..*" Course : teaches @enduml | K9: A | L9: C | M9: D（平局） | N9: A | O9: C | P9: A | Q9: A | R9: C | S9: D（平局）
E10: C09 | F10: TeamSportsScoutingSystem | G10: The Team Sports Scouting System is used by various employees of the club, including the head coach, the director of the club and the scouts. It is the role of the head coach to identify designated player profiles for future signings, which includes designated target positions for a player (e.g. GK for goalkeeper, LB for left back, etc.), and other player attributes (identified by a name and a value). Scouts may note players on a long list who seem to match a designated target profile at any time. This long list is periodically evaluated by the head scout when setting up scouting assignments for his team to investigate a specific player more thoroughly. As the completion of a scouting assignment, the scout submits a scouting report about the player, which includes the pros and cons of the player as well as a recommendation (e.g. key player, first team player, reserve team player, prospective player, not a good signing). After comparing first scouting results for a designated player profile, the head coach and the head scout decide upon which players to move to the short list. Several other rounds of scouting can be carried out for each short-listed player as part of scouting assignments – some of which is carried out by the head scout himself. If a player is finally recommended for signing by the head scout, the director makes an official offer for the player. | H10: @startuml enum Position { GK CB LB RB CDM CM CAM LW RW ST } enum Recommendation { KEY_PLAYER FIRST_TEAM RESERVE_TEAM PROSPECTIVE NOT_GOOD_SIGNING } enum ScoutingState { LONG_LIST UNDER_INVESTIGATION SHORT_LIST RECOMMENDED OFFER_MADE } class Employee { employeeId: int name: String } class HeadCoach { } class Director { } class Scout { } class HeadScout { } class Player { playerId: int name: String currentClub: String } class TargetProfile { profileId: int name: String targetPositions: List<Position> } class Attribute { name: String value: String } class LongListEntry { entryId: int entryDate: Date notes: String } class ScoutingAssignment { assignmentId: int description: String assignmentDate: Date deadline: Date } class ScoutingReport { reportId: int pros: String cons: String recommendation: Recommendation submissionDate: Date } class ScoutingRecord { currentState: ScoutingState } class Offer { offerId: int amount: double offerDate: Date status: String } Employee <|-- HeadCoach Employee <|-- Director Employee <|-- Scout Scout <|-- HeadScout HeadCoach --> "*" TargetProfile: defines TargetProfile *-- "*" Attribute: attributes Scout --> "*" LongListEntry: logs LongListEntry --> "1" Player: player LongListEntry --> "1" TargetProfile: matchedProfile ScoutingRecord --> "*" LongListEntry: initialEntries ScoutingRecord --> "*" ScoutingAssignment: assignments ScoutingAssignment --> "1" Player: assignedPlayer ScoutingAssignment --> "1" Scout: assignedScout Scout --> "*" ScoutingReport: submits ScoutingAssignment --> "1" ScoutingReport: produces ScoutingReport --> "1" ScoutingAssignment: fulfills 'opposite produces HeadCoach --> "*" ScoutingRecord: manages HeadScout --> "*" ScoutingRecord: evaluates ScoutingRecord --> "1" Player: tracks ScoutingRecord --> "1" TargetProfile: alignedWith Director --> "*" Offer: makes Offer --> "1" Player: offeredPlayer Offer --> "1" ScoutingRecord: basedOn @enduml | I10: @startuml enum Recommendation { KEY_PLAYER FIRST_TEAM_PLAYER RESERVE_TEAM_PLAYER PROSPECTIVE_PLAYER NOT_A_GOOD_SIGNING } enum AssignmentStatus { PENDING IN_PROGRESS COMPLETED } class Employee { + id: UUID + name: String } class HeadCoach class Director class Scout class HeadScout Employee <|-- HeadCoach Employee <|-- Director Employee <|-- Scout Scout <|-- HeadScout class TargetProfile { + id: UUID + description: String } class TargetPosition { + code: String + name: String } class ProfileAttribute { + name: String + value: String } class Player { + id: UUID + name: String + currentClub: String } class LongListEntry { + dateAdded: Date + notes: String } class ShortListEntry { + dateAdded: Date } class ScoutingAssignment { + id: UUID + status: AssignmentStatus + deadline: Date } class ScoutingReport { + id: UUID + pros: String + cons: String + recommendation: Recommendation } class ContractOffer { + id: UUID + amount: Decimal + date: Date } HeadCoach "1" -- "0..*" TargetProfile : identifies > TargetProfile "1" -- "1..*" TargetPosition : targets > TargetProfile "1" -- "0..*" ProfileAttribute : defines > Scout "1" -- "0..*" LongListEntry : creates > LongListEntry "0..*" -- "1" Player : evaluates > LongListEntry "0..*" -- "1" TargetProfile : matches > HeadScout "1" -- "0..*" ScoutingAssignment : creates > ScoutingAssignment "0..*" -- "1" Scout : assigned to > ScoutingAssignment "0..*" -- "1" Player : investigates > Scout "1" -- "0..*" ScoutingReport : submits > ScoutingReport "1" -- "1" ScoutingAssignment : completes > HeadCoach "1" -- "0..*" ShortListEntry : approves > HeadScout "1" -- "0..*" ShortListEntry : approves > ShortListEntry "0..*" -- "1" Player : includes > ShortListEntry "0..*" -- "1" TargetProfile : fulfills > Director "1" -- "0..*" ContractOffer : makes > ContractOffer "0..*" -- "1" Player : offered to > @enduml | J10: @startuml class Team { + name : String } class Employee { + name : String + role : String } class Player { + id : String + name : String + targetPosition : String + playerStatus : String } class PlayerProfile { + targetPosition : String + playerAttributes : List<Attribute> } class Attribute { + name : String + value : String } class Scout { + name : String } class ScoutingAssignment { + assignmentDate : Date + status : String + shortList : List<Player> + scoutingResults : List<String> } class ScoutingReport { + pros : List<String> + cons : List<String> + recommendation : String + decision : String + relatedAssignment : ScoutingAssignment } class Director { + name : String } class HeadCoach { + name : String } class HeadScout { + name : String } Team --> "*" Employee : employs Employee --|> HeadCoach Employee --|> Director Employee --|> Scout Employee --|> HeadScout HeadCoach --> "*" PlayerProfile : identifies Scout --> "*" Player : notes HeadScout --> "*" ScoutingAssignment : evaluates Scout --> "*" ScoutingReport : submits HeadCoach --> "*" PlayerProfile : decides HeadScout --> "*" PlayerProfile : recommends Director --> "*" Player : makesOffer ScoutingAssignment --> "*" PlayerProfile : investigates ScoutingReport --> "1" relatedAssignment : linkedAssignment ScoutingReport --> "1" PlayerProfile : reportsOn PlayerProfile --> "*" Player : profiles PlayerProfile --> "*" Attribute : hasAttributes @enduml | K10: B | L10: B | M10: A | N10: B | O10: B | P10: A | Q10: D（平局） | R10: B | S10: A
E11: C10 | F11: AirTrafficControlNavigationSystem | G11: The Air Traffic Control and Navigation System manages the complete lifecycle of flight operations, airspace monitoring, and ground infrastructure. The system tracks specific flight instances, identified by flight number, airline code, departure city, scheduled time, and current operational status derived from an associated aircraft status record. This aircraft status record contains the registration number, operational state, and system health score. Each flight instance is assigned a crew of members, defined by employee ID, name, certification status, and role. Crew members can verify their certification, maintain flight logs, access specific airport terminals, and report maintenance issues. Every flight instance is linked to a passenger manifest indicating the total count of passengers and generates event logs detailing descriptions, timestamps, and severity levels. Additionally, each flight instance is associated with a specific departure terminal. Flight operations rely on detailed flight plans that specify altitude levels and required clearance levels (Ground or Tower). A flight plan calculates altitude based on emergency status and verifies clearance validity. Each plan defines the specific flight instance it governs and is composed of multiple route segments, defined by distance and estimated time. Each route segment connects exactly two waypoints using geographic coordinates. Both route segments and flight plans are influenced by weather reports, which document condition types (Clear, Cloudy, Storm, Fog), visibility, wind speed, timestamps, and location codes. Waypoints may reference various navigation aids, such as VOR or ILS systems, characterized by their type, frequency, and location coordinates. The system manages airspace sectors divided into altitude floors and ceilings, which contain multiple sub-sectors. These sectors manage specific runways and are equipped with navigation aids. Runways are described by an identifier, dimensions (length and width), surface type, and the ability to allocate based on request time. Each runway is controlled by a specific control tower located at a designated site. Airport terminals provide access to these runways and have a defined gate count. Control towers employ air traffic controllers, who are identified by name, duty status, and assigned clearance level. Controllers can determine their availability, authorize maneuvers based on clearance type, and generate clearance messages for flight plans they monitor. Each controller utilizes a system dashboard and a communication channel. The dashboard supports different display modes, allows data refreshing, and displays alerts; it integrates data from radar systems and displays real-time traffic for all flight instances. Radar systems, characterized by scan range, resolution, and active status, process scan data to monitor specific airspace sectors. Communication channels, defined by frequency band and encryption status, establish connections and are housed within control towers. Maintenance records track descriptions, dates, criticality, and target components for both aircraft statuses and runways. Finally, flight logs record events related to specific flight instances, ensuring a comprehensive history of operational activities, with specific logs maintained by crew members. | H11: @startuml ' ===== Enumerations ===== enum OperationalState { SCHEDULED BOARDING TAXIING AIRBORNE LANDED EMERGENCY } enum CrewRole { CAPTAIN FIRST_OFFICER FLIGHT_ATTENDANT ENGINEER } enum ClearanceLevel { GROUND TOWER } enum WeatherConditionType { CLEAR CLOUDY STORM FOG } enum NavAidType { VOR ILS } enum SurfaceType { ASPHALT CONCRETE GRASS } enum SeverityLevel { LOW MEDIUM HIGH CRITICAL } enum Criticality { MINOR MODERATE MAJOR SEVERE } enum DutyStatus { ON_DUTY OFF_DUTY ON_BREAK } enum DisplayMode { RADAR_SWEEP TOPOGRAPHICAL TRAFFIC_DENSITY } ' ===== Flight Domain ===== class FlightInstance { -flightNumber: String -airlineCode: String -departureCity: String -scheduledTime: Date } class AircraftStatus { -registrationNumber: String -operationalState: OperationalState -systemHealthScore: double } class CrewMember { -employeeId: String -name: String -certificationStatus: boolean -role: CrewRole +verifyCertification(): boolean +maintainFlightLog(): void +accessTerminal(terminal: AirportTerminal): void +reportMaintenanceIssue(): void } class PassengerManifest { -totalCount: int } class EventLog { -description: String -timestamp: Date -severity: SeverityLevel } class FlightLog { -entryDate: Date -eventDescription: String } class FlightPlan { -altitudeLevel: double -clearanceLevel: ClearanceLevel +computeAltitudeAdjustment(emergencyStatus: boolean): double +verifyClearanceValidity(): boolean } class RouteSegment { -distance: double -estimatedTime: double } class Waypoint { -name: String -latitude: double -longitude: double } class WeatherReport { -conditionType: WeatherConditionType -visibility: double -windSpeed: double -timestamp: Date -locationCode: String } class NavigationAid { -aidType: NavAidType -frequency: double -latitude: double -longitude: double } class AirportTerminal { -name: String -gateCount: int } ' ===== Airspace Domain ===== class AirspaceSector { -altitudeFloor: double -altitudeCeiling: double } class SubSector { -sectorCode: String } class Runway { -identifier: String -length: double -width: double -surfaceType: SurfaceType +allocate(requestTime: Date): boolean } class ControlTower { -site: String -name: String } ' ===== ATC Personnel Domain ===== class AirTrafficController { -name: String -dutyStatus: DutyStatus -clearanceLevel: ClearanceLevel +determineAvailability(): boolean +authorizeManeuver(clearanceLevel: ClearanceLevel): boolean +generateClearanceMessage(flightPlan: FlightPlan): String } class ControllerDashboard { -displayMode: DisplayMode -alertsActive: boolean +setDisplayMode(mode: DisplayMode): void +refreshData(): void +displayAlert(): void } class RadarSystem { -scanRange: double -resolution: double -activeStatus: boolean +processScanData(): void } class CommunicationChannel { -frequencyBand: double -encryptionStatus: boolean +establishConnection(): boolean } ' ===== Maintenance Domain ===== class MaintenanceRecord { -description: String -date: Date -criticality: Criticality -targetComponent: String } ' ===== Relationships ===== ' -- Flight Instance -- FlightInstance --> "1" AircraftStatus : aircraftStatus FlightInstance --> "1..*" CrewMember : assignedCrew FlightInstance --> "1" PassengerManifest : passengerManifest FlightInstance --> "0..*" EventLog : eventLogs FlightInstance --> "1" AirportTerminal : departureTerminal FlightInstance --> "1" FlightPlan : flightPlan 'opposite governs FlightInstance --> "0..*" FlightLog : flightLogs ' -- Aircraft Status -- AircraftStatus --> "0..*" MaintenanceRecord : maintenanceRecords ' -- Crew Member -- CrewMember --> "0..*" FlightLog : authoredLogs CrewMember --> "0..*" AirportTerminal : accessibleTerminals CrewMember --> "0..*" MaintenanceRecord : reportedMaintenance ' -- Flight Plan -- FlightPlan *-- "1..*" RouteSegment : routeSegments FlightPlan --> "0..*" WeatherReport : planWeatherInfluences FlightPlan --> "1" FlightInstance : governs 'opposite flightPlan ' -- Route Segment -- RouteSegment --> "2" Waypoint : connectedWaypoints RouteSegment --> "0..*" WeatherReport : segmentWeatherInfluences ' -- Waypoint -- Waypoint --> "0..*" NavigationAid : referencedNavAids ' -- Airspace Composite -- AirspaceSector *-- "0..*" SubSector : subSectors ' -- Sector to Infrastructure -- AirspaceSector --> "0..*" Runway : managedRunways AirspaceSector --> "0..*" NavigationAid : equippedNavAids ' -- Runway -- Runway --> "1" ControlTower : controlledBy Runway --> "0..*" MaintenanceRecord : maintenanceRecords ' -- Control Tower -- ControlTower --> "1..*" AirTrafficController : employedControllers ControlTower --> "1..*" CommunicationChannel : housedChannels ' -- Air Traffic Controller -- AirTrafficController --> "1" ControllerDashboard : utilizesDashboard AirTrafficController --> "1" CommunicationChannel : utilizesChannel AirTrafficController --> "0..*" FlightPlan : monitoredFlightPlans ' -- Controller Dashboard -- ControllerDashboard --> "0..*" RadarSystem : integratedRadarData ControllerDashboard --> "0..*" FlightInstance : displayedTraffic ' -- Radar System -- RadarSystem --> "1" AirspaceSector : monitoredSector ' -- Terminal to Runway -- AirportTerminal --> "0..*" Runway : providesAccessTo @enduml | I11: @startuml enum ClearanceLevel { Ground Tower } enum ConditionType { Clear Cloudy Storm Fog } enum NavAidType { VOR ILS } class FlightInstance { flightNumber: String airlineCode: String departureCity: String scheduledTime: DateTime operationalStatus: String } class AircraftStatus { registrationNumber: String operationalState: String systemHealthScore: int } class CrewMember { employeeId: String name: String certificationStatus: String role: String verifyCertification() maintainFlightLog() accessTerminal() reportMaintenanceIssue() } class PassengerManifest { totalPassengerCount: int } class EventLog { description: String timestamp: DateTime severityLevel: String } class FlightPlan { altitudeLevels: String requiredClearanceLevel: ClearanceLevel calculateAltitude(emergencyStatus: boolean) verifyClearanceValidity() } class RouteSegment { distance: float estimatedTime: float } class Waypoint { geographicCoordinates: String } class NavigationAid { type: NavAidType frequency: float locationCoordinates: String } class WeatherReport { conditionType: ConditionType visibility: float windSpeed: float timestamp: DateTime locationCode: String } class AirspaceSector { altitudeFloor: float altitudeCeiling: float } class Runway { identifier: String length: float width: float surfaceType: String allocate(requestTime: DateTime) } class AirportTerminal { gateCount: int provideAccessToRunway() } class ControlTower { designatedSite: String } class AirTrafficController { name: String dutyStatus: String assignedClearanceLevel: ClearanceLevel determineAvailability() authorizeManeuver(clearanceType: String) generateClearanceMessage(flightPlan: FlightPlan) } class SystemDashboard { displayMode: String refreshData() displayAlerts() } class RadarSystem { scanRange: float resolution: float activeStatus: boolean processScanData() } class CommunicationChannel { frequencyBand: String encryptionStatus: boolean establishConnection() } class MaintenanceRecord { description: String date: DateTime criticality: String targetComponent: String } class FlightLog { eventDetails: String timestamp: DateTime } FlightInstance "1" --> "1" AircraftStatus : derives status from FlightInstance "1" --> "1" PassengerManifest : linked to FlightInstance "1" --> "*" EventLog : generates FlightInstance "*" --> "1" AirportTerminal : departs from FlightInstance "1" --> "1" FlightPlan : governed by FlightInstance "1" --> "*" FlightLog : records FlightInstance "*" --> "*" CrewMember : assigned CrewMember "1" --> "*" FlightLog : maintains FlightPlan "1" --> "*" RouteSegment : composed of FlightPlan "*" --> "*" WeatherReport : influenced by FlightPlan "*" --> "*" AirTrafficController : monitored by RouteSegment "1" --> "1" Waypoint : startWaypoint RouteSegment "1" --> "1" Waypoint : endWaypoint RouteSegment "*" --> "*" WeatherReport : influenced by Waypoint "*" --> "*" NavigationAid : references AirspaceSector "1" --> "0..*" AirspaceSector : contains sub-sectors AirspaceSector "1" --> "*" Runway : manages AirspaceSector "1" --> "*" NavigationAid : equipped with AirspaceSector "*" --> "*" RadarSystem : monitored by Runway "*" --> "1" ControlTower : controlled by Runway "*" --> "*" AirportTerminal : accessed by Runway "1" --> "*" MaintenanceRecord : tracked by ControlTower "1" --> "*" AirTrafficController : employs ControlTower "1" --> "*" CommunicationChannel : houses AirTrafficController "1" --> "1" SystemDashboard : utilizes AirTrafficController "1" --> "1" CommunicationChannel : utilizes SystemDashboard "*" --> "*" RadarSystem : integrates data from SystemDashboard "*" --> "*" FlightInstance : displays real-time traffic for AircraftStatus "1" --> "*" MaintenanceRecord : tracked by @enduml | J11: @startuml class FlightInstance { - flightNumber: String - airlineCode: String - departureCity: String - scheduledTime: Date - operationalStatus: String } class AircraftStatusRecord { - registrationNumber: String - operationalState: String - systemHealthScore: Integer } class CrewMember { - employeeID: String - name: String - certificationStatus: Boolean - role: String + verifyCertification() + maintainFlightLogs() + accessAirportTerminals() + reportMaintenanceIssues() } class PassengerManifest { - totalCount: Integer } class EventLog { - description: String - timestamp: Date - severityLevel: String } class FlightPlan { - altitudeLevel: String - clearanceLevel: String + calculateAltitude() + verifyClearanceValidity() } class RouteSegment { - distance: Double - estimatedTime: Double } class Waypoint { - type: String - frequency: String - locationCoordinates: String } class WeatherReport { - conditionType: String - visibility: Double - windSpeed: Double - timestamp: Date - locationCode: String } class AirspaceSector { - altitudeFloor: Integer - altitudeCeiling: Integer } class Runway { - identifier: String - length: Double - width: Double - surfaceType: String + allocateRunway() } class ControlTower { - location: String } class AirTrafficController { - name: String - dutyStatus: String - clearanceLevel: String + determineAvailability() + authorizeManeuvers() + generateClearanceMessages() } class Dashboard { + refreshData() + displayAlerts() } class RadarSystem { - scanRange: Double - resolution: String - activeStatus: Boolean } class CommunicationChannel { - frequencyBand: String - encryptionStatus: Boolean } class MaintenanceRecord { - description: String - date: Date - criticality: String - targetComponent: String } class FlightLog { - eventDetails: String } FlightInstance -- RoomMaster FlightInstance *-- AircraftStatusRecord FlightInstance *-- CrewMember FlightInstance *-- PassengerManifest FlightInstance *-- EventLog FlightInstance *-- FlightPlan FlightPlan *-- RouteSegment RouteSegment -- Waypoint FlightInstance *-- WeatherReport AirspaceSector *-- Runway Runway -- ControlTower ControlTower *-- AirTrafficController AirTrafficController *-- Dashboard Dashboard *-- RadarSystem ControlTower *-- CommunicationChannel MaintenanceRecord -- AircraftStatusRecord MaintenanceRecord -- Runway FlightLog -- CrewMember @enduml | K11: D（平局） | L11: B | M11: A | N11: A | O11: B | P11: A | Q11: D（平局） | R11: B | S11: A
E12: C11 | F12: AI-AssistedDrugDiscoveryPlatform | G12: The AI-Assisted Drug Discovery Platform supports the end-to-end development of new medicines, managed by researchers from various institutions who lead specific research projects. Each project encompasses multiple laboratory experiments and clinical trials. Laboratory experiments are conducted at specific stages of development, involving a defined number of samples and execution dates. These experiments generate quantitative results with observation dates and produce detailed logs containing notes and timestamps. The data from these experiments undergoes statistical analysis to compute mean values, ensuring data integrity through a validator that checks inputs against specific schema versions. Central to the platform is the management of molecular compounds, characterized by their weight and chemical formula, which can be classified as small molecules, biologics, peptides, or synthetic compounds. Compounds are stored in chemical libraries and serve as the basis for drug candidates. Each drug candidate tracks its current development stage, possesses a proposed dosage regimen specifying amount, frequency, and unit, and includes a comprehensive toxicity profile. This profile flags potential adverse events—such as allergic reactions, cardiovascular issues, or neurotoxicity—and determines carcinogenicity. Safety assessments are performed on these profiles and regimens to evaluate symptoms, check severity, and link to specific adverse event reports that detail the event category, patient notes, and severity level, with capabilities to flag life-threatening incidents. Drug candidates interact with specific target proteins, identified by their sequences and sequence identifiers. These interactions are quantified by binding affinity measurements, which include constants and units. Simulation models, which can be active or archived, are associated with target proteins and used to simulate specific compounds, calculating scores based on solvent inclusion and force field configurations. Clinical trials, designed as observational, randomized controlled, or cross-sectional studies, enroll specific compounds and include study cohorts of defined sizes. These cohorts focus on particular targets and operate under protocols. Assay protocols, authored by researchers, define methods to identify compound classes and require data validators. Pharmacokinetic studies analyze specific drug candidates, referencing binding affinities. The system also manages regulatory and publication aspects. Regulatory agencies review drug candidates, while publication records document findings related to research projects. Drug candidates maintain a validation status indicating whether they are validated and when. Researchers can generate comprehensive compound reports for specific molecules. Additionally, study cohorts can be assigned specific protocols, and simulation models are linked to the compounds they simulate, creating a fully integrated environment for tracking scientific progress from initial compound identification through clinical testing and regulatory review. | H12: @startuml enum DevelopmentStage { DISCOVERY PRECLINICAL PHASE_I PHASE_II PHASE_III APPROVED } enum TrialType { OBSERVATIONAL RANDOMIZED_CONTROLLED CROSS_SECTIONAL } enum EventCategory { ALLERGIC_REACTION CARDIOVASCULAR NEUROTOXICITY OTHER } enum SeverityLevel { MILD MODERATE SEVERE LIFE_THREATENING } enum SimulationStatus { ACTIVE ARCHIVED } class Institution { name : String address : String } class Researcher { name : String email : String expertise : String } class ResearchProject { title : String startDate : Date endDate : Date budget : double } class LaboratoryExperiment { experimentId : String stage : DevelopmentStage sampleCount : int executionDate : Date } class QuantitativeResult { value : double observationDate : Date unit : String } class ExperimentLog { notes : String timestamp : Date } class DataValidator { validatorId : String schemaVersion : String isActive : boolean } class ChemicalLibrary { name : String location : String capacity : int } class Compound { compoundId : String weight : double chemicalFormula : String } class SmallMolecule { } class Biologic { } class Peptide { } class SyntheticCompound { } class DrugCandidate { candidateId : String stage : DevelopmentStage isValidated : boolean validationDate : Date } class DosageRegimen { amount : double frequency : int unit : String } class ToxicityProfile { profileId : String isCarcinogenic : boolean } class AdverseEventReport { reportId : String category : EventCategory patientNotes : String severity : SeverityLevel isLifeThreatening : boolean } class TargetProtein { proteinId : String sequence : String sequenceIdentifier : String } class BindingAffinity { constant : double unit : String } class SimulationModel { modelId : String status : SimulationStatus solventInclusion : boolean forceFieldConfig : String score : double } class ClinicalTrial { trialId : String type : TrialType enrollmentSize : int } class StudyCohort { cohortId : String size : int targetFocus : String } class Protocol { protocolId : String description : String } class AssayProtocol { compoundClass : String methodName : String } class PharmacokineticStudy { studyId : String analysisDate : Date results : String } class RegulatoryAgency { agencyId : String name : String jurisdiction : String } class RegulatoryReview { reviewId : String reviewDate : Date decision : String } class PublicationRecord { publicationId : String title : String journal : String publishDate : Date } class CompoundReport { reportId : String generatedDate : Date summary : String } class StatisticalAnalysis { analysisId : String meanValue : double analysisDate : Date } class SafetyAssessment { assessmentId : String symptomEvaluation : String severityCheck : String } ' === Relationships === Institution --> "*" Researcher : employs 'opposite employer Researcher --> "*" ResearchProject : leads 'opposite projectLead ResearchProject *-- "*" LaboratoryExperiment : encompasses 'opposite parentProject ResearchProject *-- "*" ClinicalTrial : encompasses 'opposite project LaboratoryExperiment *-- "*" QuantitativeResult : generates 'opposite sourceExperiment LaboratoryExperiment *-- "*" ExperimentLog : produces 'opposite relatedExperiment LaboratoryExperiment --> "*" StatisticalAnalysis : analyzedBy 'opposite analyzedExperiment StatisticalAnalysis --> "*" QuantitativeResult : analyzes 'opposite analyzedIn QuantitativeResult --> "1" DataValidator : validatedBy 'opposite validatedResults AssayProtocol --> "*" DataValidator : requires 'opposite requiredByProtocols Compound --> "1..*" ChemicalLibrary : storedIn 'opposite stores Compound <|-- SmallMolecule Compound <|-- Biologic Compound <|-- Peptide Compound <|-- SyntheticCompound Compound <|-- DrugCandidate Compound --> "*" CompoundReport : describedIn 'opposite targetCompound Researcher --> "*" CompoundReport : generates 'opposite author DrugCandidate *-- "1" DosageRegimen : prescribes 'opposite prescribedFor DrugCandidate *-- "1" ToxicityProfile : includes 'opposite candidate ToxicityProfile --> "*" AdverseEventReport : flags 'opposite linkedProfile DosageRegimen --> "*" AdverseEventReport : linkedTo 'opposite relatedRegimen ToxicityProfile --> "*" SafetyAssessment : evaluatedBy 'opposite assessedProfile DosageRegimen --> "*" SafetyAssessment : assessedBy 'opposite assessedRegimen SafetyAssessment --> "*" AdverseEventReport : linksTo 'opposite linkedAssessment DrugCandidate --> "*" BindingAffinity : measures 'opposite measuredFor DrugCandidate --> "*" TargetProtein : interactsWith 'opposite interactingCandidates BindingAffinity --> "1" TargetProtein : targets 'opposite affinities TargetProtein --> "*" SimulationModel : associatedWith 'opposite simulatedProtein SimulationModel --> "*" Compound : simulates 'opposite simulatedBy ClinicalTrial *-- "*" StudyCohort : includes 'opposite parentTrial ClinicalTrial --> "*" Compound : enrolls 'opposite enrolledIn StudyCohort --> "*" TargetProtein : focusesOn 'opposite focusedCohorts StudyCohort --> "1..*" Protocol : operatesUnder 'opposite appliedCohorts Protocol <|-- AssayProtocol Researcher --> "*" Protocol : authors 'opposite protocolAuthor DrugCandidate --> "*" PharmacokineticStudy : analyzedBy 'opposite studiedCandidate PharmacokineticStudy --> "*" BindingAffinity : references 'opposite referencedByStudies DrugCandidate --> "*" RegulatoryReview : reviewedIn 'opposite reviewedCandidate RegulatoryAgency --> "*" RegulatoryReview : conducts 'opposite conductingAgency ResearchProject --> "*" PublicationRecord : documentedBy 'opposite relatedProject @enduml | I12: @startuml enum StudyType { OBSERVATIONAL RANDOMIZED_CONTROLLED CROSS_SECTIONAL } enum ModelStatus { ACTIVE ARCHIVED } class Institution { name: String } class Researcher { name: String } class ResearchProject { name: String } class PublicationRecord { title: String findings: String } class LaboratoryExperiment { stage: String sampleCount: Integer executionDate: Date } class QuantitativeResult { observationDate: Date value: Float } class ExperimentLog { note: String timestamp: DateTime } class StatisticalAnalysis { meanValue: Float } class DataValidator { schemaVersion: String } class MolecularCompound { weight: Float chemicalFormula: String } class SmallMolecule class Biologic class Peptide class SyntheticCompound class ChemicalLibrary { name: String } class DrugCandidate { developmentStage: String isValidated: Boolean validationDate: Date } class DosageRegimen { amount: Float frequency: String unit: String } class ToxicityProfile { isCarcinogenic: Boolean } class AdverseEvent { category: String patientNotes: String severityLevel: String isLifeThreatening: Boolean } class SafetyAssessment { symptoms: String severity: String } class TargetProtein { sequence: String sequenceId: String } class BindingAffinity { constant: Float unit: String } class SimulationModel { status: ModelStatus solventInclusion: Boolean forceFieldConfig: String score: Float } class ClinicalTrial { studyType: StudyType } class StudyCohort { size: Integer } class AssayProtocol { method: String } class PharmacokineticStudy { details: String } class RegulatoryAgency { name: String } class CompoundReport { content: String generatedDate: Date } Researcher "1" --> "1" Institution : belongs to Researcher "1" --> "*" ResearchProject : leads Researcher "1" --> "*" AssayProtocol : authors Researcher "1" --> "*" CompoundReport : generates ResearchProject "1" --> "*" LaboratoryExperiment : encompasses ResearchProject "1" --> "*" ClinicalTrial : encompasses ResearchProject "1" --> "*" PublicationRecord : documents LaboratoryExperiment "1" --> "*" QuantitativeResult : generates LaboratoryExperiment "1" --> "*" ExperimentLog : produces LaboratoryExperiment "1" --> "1" StatisticalAnalysis : analyzed by LaboratoryExperiment "*" --> "1" DataValidator : validated by MolecularCompound <|-- SmallMolecule MolecularCompound <|-- Biologic MolecularCompound <|-- Peptide MolecularCompound <|-- SyntheticCompound ChemicalLibrary "1" --> "*" MolecularCompound : stores MolecularCompound "1" --> "1" DrugCandidate : basis for DrugCandidate "1" --> "1" DosageRegimen : possesses DrugCandidate "1" --> "1" ToxicityProfile : includes DrugCandidate "*" --> "*" TargetProtein : interacts with DrugCandidate "*" --> "*" ClinicalTrial : enrolled in DrugCandidate "1" --> "*" PharmacokineticStudy : analyzed in DrugCandidate "*" --> "*" RegulatoryAgency : reviewed by ToxicityProfile "1" --> "*" AdverseEvent : flags SafetyAssessment "*" --> "1" ToxicityProfile : evaluates SafetyAssessment "*" --> "1" DosageRegimen : evaluates SafetyAssessment "*" --> "*" AdverseEvent : links to TargetProtein "1" --> "*" BindingAffinity : quantified by DrugCandidate "1" --> "*" BindingAffinity : quantified by TargetProtein "1" --> "*" SimulationModel : associated with SimulationModel "*" --> "1" MolecularCompound : simulates ClinicalTrial "1" --> "*" StudyCohort : includes StudyCohort "*" --> "1" TargetProtein : focuses on StudyCohort "*" --> "1" AssayProtocol : assigned AssayProtocol "*" --> "1" DataValidator : requires PharmacokineticStudy "*" --> "*" BindingAffinity : references CompoundReport "*" --> "1" MolecularCompound : for @enduml | J12: @startuml class Researcher { +name: String +institution: String } class Project { +title: String +startDate: Date +endDate: Date } class Experiment { +numSamples: Integer +executionDate: Date +observationDate: Date } class Result { +meanValue: Double +timestamp: Date +log: String } class Validator { +validate(inputs: List<String>, schemaVersion: String): Boolean } class Compound { +weight: Float +chemicalFormula: String } enum CompoundType { smallMolecule biologic peptide synthetic } class DrugCandidate { +developmentStage: String +dosageRegimen: String +toxicityProfile: String } class Interaction { +bindingAffinity: Float +affinityUnit: String } class TargetProtein { +sequence: String +sequenceIdentifier: String } class SimulationModel { +status: String +score: Float } class ClinicalTrial { +trialType: String +cohortSize: Integer } class Protocol { +method: String } class Report { +content: String } Researcher -- Project Project o-- Experiment Experiment o-- Result Validator -- Experiment Compound o-- DrugCandidate DrugCandidate -- Interaction TargetProtein -- Interaction SimulationModel -- TargetProtein ClinicalTrial o-- DrugCandidate Protocol o-- ClinicalTrial Researcher -- Report DrugCandidate -- Validator @enduml | K12: A | L12: B | M12: A | N12: A | O12: B | P12: A | Q12: A | R12: B | S12: A
E13: C12 | F13: AdvancedAlloyCompositionOptimization | G13: The Advanced Alloy Composition Optimization system supports research and industrial processes for developing high-performance metal alloys. The core unit of production is an Alloy Batch, created on a specific date, which contains multiple Material Specimens. Each specimen is defined by its density and surface finish, possesses a base Element Composition describing its chemical makeup, and has a current Phase Distribution detailing the fractions of target phases such as Austenite, Ferrite, Martensite, or Pearlite. Specimens can be analyzed to determine their current phase, classify grain structure, and annotate any defects. To achieve desired material properties, the system utilizes an Experiment Planner that generates Heat Treatment Profiles. These profiles, identified by name and quenching status, define processing steps and are validated before use. The planning process relies on a Phase Diagram Calculator to identify stable phases and check for equilibrium states. During execution, a Process Controller manages Thermal Analysis Runs, utilizing a Thermal Cycle Simulator to model cooling rates and peak temperatures while adhering to strict Safety Protocols that include emergency stop capabilities and temperature limits. Each thermal analysis run applies a specific profile. Data collection is organized under Research Projects, led by a principal investigator with a defined budget and associated design constraints. Projects encompass Experimental Datasets that verify data integrity, filter results, and store generated outcomes. These datasets aggregate Spectroscopy Data, which records wavelengths and emission intensities to detect phases and analyze elemental composition. Microstructure Analysis correlates specimen samples with spectroscopic data to refine phase distributions, utilizing the Phase Diagram Calculator as a reference. Furthermore, Stress Test Runners perform destructive or non-destructive tensile tests on specimens to generate Performance Metrics regarding load and increment steps. These metrics feed into Optimization Results that track convergence and recommend optimal element compositions. The system ensures adherence to engineering and legal standards through Design Constraints and Regulatory Standards, which specify limit values and effective dates to check specimen compliance. A Compliance Archive stores Batch Records, linking regulatory standards to specific batches; each record documents the primary phase, quality status, and the associated alloy batch. Operational support includes a Cost Estimator for calculating raw material expenses based on composition, a Supplier Network for finding vendors meeting design constraints, and a Quality Assurance module where certified inspectors approve batches. Finally, a Report Generator compiles performance metrics and quality assurance sources into summary reports in various formats. | H13: @startuml ' Enumerations enum SurfaceFinish { POLISHED ROUGH MACHINED AS_CAST } enum PhaseType { AUSTENITE FERRITE MARTENSITE PEARLITE } enum TestType { DESTRUCTIVE NON_DESTRUCTIVE } enum QualityStatus { APPROVED REJECTED PENDING } enum RunState { INITIALIZED HEATING HOLDING COOLING COMPLETED EMERGENCY_STOP } enum ReportFormat { PDF CSV JSON HTML } ' Domain Classes class AlloyBatch { batchId: String creationDate: Date name: String } class MaterialSpecimen { specimenId: String density: double surfaceFinish: SurfaceFinish grainStructure: String defectAnnotation: String } class ElementComposition { elementName: String percentage: double } class PhaseDistribution { phaseType: PhaseType fraction: double } class ExperimentPlanner { plannerId: String name: String } class HeatTreatmentProfile { profileId: String name: String quenchingStatus: boolean isValidated: boolean } class ProcessingStep { stepOrder: int targetTemperature: double durationMinutes: int description: String } class PhaseDiagramCalculator { calculatorId: String name: String equilibriumState: boolean stablePhases: String } class ProcessController { controllerId: String name: String } class ThermalAnalysisRun { runId: String currentState: RunState peakTemperature: double coolingRate: double startTime: Date endTime: Date } class ThermalCycleSimulator { simulatorId: String name: String } class SafetyProtocol { protocolId: String maxTemperatureLimit: double minTemperatureLimit: double emergencyStopEnabled: boolean } class ResearchProject { projectId: String projectName: String principalInvestigator: String budget: double } class ExperimentalDataset { datasetId: String name: String dataIntegrityVerified: boolean creationDate: Date filterCriteria: String resultsFiltered: boolean } class SpectroscopyData { dataId: String wavelength: double emissionIntensity: double detectedPhase: PhaseType timestamp: Date } class MicrostructureAnalysis { analysisId: String correlatedPhase: PhaseType refinedFraction: double description: String } class StressTestRunner { runnerId: String name: String } class StressTestRun { testId: String testType: TestType maxLoad: double incrementStep: double timestamp: Date } class PerformanceMetric { metricId: String loadValue: double incrementValue: double stressValue: double strainValue: double } class OptimizationResult { resultId: String convergenceTracked: boolean iterationCount: int recommendedComposition: String } class DesignConstraint { constraintId: String constraintName: String limitValue: double effectiveDate: Date } class RegulatoryStandard { standardId: String standardName: String limitValue: double effectiveDate: Date } class ComplianceArchive { archiveId: String archiveDate: Date } class BatchRecord { recordId: String primaryPhase: PhaseType qualityStatus: QualityStatus recordDate: Date } class CostEstimator { estimatorId: String name: String } class CostEstimation { estimationId: String totalCost: double currency: String calculationDate: Date } class SupplierNetwork { networkId: String name: String } class Supplier { supplierId: String name: String meetsConstraints: boolean contactInfo: String } class QualityAssurance { moduleId: String name: String } class QualityAssuranceReview { reviewId: String inspectorName: String inspectorCertified: boolean approvalDate: Date isApproved: boolean } class ReportGenerator { generatorId: String name: String } class SummaryReport { reportId: String title: String format: ReportFormat generationDate: Date } ' Associations and Compositions AlloyBatch "1" *-- "1..*" MaterialSpecimen: contains specimens MaterialSpecimen "1" *-- "1..*" ElementComposition: base composition MaterialSpecimen "1" *-- "1..*" PhaseDistribution: current phases ExperimentPlanner "1" --> "1..*" HeatTreatmentProfile: generates profiles HeatTreatmentProfile "1" *-- "1..*" ProcessingStep: defined steps PhaseDiagramCalculator "1" --> "*" HeatTreatmentProfile: references for planning PhaseDiagramCalculator "1" --> "*" MicrostructureAnalysis: references for analysis ProcessController "1" --> "1..*" ThermalAnalysisRun: manages runs ProcessController "1" --> "1" ThermalCycleSimulator: utilizes simulator ProcessController "1" --> "1..*" SafetyProtocol: adheres to protocols ThermalCycleSimulator "1" --> "*" ThermalAnalysisRun: simulates ThermalAnalysisRun "*" --> "1" HeatTreatmentProfile: applies profile ResearchProject "1" *-- "1..*" ExperimentalDataset: encompassed datasets ResearchProject "1" --> "1..*" DesignConstraint: associated constraints ExperimentalDataset "1" *-- "*" SpectroscopyData: aggregated data ExperimentalDataset "1" *-- "*" MicrostructureAnalysis: included analyses MicrostructureAnalysis "*" --> "1" MaterialSpecimen: correlates specimen MicrostructureAnalysis "*" --> "1" SpectroscopyData: correlates spectroscopic data StressTestRunner "1" --> "1..*" StressTestRun: performs tests MaterialSpecimen "1" --> "*" StressTestRun: tested in StressTestRun "1" *-- "1..*" PerformanceMetric: generated metrics PerformanceMetric "*" --> "1" OptimizationResult: feeds into ComplianceArchive "1" *-- "1..*" BatchRecord: stored records BatchRecord "*" --> "1" AlloyBatch: documents batch BatchRecord "*" --> "1..*" RegulatoryStandard: linked standards CostEstimator "1" --> "*" AlloyBatch: estimates costs for CostEstimator "1" --> "*" ElementComposition: calculates based on CostEstimator "1" --> "*" CostEstimation: produces estimations AlloyBatch "1" --> "1" CostEstimation: estimated by SupplierNetwork "1" --> "*" Supplier: finds vendors SupplierNetwork "1" --> "*" DesignConstraint: matches constraints QualityAssurance "1" --> "*" QualityAssuranceReview: conducts reviews AlloyBatch "1" --> "*" QualityAssuranceReview: reviewed in ReportGenerator "1" --> "*" SummaryReport: compiles reports ReportGenerator "*" --> "*" PerformanceMetric: compiles from metrics ReportGenerator "*" --> "*" QualityAssuranceReview: compiles from reviews @enduml | I13: @startuml skinparam classAttributeIconSize 0 hide empty members class AlloyBatch { creationDate: Date } class MaterialSpecimen { density: Float surfaceFinish: String } class ElementComposition { chemicalMakeup: Map } class PhaseDistribution { austenite: Float ferrite: Float martensite: Float pearlite: Float } class ExperimentPlanner { generateProfile() } class HeatTreatmentProfile { name: String quenchingStatus: Boolean processingSteps: List isValidated: Boolean } class PhaseDiagramCalculator { identifyStablePhases() checkEquilibrium() } class ProcessController { manageRun() } class ThermalAnalysisRun { runAnalysis() } class ThermalCycleSimulator { coolingRate: Float peakTemperature: Float } class SafetyProtocol { emergencyStop: Boolean temperatureLimit: Float } class ResearchProject { principalInvestigator: String budget: Decimal } class ExperimentalDataset { integrityVerified: Boolean filterResults() } class SpectroscopyData { wavelength: Float emissionIntensity: Float } class MicrostructureAnalysis { correlateData() refinePhases() } class StressTestRunner { testType: String performTest() } class PerformanceMetric { load: Float incrementStep: Integer } class OptimizationResult { convergence: Float } class DesignConstraint { limitValue: Float } class RegulatoryStandard { limitValue: Float effectiveDate: Date } class ComplianceArchive { storeRecord() } class BatchRecord { primaryPhase: String qualityStatus: String } class CostEstimator { calculateExpenses() } class SupplierNetwork { findVendors() } class QualityAssurance { inspector: String isCertified: Boolean approveBatch() } class ReportGenerator { format: String compileReport() } AlloyBatch "1" *-- "0..*" MaterialSpecimen MaterialSpecimen "1" *-- "1" ElementComposition MaterialSpecimen "1" *-- "1" PhaseDistribution ExperimentPlanner ..> HeatTreatmentProfile : generates HeatTreatmentProfile ..> PhaseDiagramCalculator : validated by ProcessController "1" --> "0..*" ThermalAnalysisRun : manages ThermalAnalysisRun "1" --> "1" HeatTreatmentProfile : applies ThermalAnalysisRun ..> ThermalCycleSimulator : utilizes ThermalAnalysisRun ..> SafetyProtocol : adheres to ResearchProject "1" *-- "0..*" ExperimentalDataset ResearchProject "1" --> "0..*" DesignConstraint ExperimentalDataset "1" *-- "0..*" SpectroscopyData MicrostructureAnalysis ..> MaterialSpecimen : correlates MicrostructureAnalysis ..> SpectroscopyData : correlates MicrostructureAnalysis ..> PhaseDiagramCalculator : references StressTestRunner ..> MaterialSpecimen : tests StressTestRunner ..> PerformanceMetric : generates OptimizationResult ..> PerformanceMetric : fed by OptimizationResult --> ElementComposition : recommends ComplianceArchive "1" *-- "0..*" BatchRecord BatchRecord "0..*" --> "1" AlloyBatch BatchRecord "0..*" --> "1" RegulatoryStandard CostEstimator ..> ElementComposition : calculates from SupplierNetwork ..> DesignConstraint : meets QualityAssurance ..> AlloyBatch : approves ReportGenerator ..> PerformanceMetric : compiles ReportGenerator ..> QualityAssurance : compiles @enduml | J13: @startuml class AlloyBatch { - creationDate: Date } class MaterialSpecimen { - density: float - surfaceFinish: String } class ElementComposition { } class PhaseDistribution { - austeniteFraction: float - ferriteFraction: float - martensiteFraction: float - pearliteFraction: float } class ExperimentPlanner { } class HeatTreatmentProfile { - name: String - quenchingStatus: Boolean } class PhaseDiagramCalculator { } class ProcessController { } class ThermalAnalysisRun { } class ThermalCycleSimulator { } class SafetyProtocol { - emergencyStop: Boolean - temperatureLimits: float } class ResearchProject { - budget: float } class ExperimentalDataset { } class SpectroscopyData { - wavelength: float - emissionIntensity: float } class MicrostructureAnalysis { } class StressTestRunner { } class PerformanceMetric { - load: float - incrementSteps: int } class OptimizationResult { } class DesignConstraint { - limitValue: float - effectiveDate: Date } class RegulatoryStandard { } class ComplianceArchive { } class CostEstimator { } class SupplierNetwork { } class QualityAssurance { } class ReportGenerator { } // Relationships AlloyBatch "1" -- "*" MaterialSpecimen MaterialSpecimen -- ElementComposition MaterialSpecimen -- PhaseDistribution ExperimentPlanner "1" -- "*" HeatTreatmentProfile PhaseDiagramCalculator -- PhaseDistribution ProcessController "1" -- "*" ThermalAnalysisRun ThermalAnalysisRun -- HeatTreatmentProfile ThermalAnalysisRun -- SafetyProtocol ResearchProject "1" -- "*" ExperimentalDataset ExperimentalDataset -- SpectroscopyData ExperimentalDataset -- MicrostructureAnalysis StressTestRunner -- PerformanceMetric OptimizationResult -- ElementComposition ComplianceArchive -- AlloyBatch DesignConstraint -- RegulatoryStandard @enduml | K13: A | L13: B | M13: A | N13: A | O13: B | P13: A | Q13: A | R13: B | S13: A

Sheet 人工最终结果
A1: 需求name | B1: 类别 | C1: 评审1 | D1: 评审2 | E1: 评审3 | F1: 人工最终结果 | G1: 票型 | H1: 表决状态
A2: BankAccount | B2: A vs B | C2: =IF(LEFT(评测集!K2,1)="D","D(平局)",评测集!K2) -> D(平局) | D2: =IF(LEFT(评测集!N2,1)="D","D(平局)",评测集!N2) -> D(平局) | E2: =IF(LEFT(评测集!Q2,1)="D","D(平局)",评测集!Q2) -> D(平局) | F2: =IF(OR(C2=D2,C2=E2),C2,IF(D2=E2,D2,"无多数/待复核")) -> D(平局) | G2: =C2&" / "&D2&" / "&E2 -> D(平局) / D(平局) / D(平局) | H2: =IF(F2="无多数/待复核","待复核","多数通过") -> 多数通过
A3: BankAccount | B3: B vs C | C3: =IF(LEFT(评测集!L2,1)="D","D(平局)",评测集!L2) -> B | D3: =IF(LEFT(评测集!O2,1)="D","D(平局)",评测集!O2) -> B | E3: =IF(LEFT(评测集!R2,1)="D","D(平局)",评测集!R2) -> C | F3: =IF(OR(C3=D3,C3=E3),C3,IF(D3=E3,D3,"无多数/待复核")) -> B | G3: =C3&" / "&D3&" / "&E3 -> B / B / C | H3: =IF(F3="无多数/待复核","待复核","多数通过") -> 多数通过
A4: BankAccount | B4: A vs C | C4: =IF(LEFT(评测集!M2,1)="D","D(平局)",评测集!M2) -> A | D4: =IF(LEFT(评测集!P2,1)="D","D(平局)",评测集!P2) -> A | E4: =IF(LEFT(评测集!S2,1)="D","D(平局)",评测集!S2) -> C | F4: =IF(OR(C4=D4,C4=E4),C4,IF(D4=E4,D4,"无多数/待复核")) -> A | G4: =C4&" / "&D4&" / "&E4 -> A / A / C | H4: =IF(F4="无多数/待复核","待复核","多数通过") -> 多数通过
A5: EUScienceConnect | B5: A vs B | C5: =IF(LEFT(评测集!K3,1)="D","D(平局)",评测集!K3) -> A | D5: =IF(LEFT(评测集!N3,1)="D","D(平局)",评测集!N3) -> A | E5: =IF(LEFT(评测集!Q3,1)="D","D(平局)",评测集!Q3) -> A | F5: =IF(OR(C5=D5,C5=E5),C5,IF(D5=E5,D5,"无多数/待复核")) -> A | G5: =C5&" / "&D5&" / "&E5 -> A / A / A | H5: =IF(F5="无多数/待复核","待复核","多数通过") -> 多数通过
A6: EUScienceConnect | B6: B vs C | C6: =IF(LEFT(评测集!L3,1)="D","D(平局)",评测集!L3) -> C | D6: =IF(LEFT(评测集!O3,1)="D","D(平局)",评测集!O3) -> C | E6: =IF(LEFT(评测集!R3,1)="D","D(平局)",评测集!R3) -> B | F6: =IF(OR(C6=D6,C6=E6),C6,IF(D6=E6,D6,"无多数/待复核")) -> C | G6: =C6&" / "&D6&" / "&E6 -> C / C / B | H6: =IF(F6="无多数/待复核","待复核","多数通过") -> 多数通过
A7: EUScienceConnect | B7: A vs C | C7: =IF(LEFT(评测集!M3,1)="D","D(平局)",评测集!M3) -> A | D7: =IF(LEFT(评测集!P3,1)="D","D(平局)",评测集!P3) -> A | E7: =IF(LEFT(评测集!S3,1)="D","D(平局)",评测集!S3) -> A | F7: =IF(OR(C7=D7,C7=E7),C7,IF(D7=E7,D7,"无多数/待复核")) -> A | G7: =C7&" / "&D7&" / "&E7 -> A / A / A | H7: =IF(F7="无多数/待复核","待复核","多数通过") -> 多数通过
A8: Cruise | B8: A vs B | C8: =IF(LEFT(评测集!K4,1)="D","D(平局)",评测集!K4) -> A | D8: =IF(LEFT(评测集!N4,1)="D","D(平局)",评测集!N4) -> A | E8: =IF(LEFT(评测集!Q4,1)="D","D(平局)",评测集!Q4) -> D(平局) | F8: =IF(OR(C8=D8,C8=E8),C8,IF(D8=E8,D8,"无多数/待复核")) -> A | G8: =C8&" / "&D8&" / "&E8 -> A / A / D(平局) | H8: =IF(F8="无多数/待复核","待复核","多数通过") -> 多数通过
A9: Cruise | B9: B vs C | C9: =IF(LEFT(评测集!L4,1)="D","D(平局)",评测集!L4) -> B | D9: =IF(LEFT(评测集!O4,1)="D","D(平局)",评测集!O4) -> B | E9: =IF(LEFT(评测集!R4,1)="D","D(平局)",评测集!R4) -> B | F9: =IF(OR(C9=D9,C9=E9),C9,IF(D9=E9,D9,"无多数/待复核")) -> B | G9: =C9&" / "&D9&" / "&E9 -> B / B / B | H9: =IF(F9="无多数/待复核","待复核","多数通过") -> 多数通过
A10: Cruise | B10: A vs C | C10: =IF(LEFT(评测集!M4,1)="D","D(平局)",评测集!M4) -> A | D10: =IF(LEFT(评测集!P4,1)="D","D(平局)",评测集!P4) -> A | E10: =IF(LEFT(评测集!S4,1)="D","D(平局)",评测集!S4) -> A | F10: =IF(OR(C10=D10,C10=E10),C10,IF(D10=E10,D10,"无多数/待复核")) -> A | G10: =C10&" / "&D10&" / "&E10 -> A / A / A | H10: =IF(F10="无多数/待复核","待复核","多数通过") -> 多数通过
A11: House | B11: A vs B | C11: =IF(LEFT(评测集!K5,1)="D","D(平局)",评测集!K5) -> A | D11: =IF(LEFT(评测集!N5,1)="D","D(平局)",评测集!N5) -> A | E11: =IF(LEFT(评测集!Q5,1)="D","D(平局)",评测集!Q5) -> B | F11: =IF(OR(C11=D11,C11=E11),C11,IF(D11=E11,D11,"无多数/待复核")) -> A | G11: =C11&" / "&D11&" / "&E11 -> A / A / B | H11: =IF(F11="无多数/待复核","待复核","多数通过") -> 多数通过
A12: House | B12: B vs C | C12: =IF(LEFT(评测集!L5,1)="D","D(平局)",评测集!L5) -> B | D12: =IF(LEFT(评测集!O5,1)="D","D(平局)",评测集!O5) -> B | E12: =IF(LEFT(评测集!R5,1)="D","D(平局)",评测集!R5) -> D(平局) | F12: =IF(OR(C12=D12,C12=E12),C12,IF(D12=E12,D12,"无多数/待复核")) -> B | G12: =C12&" / "&D12&" / "&E12 -> B / B / D(平局) | H12: =IF(F12="无多数/待复核","待复核","多数通过") -> 多数通过
A13: House | B13: A vs C | C13: =IF(LEFT(评测集!M5,1)="D","D(平局)",评测集!M5) -> A | D13: =IF(LEFT(评测集!P5,1)="D","D(平局)",评测集!P5) -> A | E13: =IF(LEFT(评测集!S5,1)="D","D(平局)",评测集!S5) -> C | F13: =IF(OR(C13=D13,C13=E13),C13,IF(D13=E13,D13,"无多数/待复核")) -> A | G13: =C13&" / "&D13&" / "&E13 -> A / A / C | H13: =IF(F13="无多数/待复核","待复核","多数通过") -> 多数通过
A14: CelO | B14: A vs B | C14: =IF(LEFT(评测集!K6,1)="D","D(平局)",评测集!K6) -> B | D14: =IF(LEFT(评测集!N6,1)="D","D(平局)",评测集!N6) -> B | E14: =IF(LEFT(评测集!Q6,1)="D","D(平局)",评测集!Q6) -> A | F14: =IF(OR(C14=D14,C14=E14),C14,IF(D14=E14,D14,"无多数/待复核")) -> B | G14: =C14&" / "&D14&" / "&E14 -> B / B / A | H14: =IF(F14="无多数/待复核","待复核","多数通过") -> 多数通过
A15: CelO | B15: B vs C | C15: =IF(LEFT(评测集!L6,1)="D","D(平局)",评测集!L6) -> B | D15: =IF(LEFT(评测集!O6,1)="D","D(平局)",评测集!O6) -> B | E15: =IF(LEFT(评测集!R6,1)="D","D(平局)",评测集!R6) -> B | F15: =IF(OR(C15=D15,C15=E15),C15,IF(D15=E15,D15,"无多数/待复核")) -> B | G15: =C15&" / "&D15&" / "&E15 -> B / B / B | H15: =IF(F15="无多数/待复核","待复核","多数通过") -> 多数通过
A16: CelO | B16: A vs C | C16: =IF(LEFT(评测集!M6,1)="D","D(平局)",评测集!M6) -> A | D16: =IF(LEFT(评测集!P6,1)="D","D(平局)",评测集!P6) -> C | E16: =IF(LEFT(评测集!S6,1)="D","D(平局)",评测集!S6) -> A | F16: =IF(OR(C16=D16,C16=E16),C16,IF(D16=E16,D16,"无多数/待复核")) -> A | G16: =C16&" / "&D16&" / "&E16 -> A / C / A | H16: =IF(F16="无多数/待复核","待复核","多数通过") -> 多数通过
A17: TileOGame | B17: A vs B | C17: =IF(LEFT(评测集!K7,1)="D","D(平局)",评测集!K7) -> A | D17: =IF(LEFT(评测集!N7,1)="D","D(平局)",评测集!N7) -> A | E17: =IF(LEFT(评测集!Q7,1)="D","D(平局)",评测集!Q7) -> B | F17: =IF(OR(C17=D17,C17=E17),C17,IF(D17=E17,D17,"无多数/待复核")) -> A | G17: =C17&" / "&D17&" / "&E17 -> A / A / B | H17: =IF(F17="无多数/待复核","待复核","多数通过") -> 多数通过
A18: TileOGame | B18: B vs C | C18: =IF(LEFT(评测集!L7,1)="D","D(平局)",评测集!L7) -> C | D18: =IF(LEFT(评测集!O7,1)="D","D(平局)",评测集!O7) -> C | E18: =IF(LEFT(评测集!R7,1)="D","D(平局)",评测集!R7) -> C | F18: =IF(OR(C18=D18,C18=E18),C18,IF(D18=E18,D18,"无多数/待复核")) -> C | G18: =C18&" / "&D18&" / "&E18 -> C / C / C | H18: =IF(F18="无多数/待复核","待复核","多数通过") -> 多数通过
A19: TileOGame | B19: A vs C | C19: =IF(LEFT(评测集!M7,1)="D","D(平局)",评测集!M7) -> C | D19: =IF(LEFT(评测集!P7,1)="D","D(平局)",评测集!P7) -> C | E19: =IF(LEFT(评测集!S7,1)="D","D(平局)",评测集!S7) -> C | F19: =IF(OR(C19=D19,C19=E19),C19,IF(D19=E19,D19,"无多数/待复核")) -> C | G19: =C19&" / "&D19&" / "&E19 -> C / C / C | H19: =IF(F19="无多数/待复核","待复核","多数通过") -> 多数通过
A20: SellingGoods | B20: A vs B | C20: =IF(LEFT(评测集!K8,1)="D","D(平局)",评测集!K8) -> D(平局) | D20: =IF(LEFT(评测集!N8,1)="D","D(平局)",评测集!N8) -> B | E20: =IF(LEFT(评测集!Q8,1)="D","D(平局)",评测集!Q8) -> D(平局) | F20: =IF(OR(C20=D20,C20=E20),C20,IF(D20=E20,D20,"无多数/待复核")) -> D(平局) | G20: =C20&" / "&D20&" / "&E20 -> D(平局) / B / D(平局) | H20: =IF(F20="无多数/待复核","待复核","多数通过") -> 多数通过
A21: SellingGoods | B21: B vs C | C21: =IF(LEFT(评测集!L8,1)="D","D(平局)",评测集!L8) -> B | D21: =IF(LEFT(评测集!O8,1)="D","D(平局)",评测集!O8) -> B | E21: =IF(LEFT(评测集!R8,1)="D","D(平局)",评测集!R8) -> B | F21: =IF(OR(C21=D21,C21=E21),C21,IF(D21=E21,D21,"无多数/待复核")) -> B | G21: =C21&" / "&D21&" / "&E21 -> B / B / B | H21: =IF(F21="无多数/待复核","待复核","多数通过") -> 多数通过
A22: SellingGoods | B22: A vs C | C22: =IF(LEFT(评测集!M8,1)="D","D(平局)",评测集!M8) -> A | D22: =IF(LEFT(评测集!P8,1)="D","D(平局)",评测集!P8) -> A | E22: =IF(LEFT(评测集!S8,1)="D","D(平局)",评测集!S8) -> A | F22: =IF(OR(C22=D22,C22=E22),C22,IF(D22=E22,D22,"无多数/待复核")) -> A | G22: =C22&" / "&D22&" / "&E22 -> A / A / A | H22: =IF(F22="无多数/待复核","待复核","多数通过") -> 多数通过
A23: University | B23: A vs B | C23: =IF(LEFT(评测集!K9,1)="D","D(平局)",评测集!K9) -> A | D23: =IF(LEFT(评测集!N9,1)="D","D(平局)",评测集!N9) -> A | E23: =IF(LEFT(评测集!Q9,1)="D","D(平局)",评测集!Q9) -> A | F23: =IF(OR(C23=D23,C23=E23),C23,IF(D23=E23,D23,"无多数/待复核")) -> A | G23: =C23&" / "&D23&" / "&E23 -> A / A / A | H23: =IF(F23="无多数/待复核","待复核","多数通过") -> 多数通过
A24: University | B24: B vs C | C24: =IF(LEFT(评测集!L9,1)="D","D(平局)",评测集!L9) -> C | D24: =IF(LEFT(评测集!O9,1)="D","D(平局)",评测集!O9) -> C | E24: =IF(LEFT(评测集!R9,1)="D","D(平局)",评测集!R9) -> C | F24: =IF(OR(C24=D24,C24=E24),C24,IF(D24=E24,D24,"无多数/待复核")) -> C | G24: =C24&" / "&D24&" / "&E24 -> C / C / C | H24: =IF(F24="无多数/待复核","待复核","多数通过") -> 多数通过
A25: University | B25: A vs C | C25: =IF(LEFT(评测集!M9,1)="D","D(平局)",评测集!M9) -> D(平局) | D25: =IF(LEFT(评测集!P9,1)="D","D(平局)",评测集!P9) -> A | E25: =IF(LEFT(评测集!S9,1)="D","D(平局)",评测集!S9) -> D(平局) | F25: =IF(OR(C25=D25,C25=E25),C25,IF(D25=E25,D25,"无多数/待复核")) -> D(平局) | G25: =C25&" / "&D25&" / "&E25 -> D(平局) / A / D(平局) | H25: =IF(F25="无多数/待复核","待复核","多数通过") -> 多数通过
A26: TeamSportsScoutingSystem | B26: A vs B | C26: =IF(LEFT(评测集!K10,1)="D","D(平局)",评测集!K10) -> B | D26: =IF(LEFT(评测集!N10,1)="D","D(平局)",评测集!N10) -> B | E26: =IF(LEFT(评测集!Q10,1)="D","D(平局)",评测集!Q10) -> D(平局) | F26: =IF(OR(C26=D26,C26=E26),C26,IF(D26=E26,D26,"无多数/待复核")) -> B | G26: =C26&" / "&D26&" / "&E26 -> B / B / D(平局) | H26: =IF(F26="无多数/待复核","待复核","多数通过") -> 多数通过
A27: TeamSportsScoutingSystem | B27: B vs C | C27: =IF(LEFT(评测集!L10,1)="D","D(平局)",评测集!L10) -> B | D27: =IF(LEFT(评测集!O10,1)="D","D(平局)",评测集!O10) -> B | E27: =IF(LEFT(评测集!R10,1)="D","D(平局)",评测集!R10) -> B | F27: =IF(OR(C27=D27,C27=E27),C27,IF(D27=E27,D27,"无多数/待复核")) -> B | G27: =C27&" / "&D27&" / "&E27 -> B / B / B | H27: =IF(F27="无多数/待复核","待复核","多数通过") -> 多数通过
A28: TeamSportsScoutingSystem | B28: A vs C | C28: =IF(LEFT(评测集!M10,1)="D","D(平局)",评测集!M10) -> A | D28: =IF(LEFT(评测集!P10,1)="D","D(平局)",评测集!P10) -> A | E28: =IF(LEFT(评测集!S10,1)="D","D(平局)",评测集!S10) -> A | F28: =IF(OR(C28=D28,C28=E28),C28,IF(D28=E28,D28,"无多数/待复核")) -> A | G28: =C28&" / "&D28&" / "&E28 -> A / A / A | H28: =IF(F28="无多数/待复核","待复核","多数通过") -> 多数通过
A29: AirTrafficControlNavigationSystem | B29: A vs B | C29: =IF(LEFT(评测集!K11,1)="D","D(平局)",评测集!K11) -> D(平局) | D29: =IF(LEFT(评测集!N11,1)="D","D(平局)",评测集!N11) -> A | E29: =IF(LEFT(评测集!Q11,1)="D","D(平局)",评测集!Q11) -> D(平局) | F29: =IF(OR(C29=D29,C29=E29),C29,IF(D29=E29,D29,"无多数/待复核")) -> D(平局) | G29: =C29&" / "&D29&" / "&E29 -> D(平局) / A / D(平局) | H29: =IF(F29="无多数/待复核","待复核","多数通过") -> 多数通过
A30: AirTrafficControlNavigationSystem | B30: B vs C | C30: =IF(LEFT(评测集!L11,1)="D","D(平局)",评测集!L11) -> B | D30: =IF(LEFT(评测集!O11,1)="D","D(平局)",评测集!O11) -> B | E30: =IF(LEFT(评测集!R11,1)="D","D(平局)",评测集!R11) -> B | F30: =IF(OR(C30=D30,C30=E30),C30,IF(D30=E30,D30,"无多数/待复核")) -> B | G30: =C30&" / "&D30&" / "&E30 -> B / B / B | H30: =IF(F30="无多数/待复核","待复核","多数通过") -> 多数通过
A31: AirTrafficControlNavigationSystem | B31: A vs C | C31: =IF(LEFT(评测集!M11,1)="D","D(平局)",评测集!M11) -> A | D31: =IF(LEFT(评测集!P11,1)="D","D(平局)",评测集!P11) -> A | E31: =IF(LEFT(评测集!S11,1)="D","D(平局)",评测集!S11) -> A | F31: =IF(OR(C31=D31,C31=E31),C31,IF(D31=E31,D31,"无多数/待复核")) -> A | G31: =C31&" / "&D31&" / "&E31 -> A / A / A | H31: =IF(F31="无多数/待复核","待复核","多数通过") -> 多数通过
A32: AI-AssistedDrugDiscoveryPlatform | B32: A vs B | C32: =IF(LEFT(评测集!K12,1)="D","D(平局)",评测集!K12) -> A | D32: =IF(LEFT(评测集!N12,1)="D","D(平局)",评测集!N12) -> A | E32: =IF(LEFT(评测集!Q12,1)="D","D(平局)",评测集!Q12) -> A | F32: =IF(OR(C32=D32,C32=E32),C32,IF(D32=E32,D32,"无多数/待复核")) -> A | G32: =C32&" / "&D32&" / "&E32 -> A / A / A | H32: =IF(F32="无多数/待复核","待复核","多数通过") -> 多数通过
A33: AI-AssistedDrugDiscoveryPlatform | B33: B vs C | C33: =IF(LEFT(评测集!L12,1)="D","D(平局)",评测集!L12) -> B | D33: =IF(LEFT(评测集!O12,1)="D","D(平局)",评测集!O12) -> B | E33: =IF(LEFT(评测集!R12,1)="D","D(平局)",评测集!R12) -> B | F33: =IF(OR(C33=D33,C33=E33),C33,IF(D33=E33,D33,"无多数/待复核")) -> B | G33: =C33&" / "&D33&" / "&E33 -> B / B / B | H33: =IF(F33="无多数/待复核","待复核","多数通过") -> 多数通过
A34: AI-AssistedDrugDiscoveryPlatform | B34: A vs C | C34: =IF(LEFT(评测集!M12,1)="D","D(平局)",评测集!M12) -> A | D34: =IF(LEFT(评测集!P12,1)="D","D(平局)",评测集!P12) -> A | E34: =IF(LEFT(评测集!S12,1)="D","D(平局)",评测集!S12) -> A | F34: =IF(OR(C34=D34,C34=E34),C34,IF(D34=E34,D34,"无多数/待复核")) -> A | G34: =C34&" / "&D34&" / "&E34 -> A / A / A | H34: =IF(F34="无多数/待复核","待复核","多数通过") -> 多数通过
A35: AdvancedAlloyCompositionOptimization | B35: A vs B | C35: =IF(LEFT(评测集!K13,1)="D","D(平局)",评测集!K13) -> A | D35: =IF(LEFT(评测集!N13,1)="D","D(平局)",评测集!N13) -> A | E35: =IF(LEFT(评测集!Q13,1)="D","D(平局)",评测集!Q13) -> A | F35: =IF(OR(C35=D35,C35=E35),C35,IF(D35=E35,D35,"无多数/待复核")) -> A | G35: =C35&" / "&D35&" / "&E35 -> A / A / A | H35: =IF(F35="无多数/待复核","待复核","多数通过") -> 多数通过
A36: AdvancedAlloyCompositionOptimization | B36: B vs C | C36: =IF(LEFT(评测集!L13,1)="D","D(平局)",评测集!L13) -> B | D36: =IF(LEFT(评测集!O13,1)="D","D(平局)",评测集!O13) -> B | E36: =IF(LEFT(评测集!R13,1)="D","D(平局)",评测集!R13) -> B | F36: =IF(OR(C36=D36,C36=E36),C36,IF(D36=E36,D36,"无多数/待复核")) -> B | G36: =C36&" / "&D36&" / "&E36 -> B / B / B | H36: =IF(F36="无多数/待复核","待复核","多数通过") -> 多数通过
A37: AdvancedAlloyCompositionOptimization | B37: A vs C | C37: =IF(LEFT(评测集!M13,1)="D","D(平局)",评测集!M13) -> A | D37: =IF(LEFT(评测集!P13,1)="D","D(平局)",评测集!P13) -> A | E37: =IF(LEFT(评测集!S13,1)="D","D(平局)",评测集!S13) -> A | F37: =IF(OR(C37=D37,C37=E37),C37,IF(D37=E37,D37,"无多数/待复核")) -> A | G37: =C37&" / "&D37&" / "&E37 -> A / A / A | H37: =IF(F37="无多数/待复核","待复核","多数通过") -> 多数通过
