Workbook

Sheet 实验结果
A1: 需求name | B1: 需求描述 | C1: 类别 | D1: 指标类别 | E1: 位置 | F1: 提示词 | G1: 生产模式设置 | H1: 基座模型设置 | I1: 输出结果 | J1: 最终结果 | K1: 实际结果 | L1: 人工打标 | M1: 一致性
A2: AdvancedAlloyCompositionOptimization | B2: The Advanced Alloy Composition Optimization system supports research and industrial processes for developing high-performance metal alloys. The core unit of production is an Alloy Batch, created on a specific date, which contains multiple Material Specimens. Each specimen is defined by its density and surface finish, possesses a base Element Composition describing its chemical makeup, and has a current Phase Distribution detailing the fractions of target phases such as Austenite, Ferrite, Martensite, or Pearlite. Specimens can be analyzed to determine their current phase, classify grain structure, and annotate any defects. To achieve desired material properties, the system utilizes an Experiment Planner that generates Heat Treatment Profiles. These profiles, identified by name and quenching status, define processing steps and are validated before use. The planning process relies on a Phase Diagram Calculator to identify stable phases and check for equilibrium states. During execution, a Process Controller manages Thermal Analysis Runs, utilizing a Thermal Cycle Simulator to model cooling rates and peak temperatures while adhering to strict Safety Protocols that include emergency stop capabilities and temperature limits. Each thermal analysis run applies a specific profile. Data collection is organized under Research Projects, led by a principal investigator with a defined budget and associated design constraints. Projects encompass Experimental Datasets that verify data integrity, filter results, and store generated outcomes. These datasets aggregate Spectroscopy Data, which records wavelengths and emission intensities to detect phases and analyze elemental composition. Microstructure Analysis correlates specimen samples with spectroscopic data to refine phase distributions, utilizing the Phase Diagram Calculator as a reference. Furthermore, Stress Test Runners perform destructive or non-destructive tensile tests on specimens to generate Performance Metrics regarding load and increment steps. These metrics feed into Optimization Results that track convergence and recommend optimal element compositions. The system ensures adherence to engineering and legal standards through Design Constraints and Regulatory Standards, which specify limit values and effective dates to check specimen compliance. A Compliance Archive stores Batch Records, linking regulatory standards to specific batches; each record documents the primary phase, quality status, and the associated alloy batch. Operational support includes a Cost Estimator for calculating raw material expenses based on composition, a Supplier Network for finding vendors meeting design constraints, and a Quality Assurance module where certified inspectors approve batches. Finally, a Report Generator compiles performance metrics and quality assurance sources into summary reports in various formats. | C2: A vs B | D2: faithfulness | E2: l2r | F2: You are a professional software engineer with expertise across multiple domains. You evaluate UML class diagrams from the perspective of real-world software design, applying domain knowledge and engineering best practices alongside the provided scoring criteria. Please evaluate the two diagrams (Model 1, Model 2) based on the provided requirement and scoring criteria. # Criteria **CRITICAL INSTRUCTION**: You MUST evaluate the responses against EACH AND EVERY criterion listed in the "Specific Instructions" one by one. DO NOT aggregate, summarize, or skip any criterion. **Specific Instructions**: - Ensure that the design aligns with the given requirement strictly, achieving all the functionalities based on the requirements without making any hallucinations and additions. Ensure that the conceptual classes and their relationships accurately represent the essentials outlined in the requirement. This includes a detailed focus on the associations between classes, their cardinalities, and the types of relationships such as inheritance, aggregation, and composition. Clarity in class names and the optional inclusion of attributes are key for aligning with the project's vision. # Evaluation Guidelines ## General Rules - Consider only UML class diagram semantics (e.g., classes, attributes, associations, multiplicities, generalisation, composition/aggregation). - Ignore layout, styling, skinparams, comments, and notes. - If the response is incomplete or misses any required key component, regard it as a bad one. - Give credit for semantic clarity, but not for layout, comments, visibility markers, or other presentation-only differences. ## Forbidden Penalties (Strictly Enforced) You MUST NOT deduct points, lower scores, or claim a model is "worse", "complex", or "less practical" based on ANY of the following: 1. **Association Styles**: Using two opposite unidirectional associations (e.g., `A --> B` and `B --> A`) instead of one single bidirectional line (e.g., `A -- B`). They are 100% semantically equivalent. Treat opposite-direction associations as equivalent unless role labels, multiplicities, or navigability contradict the requirements. 2. **PlantUML Comments**: Using single-quote comments (e.g., `'opposite bank`) at the end of lines. These are standard tooling annotations — ignore them for scoring unless they obscure or contradict the relation meaning. 3. **Primitive Types**: Using common aliases for types (e.g., `int` instead of `Integer`, `str` instead of `String`, `boolean` instead of `Boolean`). Lowercase or language-flavored spellings are acceptable. 4. **Equivalent Multiplicity Literals**: Using `*` instead of `0..*`, or `1` instead of `1..1`. These pairs are semantically identical. 5. **Optional Abstractness**: Marking or not marking a superclass as `abstract` when the requirement does not say whether direct instances are allowed. Do not reward either style without requirement evidence. These forbidden factors must not appear as negative evidence under any criterion and must not affect criterion scores or the final choice. ## Evidence & Calibration Requirements - For every criterion you discuss, cite concrete evidence from both models. Quote or closely paraphrase the relevant class, attribute, association, multiplicity, inheritance, note, or missing element. - Do not claim a class, attribute, or association is missing when a synonymous or directly related element is present. If the present element is indirect, vague, over-constrained, or semantically weak, state that precise weakness instead. - Distinguish omissions from contradictions. Missing a hard constraint is usually less severe than explicitly modeling the opposite or an invalid multiplicity. - Do not reward a simpler model merely for being shorter if the more detailed model uses traceable intermediate workflow/concept classes required for domain reasoning. - Do not penalize a detailed model merely for using transparent refinements such as `Definition`, `Placement`, `Entry`, `Session`, `State`, `Record`, `Assignment`, `Arrangement`, or `Need` when the base requirement term remains recognizable. - Do not reward extra identifiers, timestamps, statuses, classes, or implementation-oriented detail unless they improve coverage of a stated requirement fact. - Text introduced by `e.g.`, `for example`, or `such as` gives examples, not a complete enumeration, unless the requirement explicitly declares a closed list. - Keep UML/PlantUML standards separate from domain accuracy. Domain-faithfulness problems, wrong business multiplicities, missing constraints, or vague semantics belong under the domain criteria, not UML standards, unless they make the notation invalid or unreadable. - When evaluating position bias, remember that Model 1 and Model 2 may be swapped in a second pass. Use only the content under each model block, not assumptions from prior comparisons or labels. # Requirement ``` The Advanced Alloy Composition Optimization system supports research and industrial processes for developing high-performance metal alloys. The core unit of production is an Alloy Batch, created on a specific date, which contains multiple Material Specimens. Each specimen is defined by its density and surface finish, possesses a base Element Composition describing its chemical makeup, and has a current Phase Distribution detailing the fractions of target phases such as Austenite, Ferrite, Martensite, or Pearlite. Specimens can be analyzed to determine their current phase, classify grain structure, and annotate any defects. To achieve desired material properties, the system utilizes an Experiment Planner that generates Heat Treatment Profiles. These profiles, identified by name and quenching status, define processing steps and are validated before use. The planning process relies on a Phase Diagram Calculator to identify stable phases and check for equilibrium states. During execution, a Process Controller manages Thermal Analysis Runs, utilizing a Thermal Cycle Simulator to model cooling rates and peak temperatures while adhering to strict Safety Protocols that include emergency stop capabilities and temperature limits. Each thermal analysis run applies a specific profile. Data collection is organized under Research Projects, led by a principal investigator with a defined budget and associated design constraints. Projects encompass Experimental Datasets that verify data integrity, filter results, and store generated outcomes. These datasets aggregate Spectroscopy Data, which records wavelengths and emission intensities to detect phases and analyze elemental composition. Microstructure Analysis correlates specimen samples with spectroscopic data to refine phase distributions, utilizing the Phase Diagram Calculator as a reference. Furthermore, Stress Test Runners perform destructive or non-destructive tensile tests on specimens to generate Performance Metrics regarding load and increment steps. These metrics feed into Optimization Results that track convergence and recommend optimal element compositions. The system ensures adherence to engineering and legal standards through Design Constraints and Regulatory Standards, which specify limit values and effective dates to check specimen compliance. A Compliance Archive stores Batch Records, linking regulatory standards to specific batches; each record documents the primary phase, quality status, and the associated alloy batch. Operational support includes a Cost Estimator for calculating raw material expenses based on composition, a Supplier Network for finding vendors meeting design constraints, and a Quality Assurance module where certified inspectors approve batches. Finally, a Report Generator compiles performance metrics and quality assurance sources into summary reports in various formats. ``` # Model 1 ``` @startuml ' Enumerations enum SurfaceFinish { POLISHED ROUGH MACHINED AS_CAST } enum PhaseType { AUSTENITE FERRITE MARTENSITE PEARLITE } enum TestType { DESTRUCTIVE NON_DESTRUCTIVE } enum QualityStatus { APPROVED REJECTED PENDING } enum RunState { INITIALIZED HEATING HOLDING COOLING COMPLETED EMERGENCY_STOP } enum ReportFormat { PDF CSV JSON HTML } ' Domain Classes class AlloyBatch { batchId: String creationDate: Date name: String } class MaterialSpecimen { specimenId: String density: double surfaceFinish: SurfaceFinish grainStructure: String defectAnnotation: String } class ElementComposition { elementName: String percentage: double } class PhaseDistribution { phaseType: PhaseType fraction: double } class ExperimentPlanner { plannerId: String name: String } class HeatTreatmentProfile { profileId: String name: String quenchingStatus: boolean isValidated: boolean } class ProcessingStep { stepOrder: int targetTemperature: double durationMinutes: int description: String } class PhaseDiagramCalculator { calculatorId: String name: String equilibriumState: boolean stablePhases: String } class ProcessController { controllerId: String name: String } class ThermalAnalysisRun { runId: String currentState: RunState peakTemperature: double coolingRate: double startTime: Date endTime: Date } class ThermalCycleSimulator { simulatorId: String name: String } class SafetyProtocol { protocolId: String maxTemperatureLimit: double minTemperatureLimit: double emergencyStopEnabled: boolean } class ResearchProject { projectId: String projectName: String principalInvestigator: String budget: double } class ExperimentalDataset { datasetId: String name: String dataIntegrityVerified: boolean creationDate: Date filterCriteria: String resultsFiltered: boolean } class SpectroscopyData { dataId: String wavelength: double emissionIntensity: double detectedPhase: PhaseType timestamp: Date } class MicrostructureAnalysis { analysisId: String correlatedPhase: PhaseType refinedFraction: double description: String } class StressTestRunner { runnerId: String name: String } class StressTestRun { testId: String testType: TestType maxLoad: double incrementStep: double timestamp: Date } class PerformanceMetric { metricId: String loadValue: double incrementValue: double stressValue: double strainValue: double } class OptimizationResult { resultId: String convergenceTracked: boolean iterationCount: int recommendedComposition: String } class DesignConstraint { constraintId: String constraintName: String limitValue: double effectiveDate: Date } class RegulatoryStandard { standardId: String standardName: String limitValue: double effectiveDate: Date } class ComplianceArchive { archiveId: String archiveDate: Date } class BatchRecord { recordId: String primaryPhase: PhaseType qualityStatus: QualityStatus recordDate: Date } class CostEstimator { estimatorId: String name: String } class CostEstimation { estimationId: String totalCost: double currency: String calculationDate: Date } class SupplierNetwork { networkId: String name: String } class Supplier { supplierId: String name: String meetsConstraints: boolean contactInfo: String } class QualityAssurance { moduleId: String name: String } class QualityAssuranceReview { reviewId: String inspectorName: String inspectorCertified: boolean approvalDate: Date isApproved: boolean } class ReportGenerator { generatorId: String name: String } class SummaryReport { reportId: String title: String format: ReportFormat generationDate: Date } ' Associations and Compositions AlloyBatch "1" *-- "1..*" MaterialSpecimen: contains specimens MaterialSpecimen "1" *-- "1..*" ElementComposition: base composition MaterialSpecimen "1" *-- "1..*" PhaseDistribution: current phases ExperimentPlanner "1" --> "1..*" HeatTreatmentProfile: generates profiles HeatTreatmentProfile "1" *-- "1..*" ProcessingStep: defined steps PhaseDiagramCalculator "1" --> "*" HeatTreatmentProfile: references for planning PhaseDiagramCalculator "1" --> "*" MicrostructureAnalysis: references for analysis ProcessController "1" --> "1..*" ThermalAnalysisRun: manages runs ProcessController "1" --> "1" ThermalCycleSimulator: utilizes simulator ProcessController "1" --> "1..*" SafetyProtocol: adheres to protocols ThermalCycleSimulator "1" --> "*" ThermalAnalysisRun: simulates ThermalAnalysisRun "*" --> "1" HeatTreatmentProfile: applies profile ResearchProject "1" *-- "1..*" ExperimentalDataset: encompassed datasets ResearchProject "1" --> "1..*" DesignConstraint: associated constraints ExperimentalDataset "1" *-- "*" SpectroscopyData: aggregated data ExperimentalDataset "1" *-- "*" MicrostructureAnalysis: included analyses MicrostructureAnalysis "*" --> "1" MaterialSpecimen: correlates specimen MicrostructureAnalysis "*" --> "1" SpectroscopyData: correlates spectroscopic data StressTestRunner "1" --> "1..*" StressTestRun: performs tests MaterialSpecimen "1" --> "*" StressTestRun: tested in StressTestRun "1" *-- "1..*" PerformanceMetric: generated metrics PerformanceMetric "*" --> "1" OptimizationResult: feeds into ComplianceArchive "1" *-- "1..*" BatchRecord: stored records BatchRecord "*" --> "1" AlloyBatch: documents batch BatchRecord "*" --> "1..*" RegulatoryStandard: linked standards CostEstimator "1" --> "*" AlloyBatch: estimates costs for CostEstimator "1" --> "*" ElementComposition: calculates based on CostEstimator "1" --> "*" CostEstimation: produces estimations AlloyBatch "1" --> "1" CostEstimation: estimated by SupplierNetwork "1" --> "*" Supplier: finds vendors SupplierNetwork "1" --> "*" DesignConstraint: matches constraints QualityAssurance "1" --> "*" QualityAssuranceReview: conducts reviews AlloyBatch "1" --> "*" QualityAssuranceReview: reviewed in ReportGenerator "1" --> "*" SummaryReport: compiles reports ReportGenerator "*" --> "*" PerformanceMetric: compiles from metrics ReportGenerator "*" --> "*" QualityAssuranceReview: compiles from reviews @enduml ``` # Model 2 ``` @startuml skinparam classAttributeIconSize 0 hide empty members class AlloyBatch { creationDate: Date } class MaterialSpecimen { density: Float surfaceFinish: String } class ElementComposition { chemicalMakeup: Map } class PhaseDistribution { austenite: Float ferrite: Float martensite: Float pearlite: Float } class ExperimentPlanner { generateProfile() } class HeatTreatmentProfile { name: String quenchingStatus: Boolean processingSteps: List isValidated: Boolean } class PhaseDiagramCalculator { identifyStablePhases() checkEquilibrium() } class ProcessController { manageRun() } class ThermalAnalysisRun { runAnalysis() } class ThermalCycleSimulator { coolingRate: Float peakTemperature: Float } class SafetyProtocol { emergencyStop: Boolean temperatureLimit: Float } class ResearchProject { principalInvestigator: String budget: Decimal } class ExperimentalDataset { integrityVerified: Boolean filterResults() } class SpectroscopyData { wavelength: Float emissionIntensity: Float } class MicrostructureAnalysis { correlateData() refinePhases() } class StressTestRunner { testType: String performTest() } class PerformanceMetric { load: Float incrementStep: Integer } class OptimizationResult { convergence: Float } class DesignConstraint { limitValue: Float } class RegulatoryStandard { limitValue: Float effectiveDate: Date } class ComplianceArchive { storeRecord() } class BatchRecord { primaryPhase: String qualityStatus: String } class CostEstimator { calculateExpenses() } class SupplierNetwork { findVendors() } class QualityAssurance { inspector: String isCertified: Boolean approveBatch() } class ReportGenerator { format: String compileReport() } AlloyBatch "1" *-- "0..*" MaterialSpecimen MaterialSpecimen "1" *-- "1" ElementComposition MaterialSpecimen "1" *-- "1" PhaseDistribution ExperimentPlanner ..> HeatTreatmentProfile : generates HeatTreatmentProfile ..> PhaseDiagramCalculator : validated by ProcessController "1" --> "0..*" ThermalAnalysisRun : manages ThermalAnalysisRun "1" --> "1" HeatTreatmentProfile : applies ThermalAnalysisRun ..> ThermalCycleSimulator : utilizes ThermalAnalysisRun ..> SafetyProtocol : adheres to ResearchProject "1" *-- "0..*" ExperimentalDataset ResearchProject "1" --> "0..*" DesignConstraint ExperimentalDataset "1" *-- "0..*" SpectroscopyData MicrostructureAnalysis ..> MaterialSpecimen : correlates MicrostructureAnalysis ..> SpectroscopyData : correlates MicrostructureAnalysis ..> PhaseDiagramCalculator : references StressTestRunner ..> MaterialSpecimen : tests StressTestRunner ..> PerformanceMetric : generates OptimizationResult ..> PerformanceMetric : fed by OptimizationResult --> ElementComposition : recommends ComplianceArchive "1" *-- "0..*" BatchRecord BatchRecord "0..*" --> "1" AlloyBatch BatchRecord "0..*" --> "1" RegulatoryStandard CostEstimator ..> ElementComposition : calculates from SupplierNetwork ..> DesignConstraint : meets QualityAssurance ..> AlloyBatch : approves ReportGenerator ..> PerformanceMetric : compiles ReportGenerator ..> QualityAssurance : compiles @enduml ``` # Choices Please choose from the following 3 options based on the scoring criteria: A. Response 1 is better. B. Response 2 is better. C. Tie. Please provide criterion-by-criterion scores before the final choice. Use Tie if the total scores are equal or the meaningful quality difference is small. Also, you should pay adequate and same attention to both responses. **Important**：You should act as an IMPARTIAL judge and be as OBJECTIVE as possible. AVOID ANY POSITION BIASES and ensure that the ORDER in which the responses were presented DOES NOT influence your decision. Before choosing A/B/C, first score Model 1 and Model 2 independently against each specific instruction. If the specific instruction provides a scoring scale, use that scale; otherwise use a 1-5 score where 1 means very poor alignment and 5 means excellent alignment. Base the final choice on the independent scores and the evidence, not on which model is shown first. # Output Your output should be in the following format: ```result Scores: 1. <criterion name>: Model 1 = <score>, Model 2 = <score>; Evidence: <concrete evidence from both models> 2. <criterion name>: Model 1 = <score>, Model 2 = <score>; Evidence: <concrete evidence from both models> Total: Model 1 = <total>, Model 2 = <total> Choice: A Reason: 1. Criterion name: compare Model 1 and Model 2 using concrete evidence from both models. 2. Criterion name: compare Model 1 and Model 2 using concrete evidence from both models. 3. Rejected or checked issues: mention any tempting but unsupported issue that you did not use for the decision, if relevant. 4. Overall judgment: explain why the chosen model is better, or why it is a tie. ``` | G2: codex | H2: GLM5.2 | I2: ```result Scores: 1. Design aligns with requirement (all functionalities, no hallucinations/additions): Model 1 = 4, Model 2 = 3; Evidence: Model 1 covers all required concepts: AlloyBatch, MaterialSpecimen (with grainStructure and defectAnnotation attributes per "classify grain structure, and annotate any defects"), ElementComposition, PhaseDistribution, HeatTreatmentProfile (with isValidated per "validated before use"), ProcessingStep (supported by "define processing steps"), StressTestRunner/StressTestRun (separating runner from individual test runs), ResearchProject with principalInvestigator and budget, ExperimentalDataset, SpectroscopyData, MicrostructureAnalysis, PerformanceMetric, OptimizationResult, DesignConstraint (with effectiveDate), RegulatoryStandard (with effectiveDate), ComplianceArchive, BatchRecord, CostEstimator, SupplierNetwork, QualityAssurance, ReportGenerator, SummaryReport (with ReportFormat enum). Extra classes like CostEstimation and Supplier are reasonable refinements implied by "calculating raw material expenses" and "finding vendors." Model 2 misses ProcessingStep as a separate entity (uses processingSteps: List attribute), conflates StressTestRun into StressTestRunner (no separate test-run entity), lacks SummaryReport class (format as attribute on ReportGenerator), and critically omits effectiveDate from DesignConstraint despite the requirement stating "Design Constraints and Regulatory Standards, which specify limit values and effective dates." Model 2 also lacks grainStructure and defectAnnotation on MaterialSpecimen. 2. Conceptual classes and relationships (associations, cardinalities, types: inheritance, aggregation, composition): Model 1 = 4, Model 2 = 3; Evidence: Model 1 correctly uses composition for whole-part relationships (AlloyBatch "1" *-- "1..*" MaterialSpecimen, ResearchProject "1" *-- "1..*" ExperimentalDataset, ExperimentalDataset "1" *-- "*" SpectroscopyData) and directed associations for functional relationships. It correctly attributes "utilizes simulator" and "adheres to protocols" to ProcessController (ProcessController "1" --> "1" ThermalCycleSimulator: utilizes simulator; ProcessController "1" --> "1..*" SafetyProtocol: adheres to protocols), matching the requirement that says "a Process Controller manages Thermal Analysis Runs, utilizing a Thermal Cycle Simulator...while adhering to strict Safety Protocols." PhaseDiagramCalculator is linked to both HeatTreatmentProfile (planning) and MicrostructureAnalysis (analysis reference). Model 2 incorrectly places these relationships on ThermalAnalysisRun instead of ProcessController (ThermalAnalysisRun ..> ThermalCycleSimulator : utilizes; ThermalAnalysisRun ..> SafetyProtocol : adheres to), contradicting the requirement's subject. Model 2 also extensively uses dependency relationships (..>) instead of associations for structural connections (e.g., ExperimentPlanner ..> HeatTreatmentProfile, CostEstimator ..> ElementComposition, SupplierNetwork ..> DesignConstraint), which are semantically weaker and lose structural relationship meaning. However, Model 2 does have one advantage: OptimizationResult --> ElementComposition : recommends creates a proper structural link, whereas Model 1 uses recommendedComposition: String (a weaker representation). 3. Clarity in class names and optional inclusion of attributes: Model 1 = 5, Model 2 = 3; Evidence: Model 1 uses clear, domain-aligned class names and rich attributes with six enumerations (SurfaceFinish, PhaseType, TestType, QualityStatus, RunState, ReportFormat) providing domain type-safety. All attributes map to requirement details (e.g., SafetyProtocol has maxTemperatureLimit, minTemperatureLimit, emergencyStopEnabled per "emergency stop capabilities and temperature limits"). Model 2 has clear class names but uses methods/operations (e.g., generateProfile(), manageRun(), runAnalysis()) where attributes or relationships would be more appropriate for a domain class diagram. DesignConstraint is missing effectiveDate (explicitly required). ElementComposition uses chemicalMakeup: Map and HeatTreatmentProfile uses processingSteps: List, which are implementation-flavored types. MaterialSpecimen lacks grainStructure and defectAnnotation attributes. Some classes have no domain attributes at all (e.g., ThermalAnalysisRun only has runAnalysis()). Total: Model 1 = 13, Model 2 = 9 Choice: A Reason: 1. Design alignment: Model 1 covers all required functionalities comprehensively, including ProcessingStep, StressTestRun, and SummaryReport as proper entities, and correctly includes effectiveDate on both DesignConstraint and RegulatoryStandard. Model 2 omits effectiveDate from DesignConstraint (a direct requirement violation), conflates StressTestRunner with test runs, and lacks separate ProcessingStep and SummaryReport entities. 2. Relationships and cardinalities: Model 1 correctly attributes the "utilizes" and "adheres to" relationships to ProcessController as the requirement specifies, uses appropriate relationship types (composition for containment, associations for functional links), and provides comprehensive multiplicities. Model 2 misattributes these to ThermalAnalysisRun, overuses dependency arrows (..>) instead of structural associations, and loses the compositional semantics for several key relationships. 3. Clarity and attributes: Model 1 provides rich, domain-accurate attributes and enumerations that enhance semantic clarity. Model 2 uses implementation types (Map, List), omits required attributes (effectiveDate on DesignConstraint, grainStructure and defectAnnotation on MaterialSpecimen), and substitutes methods for structural attributes in several classes. 4. Rejected or checked issues: Model 2's advantage of putting coolingRate and peakTemperature on ThermalCycleSimulator (more accurate per "a Thermal Cycle Simulator to model cooling rates and peak temperatures") and linking OptimizationResult to ElementComposition via association were considered as positive factors, but they do not compensate for the missing classes, wrong relationship attributions, and absent required attributes. Model 1's extra classes (CostEstimation, Supplier) were checked against the "no additions" criterion but found to be reasonable refinements implied by the requirement text rather than hallucinations. 5. Overall judgment: Model 1 is clearly superior due to complete requirement coverage, correct relationship attribution, proper use of UML relationship types, and comprehensive domain-accurate attributes. Model 2 has several structural inaccuracies and missing required elements that undermine its alignment with the requirement. ``` | J2: A | K2: =IF(OR(J2="",C2="",E2=""),"",IF(J2="C","D(平局)",IF(J2=IF(E2="l2r","A","B"),LEFT(C2,1),RIGHT(C2,1)))) -> A | L2: A | M2: =IF(OR(K2="",L2=""),"",--(K2=L2)) -> 1
A3: AdvancedAlloyCompositionOptimization | B3: The Advanced Alloy Composition Optimization system supports research and industrial processes for developing high-performance metal alloys. The core unit of production is an Alloy Batch, created on a specific date, which contains multiple Material Specimens. Each specimen is defined by its density and surface finish, possesses a base Element Composition describing its chemical makeup, and has a current Phase Distribution detailing the fractions of target phases such as Austenite, Ferrite, Martensite, or Pearlite. Specimens can be analyzed to determine their current phase, classify grain structure, and annotate any defects. To achieve desired material properties, the system utilizes an Experiment Planner that generates Heat Treatment Profiles. These profiles, identified by name and quenching status, define processing steps and are validated before use. The planning process relies on a Phase Diagram Calculator to identify stable phases and check for equilibrium states. During execution, a Process Controller manages Thermal Analysis Runs, utilizing a Thermal Cycle Simulator to model cooling rates and peak temperatures while adhering to strict Safety Protocols that include emergency stop capabilities and temperature limits. Each thermal analysis run applies a specific profile. Data collection is organized under Research Projects, led by a principal investigator with a defined budget and associated design constraints. Projects encompass Experimental Datasets that verify data integrity, filter results, and store generated outcomes. These datasets aggregate Spectroscopy Data, which records wavelengths and emission intensities to detect phases and analyze elemental composition. Microstructure Analysis correlates specimen samples with spectroscopic data to refine phase distributions, utilizing the Phase Diagram Calculator as a reference. Furthermore, Stress Test Runners perform destructive or non-destructive tensile tests on specimens to generate Performance Metrics regarding load and increment steps. These metrics feed into Optimization Results that track convergence and recommend optimal element compositions. The system ensures adherence to engineering and legal standards through Design Constraints and Regulatory Standards, which specify limit values and effective dates to check specimen compliance. A Compliance Archive stores Batch Records, linking regulatory standards to specific batches; each record documents the primary phase, quality status, and the associated alloy batch. Operational support includes a Cost Estimator for calculating raw material expenses based on composition, a Supplier Network for finding vendors meeting design constraints, and a Quality Assurance module where certified inspectors approve batches. Finally, a Report Generator compiles performance metrics and quality assurance sources into summary reports in various formats. | C3: A vs B | D3: faithfulness | E3: r2l | F3: You are a professional software engineer with expertise across multiple domains. You evaluate UML class diagrams from the perspective of real-world software design, applying domain knowledge and engineering best practices alongside the provided scoring criteria. Please evaluate the two diagrams (Model 1, Model 2) based on the provided requirement and scoring criteria. # Criteria **CRITICAL INSTRUCTION**: You MUST evaluate the responses against EACH AND EVERY criterion listed in the "Specific Instructions" one by one. DO NOT aggregate, summarize, or skip any criterion. **Specific Instructions**: - Ensure that the design aligns with the given requirement strictly, achieving all the functionalities based on the requirements without making any hallucinations and additions. Ensure that the conceptual classes and their relationships accurately represent the essentials outlined in the requirement. This includes a detailed focus on the associations between classes, their cardinalities, and the types of relationships such as inheritance, aggregation, and composition. Clarity in class names and the optional inclusion of attributes are key for aligning with the project's vision. # Evaluation Guidelines ## General Rules - Consider only UML class diagram semantics (e.g., classes, attributes, associations, multiplicities, generalisation, composition/aggregation). - Ignore layout, styling, skinparams, comments, and notes. - If the response is incomplete or misses any required key component, regard it as a bad one. - Give credit for semantic clarity, but not for layout, comments, visibility markers, or other presentation-only differences. ## Forbidden Penalties (Strictly Enforced) You MUST NOT deduct points, lower scores, or claim a model is "worse", "complex", or "less practical" based on ANY of the following: 1. **Association Styles**: Using two opposite unidirectional associations (e.g., `A --> B` and `B --> A`) instead of one single bidirectional line (e.g., `A -- B`). They are 100% semantically equivalent. Treat opposite-direction associations as equivalent unless role labels, multiplicities, or navigability contradict the requirements. 2. **PlantUML Comments**: Using single-quote comments (e.g., `'opposite bank`) at the end of lines. These are standard tooling annotations — ignore them for scoring unless they obscure or contradict the relation meaning. 3. **Primitive Types**: Using common aliases for types (e.g., `int` instead of `Integer`, `str` instead of `String`, `boolean` instead of `Boolean`). Lowercase or language-flavored spellings are acceptable. 4. **Equivalent Multiplicity Literals**: Using `*` instead of `0..*`, or `1` instead of `1..1`. These pairs are semantically identical. 5. **Optional Abstractness**: Marking or not marking a superclass as `abstract` when the requirement does not say whether direct instances are allowed. Do not reward either style without requirement evidence. These forbidden factors must not appear as negative evidence under any criterion and must not affect criterion scores or the final choice. ## Evidence & Calibration Requirements - For every criterion you discuss, cite concrete evidence from both models. Quote or closely paraphrase the relevant class, attribute, association, multiplicity, inheritance, note, or missing element. - Do not claim a class, attribute, or association is missing when a synonymous or directly related element is present. If the present element is indirect, vague, over-constrained, or semantically weak, state that precise weakness instead. - Distinguish omissions from contradictions. Missing a hard constraint is usually less severe than explicitly modeling the opposite or an invalid multiplicity. - Do not reward a simpler model merely for being shorter if the more detailed model uses traceable intermediate workflow/concept classes required for domain reasoning. - Do not penalize a detailed model merely for using transparent refinements such as `Definition`, `Placement`, `Entry`, `Session`, `State`, `Record`, `Assignment`, `Arrangement`, or `Need` when the base requirement term remains recognizable. - Do not reward extra identifiers, timestamps, statuses, classes, or implementation-oriented detail unless they improve coverage of a stated requirement fact. - Text introduced by `e.g.`, `for example`, or `such as` gives examples, not a complete enumeration, unless the requirement explicitly declares a closed list. - Keep UML/PlantUML standards separate from domain accuracy. Domain-faithfulness problems, wrong business multiplicities, missing constraints, or vague semantics belong under the domain criteria, not UML standards, unless they make the notation invalid or unreadable. - When evaluating position bias, remember that Model 1 and Model 2 may be swapped in a second pass. Use only the content under each model block, not assumptions from prior comparisons or labels. # Requirement ``` The Advanced Alloy Composition Optimization system supports research and industrial processes for developing high-performance metal alloys. The core unit of production is an Alloy Batch, created on a specific date, which contains multiple Material Specimens. Each specimen is defined by its density and surface finish, possesses a base Element Composition describing its chemical makeup, and has a current Phase Distribution detailing the fractions of target phases such as Austenite, Ferrite, Martensite, or Pearlite. Specimens can be analyzed to determine their current phase, classify grain structure, and annotate any defects. To achieve desired material properties, the system utilizes an Experiment Planner that generates Heat Treatment Profiles. These profiles, identified by name and quenching status, define processing steps and are validated before use. The planning process relies on a Phase Diagram Calculator to identify stable phases and check for equilibrium states. During execution, a Process Controller manages Thermal Analysis Runs, utilizing a Thermal Cycle Simulator to model cooling rates and peak temperatures while adhering to strict Safety Protocols that include emergency stop capabilities and temperature limits. Each thermal analysis run applies a specific profile. Data collection is organized under Research Projects, led by a principal investigator with a defined budget and associated design constraints. Projects encompass Experimental Datasets that verify data integrity, filter results, and store generated outcomes. These datasets aggregate Spectroscopy Data, which records wavelengths and emission intensities to detect phases and analyze elemental composition. Microstructure Analysis correlates specimen samples with spectroscopic data to refine phase distributions, utilizing the Phase Diagram Calculator as a reference. Furthermore, Stress Test Runners perform destructive or non-destructive tensile tests on specimens to generate Performance Metrics regarding load and increment steps. These metrics feed into Optimization Results that track convergence and recommend optimal element compositions. The system ensures adherence to engineering and legal standards through Design Constraints and Regulatory Standards, which specify limit values and effective dates to check specimen compliance. A Compliance Archive stores Batch Records, linking regulatory standards to specific batches; each record documents the primary phase, quality status, and the associated alloy batch. Operational support includes a Cost Estimator for calculating raw material expenses based on composition, a Supplier Network for finding vendors meeting design constraints, and a Quality Assurance module where certified inspectors approve batches. Finally, a Report Generator compiles performance metrics and quality assurance sources into summary reports in various formats. ``` # Model 1 ``` @startuml skinparam classAttributeIconSize 0 hide empty members class AlloyBatch { creationDate: Date } class MaterialSpecimen { density: Float surfaceFinish: String } class ElementComposition { chemicalMakeup: Map } class PhaseDistribution { austenite: Float ferrite: Float martensite: Float pearlite: Float } class ExperimentPlanner { generateProfile() } class HeatTreatmentProfile { name: String quenchingStatus: Boolean processingSteps: List isValidated: Boolean } class PhaseDiagramCalculator { identifyStablePhases() checkEquilibrium() } class ProcessController { manageRun() } class ThermalAnalysisRun { runAnalysis() } class ThermalCycleSimulator { coolingRate: Float peakTemperature: Float } class SafetyProtocol { emergencyStop: Boolean temperatureLimit: Float } class ResearchProject { principalInvestigator: String budget: Decimal } class ExperimentalDataset { integrityVerified: Boolean filterResults() } class SpectroscopyData { wavelength: Float emissionIntensity: Float } class MicrostructureAnalysis { correlateData() refinePhases() } class StressTestRunner { testType: String performTest() } class PerformanceMetric { load: Float incrementStep: Integer } class OptimizationResult { convergence: Float } class DesignConstraint { limitValue: Float } class RegulatoryStandard { limitValue: Float effectiveDate: Date } class ComplianceArchive { storeRecord() } class BatchRecord { primaryPhase: String qualityStatus: String } class CostEstimator { calculateExpenses() } class SupplierNetwork { findVendors() } class QualityAssurance { inspector: String isCertified: Boolean approveBatch() } class ReportGenerator { format: String compileReport() } AlloyBatch "1" *-- "0..*" MaterialSpecimen MaterialSpecimen "1" *-- "1" ElementComposition MaterialSpecimen "1" *-- "1" PhaseDistribution ExperimentPlanner ..> HeatTreatmentProfile : generates HeatTreatmentProfile ..> PhaseDiagramCalculator : validated by ProcessController "1" --> "0..*" ThermalAnalysisRun : manages ThermalAnalysisRun "1" --> "1" HeatTreatmentProfile : applies ThermalAnalysisRun ..> ThermalCycleSimulator : utilizes ThermalAnalysisRun ..> SafetyProtocol : adheres to ResearchProject "1" *-- "0..*" ExperimentalDataset ResearchProject "1" --> "0..*" DesignConstraint ExperimentalDataset "1" *-- "0..*" SpectroscopyData MicrostructureAnalysis ..> MaterialSpecimen : correlates MicrostructureAnalysis ..> SpectroscopyData : correlates MicrostructureAnalysis ..> PhaseDiagramCalculator : references StressTestRunner ..> MaterialSpecimen : tests StressTestRunner ..> PerformanceMetric : generates OptimizationResult ..> PerformanceMetric : fed by OptimizationResult --> ElementComposition : recommends ComplianceArchive "1" *-- "0..*" BatchRecord BatchRecord "0..*" --> "1" AlloyBatch BatchRecord "0..*" --> "1" RegulatoryStandard CostEstimator ..> ElementComposition : calculates from SupplierNetwork ..> DesignConstraint : meets QualityAssurance ..> AlloyBatch : approves ReportGenerator ..> PerformanceMetric : compiles ReportGenerator ..> QualityAssurance : compiles @enduml ``` # Model 2 ``` @startuml ' Enumerations enum SurfaceFinish { POLISHED ROUGH MACHINED AS_CAST } enum PhaseType { AUSTENITE FERRITE MARTENSITE PEARLITE } enum TestType { DESTRUCTIVE NON_DESTRUCTIVE } enum QualityStatus { APPROVED REJECTED PENDING } enum RunState { INITIALIZED HEATING HOLDING COOLING COMPLETED EMERGENCY_STOP } enum ReportFormat { PDF CSV JSON HTML } ' Domain Classes class AlloyBatch { batchId: String creationDate: Date name: String } class MaterialSpecimen { specimenId: String density: double surfaceFinish: SurfaceFinish grainStructure: String defectAnnotation: String } class ElementComposition { elementName: String percentage: double } class PhaseDistribution { phaseType: PhaseType fraction: double } class ExperimentPlanner { plannerId: String name: String } class HeatTreatmentProfile { profileId: String name: String quenchingStatus: boolean isValidated: boolean } class ProcessingStep { stepOrder: int targetTemperature: double durationMinutes: int description: String } class PhaseDiagramCalculator { calculatorId: String name: String equilibriumState: boolean stablePhases: String } class ProcessController { controllerId: String name: String } class ThermalAnalysisRun { runId: String currentState: RunState peakTemperature: double coolingRate: double startTime: Date endTime: Date } class ThermalCycleSimulator { simulatorId: String name: String } class SafetyProtocol { protocolId: String maxTemperatureLimit: double minTemperatureLimit: double emergencyStopEnabled: boolean } class ResearchProject { projectId: String projectName: String principalInvestigator: String budget: double } class ExperimentalDataset { datasetId: String name: String dataIntegrityVerified: boolean creationDate: Date filterCriteria: String resultsFiltered: boolean } class SpectroscopyData { dataId: String wavelength: double emissionIntensity: double detectedPhase: PhaseType timestamp: Date } class MicrostructureAnalysis { analysisId: String correlatedPhase: PhaseType refinedFraction: double description: String } class StressTestRunner { runnerId: String name: String } class StressTestRun { testId: String testType: TestType maxLoad: double incrementStep: double timestamp: Date } class PerformanceMetric { metricId: String loadValue: double incrementValue: double stressValue: double strainValue: double } class OptimizationResult { resultId: String convergenceTracked: boolean iterationCount: int recommendedComposition: String } class DesignConstraint { constraintId: String constraintName: String limitValue: double effectiveDate: Date } class RegulatoryStandard { standardId: String standardName: String limitValue: double effectiveDate: Date } class ComplianceArchive { archiveId: String archiveDate: Date } class BatchRecord { recordId: String primaryPhase: PhaseType qualityStatus: QualityStatus recordDate: Date } class CostEstimator { estimatorId: String name: String } class CostEstimation { estimationId: String totalCost: double currency: String calculationDate: Date } class SupplierNetwork { networkId: String name: String } class Supplier { supplierId: String name: String meetsConstraints: boolean contactInfo: String } class QualityAssurance { moduleId: String name: String } class QualityAssuranceReview { reviewId: String inspectorName: String inspectorCertified: boolean approvalDate: Date isApproved: boolean } class ReportGenerator { generatorId: String name: String } class SummaryReport { reportId: String title: String format: ReportFormat generationDate: Date } ' Associations and Compositions AlloyBatch "1" *-- "1..*" MaterialSpecimen: contains specimens MaterialSpecimen "1" *-- "1..*" ElementComposition: base composition MaterialSpecimen "1" *-- "1..*" PhaseDistribution: current phases ExperimentPlanner "1" --> "1..*" HeatTreatmentProfile: generates profiles HeatTreatmentProfile "1" *-- "1..*" ProcessingStep: defined steps PhaseDiagramCalculator "1" --> "*" HeatTreatmentProfile: references for planning PhaseDiagramCalculator "1" --> "*" MicrostructureAnalysis: references for analysis ProcessController "1" --> "1..*" ThermalAnalysisRun: manages runs ProcessController "1" --> "1" ThermalCycleSimulator: utilizes simulator ProcessController "1" --> "1..*" SafetyProtocol: adheres to protocols ThermalCycleSimulator "1" --> "*" ThermalAnalysisRun: simulates ThermalAnalysisRun "*" --> "1" HeatTreatmentProfile: applies profile ResearchProject "1" *-- "1..*" ExperimentalDataset: encompassed datasets ResearchProject "1" --> "1..*" DesignConstraint: associated constraints ExperimentalDataset "1" *-- "*" SpectroscopyData: aggregated data ExperimentalDataset "1" *-- "*" MicrostructureAnalysis: included analyses MicrostructureAnalysis "*" --> "1" MaterialSpecimen: correlates specimen MicrostructureAnalysis "*" --> "1" SpectroscopyData: correlates spectroscopic data StressTestRunner "1" --> "1..*" StressTestRun: performs tests MaterialSpecimen "1" --> "*" StressTestRun: tested in StressTestRun "1" *-- "1..*" PerformanceMetric: generated metrics PerformanceMetric "*" --> "1" OptimizationResult: feeds into ComplianceArchive "1" *-- "1..*" BatchRecord: stored records BatchRecord "*" --> "1" AlloyBatch: documents batch BatchRecord "*" --> "1..*" RegulatoryStandard: linked standards CostEstimator "1" --> "*" AlloyBatch: estimates costs for CostEstimator "1" --> "*" ElementComposition: calculates based on CostEstimator "1" --> "*" CostEstimation: produces estimations AlloyBatch "1" --> "1" CostEstimation: estimated by SupplierNetwork "1" --> "*" Supplier: finds vendors SupplierNetwork "1" --> "*" DesignConstraint: matches constraints QualityAssurance "1" --> "*" QualityAssuranceReview: conducts reviews AlloyBatch "1" --> "*" QualityAssuranceReview: reviewed in ReportGenerator "1" --> "*" SummaryReport: compiles reports ReportGenerator "*" --> "*" PerformanceMetric: compiles from metrics ReportGenerator "*" --> "*" QualityAssuranceReview: compiles from reviews @enduml ``` # Choices Please choose from the following 3 options based on the scoring criteria: A. Response 1 is better. B. Response 2 is better. C. Tie. Please provide criterion-by-criterion scores before the final choice. Use Tie if the total scores are equal or the meaningful quality difference is small. Also, you should pay adequate and same attention to both responses. **Important**：You should act as an IMPARTIAL judge and be as OBJECTIVE as possible. AVOID ANY POSITION BIASES and ensure that the ORDER in which the responses were presented DOES NOT influence your decision. Before choosing A/B/C, first score Model 1 and Model 2 independently against each specific instruction. If the specific instruction provides a scoring scale, use that scale; otherwise use a 1-5 score where 1 means very poor alignment and 5 means excellent alignment. Base the final choice on the independent scores and the evidence, not on which model is shown first. # Output Your output should be in the following format: ```result Scores: 1. <criterion name>: Model 1 = <score>, Model 2 = <score>; Evidence: <concrete evidence from both models> 2. <criterion name>: Model 1 = <score>, Model 2 = <score>; Evidence: <concrete evidence from both models> Total: Model 1 = <total>, Model 2 = <total> Choice: A Reason: 1. Criterion name: compare Model 1 and Model 2 using concrete evidence from both models. 2. Criterion name: compare Model 1 and Model 2 using concrete evidence from both models. 3. Rejected or checked issues: mention any tempting but unsupported issue that you did not use for the decision, if relevant. 4. Overall judgment: explain why the chosen model is better, or why it is a tie. ``` | G3: codex | H3: GLM5.2 | I3: Based on my thorough trace of every requirement element against both models, I now have enough evidence to evaluate criterion-by-criterion. ```result Scores: 1. Strict requirement alignment (all functionalities, no hallucinations): Model 1 = 2.5, Model 2 = 3.5; Evidence: M1 omits `grainStructure` and `defectAnnotation` from MaterialSpecimen (requirement: "classify grain structure, and annotate any defects"), omits `effectiveDate` from DesignConstraint (requirement: "specify limit values and effective dates"), and omits `detectedPhase` from SpectroscopyData (requirement: "detect phases"). M2 includes all of these (`grainStructure`, `defectAnnotation`, `detectedPhase`, `effectiveDate` on DesignConstraint). However, M2 misplaces `coolingRate`/`peakTemperature` onto `ThermalAnalysisRun` rather than `ThermalCycleSimulator` (requirement: "utilizing a Thermal Cycle Simulator to model cooling rates and peak temperatures"), and loses the `OptimizationResult → ElementComposition` recommendation link (only `recommendedComposition: String`). M1 correctly places simulator attributes and the recommends-link. M2's extra classes (ProcessingStep, StressTestRun, CostEstimation, Supplier, SummaryReport) are transparent refinements mapping to requirement facts, not hallucinations. 2. Conceptual classes and relationships accurately represent essentials: Model 1 = 3, Model 2 = 3.5; Evidence: Both contain all core classes. M1 models most cross-cutting links as dependencies (`..>`) without cardinality (e.g., `ExperimentPlanner ..> HeatTreatmentProfile`, `MicrostructureAnalysis ..> PhaseDiagramCalculator`, `CostEstimator ..> ElementComposition`), which weakens structural representation. M2 uses proper associations with cardinalities throughout and adds recognizable refinement classes (Supplier↔"vendors", SummaryReport↔"summary reports", ProcessingStep↔"processing steps"). M2 reverses the `MicrostructureAnalysis → PhaseDiagramCalculator` direction (`PhaseDiagramCalculator "1" --> "*" MicrostructureAnalysis` vs. requirement "utilizing the Phase Diagram Calculator as a reference"), and reverses `PhaseDiagramCalculator → HeatTreatmentProfile`; M1 has the correct direction for the MicrostructureAnalysis reference. 3. Associations, cardinalities, and relationship types: Model 1 = 2.5, Model 2 = 3.5; Evidence: M1 uses composition correctly for part-whole links (`AlloyBatch *-- MaterialSpecimen`, `ResearchProject *-- ExperimentalDataset`, `ComplianceArchive *-- BatchRecord`). But `ThermalAnalysisRun "1" --> "1" HeatTreatmentProfile` is too restrictive (a profile can be applied by multiple runs; M2's `"*" --> "1"` is correct), `BatchRecord "0..*" --> "1" RegulatoryStandard` allows only one standard (requirement: "linking regulatory standards", plural; M2's `"*" --> "1..*"` is correct), and M1 attributes "utilizes simulator"/"adheres to protocols" to `ThermalAnalysisRun` rather than `ProcessController` (requirement subject is ProcessController). M2 correctly attributes all three to `ProcessController` and has correct multiplicities for profile and standards, though M2's reversed MicrostructureAnalysis navigability is one error. M1's `AlloyBatch "1" *-- "0..*"` allows zero specimens vs. requirement "contains multiple". 4. Clarity in class names and optional attributes: Model 1 = 3.5, Model 2 = 4; Evidence: Both use clear, requirement-matching class names. M2 adds typed enums (`TestType{DESTRUCTIVE,NON_DESTRUCTIVE}`, `QualityStatus`, `PhaseType`, `ReportFormat`) that directly map to requirement facts ("destructive or non-destructive", "quality status", "various formats"), improving semantic clarity. M1 uses `testType: String` and `format: String` (acceptable but less precise). M1 hardcodes the four phase fractions as named attributes (`austenite`, `ferrite`, `martensite`, `pearlite`) which slightly over-constrains the "such as" non-closed list; M2's `phaseType` enum + `fraction` is more faithful. Total: Model 1 = 11.5, Model 2 = 14.5 Choice: B Reason: 1. Strict requirement alignment: M2 covers more requirement attributes (grainStructure, defectAnnotation, detectedPhase, DesignConstraint.effectiveDate) that M1 omits entirely. M2's extra classes are transparent refinements tied to requirement facts (Supplier↔"vendors", SummaryReport↔"summary reports", ProcessingStep↔"processing steps"), not hallucinations. M1 does better on three specific points (simulator attribute placement, MicrostructureAnalysis→Calculator direction, OptimizationResult→ElementComposition recommends link), but these are outweighed by its larger set of omissions. 2. Associations and cardinalities: M2 is clearly stronger — correct `ThermalAnalysisRun "*" --> "1" HeatTreatmentProfile`, correct `BatchRecord "*" --> "1..*" RegulatoryStandard` (plural standards), and correct ProcessController attribution for simulator/protocols. M1 has the restrictive `1..1` profile multiplicity, single-standard BatchRecord, and misattributed simulator/protocol links, plus relies heavily on uncardinalized dependencies. 3. Rejected or checked issues: I did not penalize M2 for implementation-oriented ids/timestamps (per guidelines, not rewarded but not penalized). I did not penalize M1 for using `Float`/`int` or `*` literals. I did not reward M2 merely for being longer — its additional classes were credited only where they map to stated requirement facts. M1's hardcoded four phase attributes were noted as slightly over-constrained by the "such as" phrasing but not heavily penalized. M2's reversed PhaseDiagramCalculator directions (to both HeatTreatmentProfile and MicrostructureAnalysis) were counted as domain/navigability errors, reducing its criterion-2/3 scores but not enough to override its coverage advantage. 4. Overall judgment: M2 is better. It achieves broader functional coverage of the requirement, uses proper associations with correct cardinalities, correctly attributes ProcessController's three responsibilities, and models standards/batch-record multiplicities faithfully. M1 is more compact but omits several stated attributes, uses dependency arrows without cardinality for most structural relationships, and has multiple multiplicity/attribution errors. M2's three directional/placement errors are real but fewer and less pervasive than M1's combined omissions and cardinality mistakes. ``` | J3: B | K3: =IF(OR(J3="",C3="",E3=""),"",IF(J3="C","D(平局)",IF(J3=IF(E3="l2r","A","B"),LEFT(C3,1),RIGHT(C3,1)))) -> A | L3: A | M3: =IF(OR(K3="",L3=""),"",--(K3=L3)) -> 1
A4: AdvancedAlloyCompositionOptimization | B4: The Advanced Alloy Composition Optimization system supports research and industrial processes for developing high-performance metal alloys. The core unit of production is an Alloy Batch, created on a specific date, which contains multiple Material Specimens. Each specimen is defined by its density and surface finish, possesses a base Element Composition describing its chemical makeup, and has a current Phase Distribution detailing the fractions of target phases such as Austenite, Ferrite, Martensite, or Pearlite. Specimens can be analyzed to determine their current phase, classify grain structure, and annotate any defects. To achieve desired material properties, the system utilizes an Experiment Planner that generates Heat Treatment Profiles. These profiles, identified by name and quenching status, define processing steps and are validated before use. The planning process relies on a Phase Diagram Calculator to identify stable phases and check for equilibrium states. During execution, a Process Controller manages Thermal Analysis Runs, utilizing a Thermal Cycle Simulator to model cooling rates and peak temperatures while adhering to strict Safety Protocols that include emergency stop capabilities and temperature limits. Each thermal analysis run applies a specific profile. Data collection is organized under Research Projects, led by a principal investigator with a defined budget and associated design constraints. Projects encompass Experimental Datasets that verify data integrity, filter results, and store generated outcomes. These datasets aggregate Spectroscopy Data, which records wavelengths and emission intensities to detect phases and analyze elemental composition. Microstructure Analysis correlates specimen samples with spectroscopic data to refine phase distributions, utilizing the Phase Diagram Calculator as a reference. Furthermore, Stress Test Runners perform destructive or non-destructive tensile tests on specimens to generate Performance Metrics regarding load and increment steps. These metrics feed into Optimization Results that track convergence and recommend optimal element compositions. The system ensures adherence to engineering and legal standards through Design Constraints and Regulatory Standards, which specify limit values and effective dates to check specimen compliance. A Compliance Archive stores Batch Records, linking regulatory standards to specific batches; each record documents the primary phase, quality status, and the associated alloy batch. Operational support includes a Cost Estimator for calculating raw material expenses based on composition, a Supplier Network for finding vendors meeting design constraints, and a Quality Assurance module where certified inspectors approve batches. Finally, a Report Generator compiles performance metrics and quality assurance sources into summary reports in various formats. | C4: A vs B | D4: five | E4: l2r | F4: You are a professional software engineer with expertise across multiple domains. You evaluate UML class diagrams from the perspective of real-world software design, applying domain knowledge and engineering best practices alongside the provided scoring criteria. Please evaluate the two diagrams (Model 1, Model 2) based on the provided requirement and scoring criteria. # Criteria **CRITICAL INSTRUCTION**: You MUST evaluate the responses against EACH AND EVERY criterion listed in the "Specific Instructions" one by one. DO NOT aggregate, summarize, or skip any criterion. **Specific Instructions**: - Appropriate conceptual classes aligned with the domain 1− Very Poor: Classes are mostly incorrect or irrelevant and do not accurately represent the domain. 2− Poor: Only a few classes are correct, but the majority of the domain concepts are missing or incorrect. 3− Fair: Some classes are correctly identified, but noticeable misalignments are still present. 4− Good: Most classes are correctly identified with only minor misalignments 5− Excellent: All classes are correctly identified, fully aligned with the domain. - Associations/Multiplicities between classes for domain reasoning 1− Very Poor: Associations/multiplicities are largely missing or incorrect, comprising domain reasoning. 2− Poor: Few correct associations/multiplicities with critical relationships missing. 3− Fair: Some associations/multiplicities are correct, but noticeable missing or misrepresentations remain. 4− Good: Most associations/multiplicities are correctly identified with only minor errors. 5− Excellent: All essential associations/multiplicities correctly applied. - Model attributes with appropriate data types 1− Very Poor: Attributes and data types are poorly identified and modeled; largely incorrect or irrelevant. 2− Poor: Few attributes are correct with proper types; critical attributes are missing. 3− Fair: Some attributes are correct with proper types, but significant attributes are still missing. 4− Good: Most attributes are appropriately modeled with proper data types; minor type issues may exist. 5− Excellent: All attributes are correctly modeled with appropriate data types. - Consistencies of Terminology with given context 1− Very Poor: Terminology is largely inconsistent with the given context 2− Poor: Frequent inconsistencies; critical terms misused or missing. 3− Fair: Some terminology is correct, but noticeable inconsistencies remain. 4− Good: Most terminology aligns with the given context, with minor inconsistencies. 5− Excellent: Terminology is fully consistent with the given context. - Adherence of UML class diagram standards 1− Very Poor: Poor diagram formation with major UML standards ignored, making it largely incomprehensible. 2− Poor: Frequent UML violations; diagram is difficult to interpret. 3− Fair: Some UML/PlantUML syntax errors, but major representations are still missing. 4− Good: Minor UML/PlantUML notation errors; overall diagram remains understandable. 5− Excellent: Fully adheres to UML/PlantUML syntax, notation, and conventions. # Evaluation Guidelines ## General Rules - Consider only UML class diagram semantics (e.g., classes, attributes, associations, multiplicities, generalisation, composition/aggregation). - Ignore layout, styling, skinparams, comments, and notes. - If the response is incomplete or misses any required key component, regard it as a bad one. - Give credit for semantic clarity, but not for layout, comments, visibility markers, or other presentation-only differences. ## Forbidden Penalties (Strictly Enforced) You MUST NOT deduct points, lower scores, or claim a model is "worse", "complex", or "less practical" based on ANY of the following: 1. **Association Styles**: Using two opposite unidirectional associations (e.g., `A --> B` and `B --> A`) instead of one single bidirectional line (e.g., `A -- B`). They are 100% semantically equivalent. Treat opposite-direction associations as equivalent unless role labels, multiplicities, or navigability contradict the requirements. 2. **PlantUML Comments**: Using single-quote comments (e.g., `'opposite bank`) at the end of lines. These are standard tooling annotations — ignore them for scoring unless they obscure or contradict the relation meaning. 3. **Primitive Types**: Using common aliases for types (e.g., `int` instead of `Integer`, `str` instead of `String`, `boolean` instead of `Boolean`). Lowercase or language-flavored spellings are acceptable. 4. **Equivalent Multiplicity Literals**: Using `*` instead of `0..*`, or `1` instead of `1..1`. These pairs are semantically identical. 5. **Optional Abstractness**: Marking or not marking a superclass as `abstract` when the requirement does not say whether direct instances are allowed. Do not reward either style without requirement evidence. These forbidden factors must not appear as negative evidence under any criterion and must not affect criterion scores or the final choice. ## Evidence & Calibration Requirements - For every criterion you discuss, cite concrete evidence from both models. Quote or closely paraphrase the relevant class, attribute, association, multiplicity, inheritance, note, or missing element. - Do not claim a class, attribute, or association is missing when a synonymous or directly related element is present. If the present element is indirect, vague, over-constrained, or semantically weak, state that precise weakness instead. - Distinguish omissions from contradictions. Missing a hard constraint is usually less severe than explicitly modeling the opposite or an invalid multiplicity. - Do not reward a simpler model merely for being shorter if the more detailed model uses traceable intermediate workflow/concept classes required for domain reasoning. - Do not penalize a detailed model merely for using transparent refinements such as `Definition`, `Placement`, `Entry`, `Session`, `State`, `Record`, `Assignment`, `Arrangement`, or `Need` when the base requirement term remains recognizable. - Do not reward extra identifiers, timestamps, statuses, classes, or implementation-oriented detail unless they improve coverage of a stated requirement fact. - Text introduced by `e.g.`, `for example`, or `such as` gives examples, not a complete enumeration, unless the requirement explicitly declares a closed list. - Keep UML/PlantUML standards separate from domain accuracy. Domain-faithfulness problems, wrong business multiplicities, missing constraints, or vague semantics belong under the domain criteria, not UML standards, unless they make the notation invalid or unreadable. - When evaluating position bias, remember that Model 1 and Model 2 may be swapped in a second pass. Use only the content under each model block, not assumptions from prior comparisons or labels. # Requirement ``` The Advanced Alloy Composition Optimization system supports research and industrial processes for developing high-performance metal alloys. The core unit of production is an Alloy Batch, created on a specific date, which contains multiple Material Specimens. Each specimen is defined by its density and surface finish, possesses a base Element Composition describing its chemical makeup, and has a current Phase Distribution detailing the fractions of target phases such as Austenite, Ferrite, Martensite, or Pearlite. Specimens can be analyzed to determine their current phase, classify grain structure, and annotate any defects. To achieve desired material properties, the system utilizes an Experiment Planner that generates Heat Treatment Profiles. These profiles, identified by name and quenching status, define processing steps and are validated before use. The planning process relies on a Phase Diagram Calculator to identify stable phases and check for equilibrium states. During execution, a Process Controller manages Thermal Analysis Runs, utilizing a Thermal Cycle Simulator to model cooling rates and peak temperatures while adhering to strict Safety Protocols that include emergency stop capabilities and temperature limits. Each thermal analysis run applies a specific profile. Data collection is organized under Research Projects, led by a principal investigator with a defined budget and associated design constraints. Projects encompass Experimental Datasets that verify data integrity, filter results, and store generated outcomes. These datasets aggregate Spectroscopy Data, which records wavelengths and emission intensities to detect phases and analyze elemental composition. Microstructure Analysis correlates specimen samples with spectroscopic data to refine phase distributions, utilizing the Phase Diagram Calculator as a reference. Furthermore, Stress Test Runners perform destructive or non-destructive tensile tests on specimens to generate Performance Metrics regarding load and increment steps. These metrics feed into Optimization Results that track convergence and recommend optimal element compositions. The system ensures adherence to engineering and legal standards through Design Constraints and Regulatory Standards, which specify limit values and effective dates to check specimen compliance. A Compliance Archive stores Batch Records, linking regulatory standards to specific batches; each record documents the primary phase, quality status, and the associated alloy batch. Operational support includes a Cost Estimator for calculating raw material expenses based on composition, a Supplier Network for finding vendors meeting design constraints, and a Quality Assurance module where certified inspectors approve batches. Finally, a Report Generator compiles performance metrics and quality assurance sources into summary reports in various formats. ``` # Model 1 ``` @startuml ' Enumerations enum SurfaceFinish { POLISHED ROUGH MACHINED AS_CAST } enum PhaseType { AUSTENITE FERRITE MARTENSITE PEARLITE } enum TestType { DESTRUCTIVE NON_DESTRUCTIVE } enum QualityStatus { APPROVED REJECTED PENDING } enum RunState { INITIALIZED HEATING HOLDING COOLING COMPLETED EMERGENCY_STOP } enum ReportFormat { PDF CSV JSON HTML } ' Domain Classes class AlloyBatch { batchId: String creationDate: Date name: String } class MaterialSpecimen { specimenId: String density: double surfaceFinish: SurfaceFinish grainStructure: String defectAnnotation: String } class ElementComposition { elementName: String percentage: double } class PhaseDistribution { phaseType: PhaseType fraction: double } class ExperimentPlanner { plannerId: String name: String } class HeatTreatmentProfile { profileId: String name: String quenchingStatus: boolean isValidated: boolean } class ProcessingStep { stepOrder: int targetTemperature: double durationMinutes: int description: String } class PhaseDiagramCalculator { calculatorId: String name: String equilibriumState: boolean stablePhases: String } class ProcessController { controllerId: String name: String } class ThermalAnalysisRun { runId: String currentState: RunState peakTemperature: double coolingRate: double startTime: Date endTime: Date } class ThermalCycleSimulator { simulatorId: String name: String } class SafetyProtocol { protocolId: String maxTemperatureLimit: double minTemperatureLimit: double emergencyStopEnabled: boolean } class ResearchProject { projectId: String projectName: String principalInvestigator: String budget: double } class ExperimentalDataset { datasetId: String name: String dataIntegrityVerified: boolean creationDate: Date filterCriteria: String resultsFiltered: boolean } class SpectroscopyData { dataId: String wavelength: double emissionIntensity: double detectedPhase: PhaseType timestamp: Date } class MicrostructureAnalysis { analysisId: String correlatedPhase: PhaseType refinedFraction: double description: String } class StressTestRunner { runnerId: String name: String } class StressTestRun { testId: String testType: TestType maxLoad: double incrementStep: double timestamp: Date } class PerformanceMetric { metricId: String loadValue: double incrementValue: double stressValue: double strainValue: double } class OptimizationResult { resultId: String convergenceTracked: boolean iterationCount: int recommendedComposition: String } class DesignConstraint { constraintId: String constraintName: String limitValue: double effectiveDate: Date } class RegulatoryStandard { standardId: String standardName: String limitValue: double effectiveDate: Date } class ComplianceArchive { archiveId: String archiveDate: Date } class BatchRecord { recordId: String primaryPhase: PhaseType qualityStatus: QualityStatus recordDate: Date } class CostEstimator { estimatorId: String name: String } class CostEstimation { estimationId: String totalCost: double currency: String calculationDate: Date } class SupplierNetwork { networkId: String name: String } class Supplier { supplierId: String name: String meetsConstraints: boolean contactInfo: String } class QualityAssurance { moduleId: String name: String } class QualityAssuranceReview { reviewId: String inspectorName: String inspectorCertified: boolean approvalDate: Date isApproved: boolean } class ReportGenerator { generatorId: String name: String } class SummaryReport { reportId: String title: String format: ReportFormat generationDate: Date } ' Associations and Compositions AlloyBatch "1" *-- "1..*" MaterialSpecimen: contains specimens MaterialSpecimen "1" *-- "1..*" ElementComposition: base composition MaterialSpecimen "1" *-- "1..*" PhaseDistribution: current phases ExperimentPlanner "1" --> "1..*" HeatTreatmentProfile: generates profiles HeatTreatmentProfile "1" *-- "1..*" ProcessingStep: defined steps PhaseDiagramCalculator "1" --> "*" HeatTreatmentProfile: references for planning PhaseDiagramCalculator "1" --> "*" MicrostructureAnalysis: references for analysis ProcessController "1" --> "1..*" ThermalAnalysisRun: manages runs ProcessController "1" --> "1" ThermalCycleSimulator: utilizes simulator ProcessController "1" --> "1..*" SafetyProtocol: adheres to protocols ThermalCycleSimulator "1" --> "*" ThermalAnalysisRun: simulates ThermalAnalysisRun "*" --> "1" HeatTreatmentProfile: applies profile ResearchProject "1" *-- "1..*" ExperimentalDataset: encompassed datasets ResearchProject "1" --> "1..*" DesignConstraint: associated constraints ExperimentalDataset "1" *-- "*" SpectroscopyData: aggregated data ExperimentalDataset "1" *-- "*" MicrostructureAnalysis: included analyses MicrostructureAnalysis "*" --> "1" MaterialSpecimen: correlates specimen MicrostructureAnalysis "*" --> "1" SpectroscopyData: correlates spectroscopic data StressTestRunner "1" --> "1..*" StressTestRun: performs tests MaterialSpecimen "1" --> "*" StressTestRun: tested in StressTestRun "1" *-- "1..*" PerformanceMetric: generated metrics PerformanceMetric "*" --> "1" OptimizationResult: feeds into ComplianceArchive "1" *-- "1..*" BatchRecord: stored records BatchRecord "*" --> "1" AlloyBatch: documents batch BatchRecord "*" --> "1..*" RegulatoryStandard: linked standards CostEstimator "1" --> "*" AlloyBatch: estimates costs for CostEstimator "1" --> "*" ElementComposition: calculates based on CostEstimator "1" --> "*" CostEstimation: produces estimations AlloyBatch "1" --> "1" CostEstimation: estimated by SupplierNetwork "1" --> "*" Supplier: finds vendors SupplierNetwork "1" --> "*" DesignConstraint: matches constraints QualityAssurance "1" --> "*" QualityAssuranceReview: conducts reviews AlloyBatch "1" --> "*" QualityAssuranceReview: reviewed in ReportGenerator "1" --> "*" SummaryReport: compiles reports ReportGenerator "*" --> "*" PerformanceMetric: compiles from metrics ReportGenerator "*" --> "*" QualityAssuranceReview: compiles from reviews @enduml ``` # Model 2 ``` @startuml skinparam classAttributeIconSize 0 hide empty members class AlloyBatch { creationDate: Date } class MaterialSpecimen { density: Float surfaceFinish: String } class ElementComposition { chemicalMakeup: Map } class PhaseDistribution { austenite: Float ferrite: Float martensite: Float pearlite: Float } class ExperimentPlanner { generateProfile() } class HeatTreatmentProfile { name: String quenchingStatus: Boolean processingSteps: List isValidated: Boolean } class PhaseDiagramCalculator { identifyStablePhases() checkEquilibrium() } class ProcessController { manageRun() } class ThermalAnalysisRun { runAnalysis() } class ThermalCycleSimulator { coolingRate: Float peakTemperature: Float } class SafetyProtocol { emergencyStop: Boolean temperatureLimit: Float } class ResearchProject { principalInvestigator: String budget: Decimal } class ExperimentalDataset { integrityVerified: Boolean filterResults() } class SpectroscopyData { wavelength: Float emissionIntensity: Float } class MicrostructureAnalysis { correlateData() refinePhases() } class StressTestRunner { testType: String performTest() } class PerformanceMetric { load: Float incrementStep: Integer } class OptimizationResult { convergence: Float } class DesignConstraint { limitValue: Float } class RegulatoryStandard { limitValue: Float effectiveDate: Date } class ComplianceArchive { storeRecord() } class BatchRecord { primaryPhase: String qualityStatus: String } class CostEstimator { calculateExpenses() } class SupplierNetwork { findVendors() } class QualityAssurance { inspector: String isCertified: Boolean approveBatch() } class ReportGenerator { format: String compileReport() } AlloyBatch "1" *-- "0..*" MaterialSpecimen MaterialSpecimen "1" *-- "1" ElementComposition MaterialSpecimen "1" *-- "1" PhaseDistribution ExperimentPlanner ..> HeatTreatmentProfile : generates HeatTreatmentProfile ..> PhaseDiagramCalculator : validated by ProcessController "1" --> "0..*" ThermalAnalysisRun : manages ThermalAnalysisRun "1" --> "1" HeatTreatmentProfile : applies ThermalAnalysisRun ..> ThermalCycleSimulator : utilizes ThermalAnalysisRun ..> SafetyProtocol : adheres to ResearchProject "1" *-- "0..*" ExperimentalDataset ResearchProject "1" --> "0..*" DesignConstraint ExperimentalDataset "1" *-- "0..*" SpectroscopyData MicrostructureAnalysis ..> MaterialSpecimen : correlates MicrostructureAnalysis ..> SpectroscopyData : correlates MicrostructureAnalysis ..> PhaseDiagramCalculator : references StressTestRunner ..> MaterialSpecimen : tests StressTestRunner ..> PerformanceMetric : generates OptimizationResult ..> PerformanceMetric : fed by OptimizationResult --> ElementComposition : recommends ComplianceArchive "1" *-- "0..*" BatchRecord BatchRecord "0..*" --> "1" AlloyBatch BatchRecord "0..*" --> "1" RegulatoryStandard CostEstimator ..> ElementComposition : calculates from SupplierNetwork ..> DesignConstraint : meets QualityAssurance ..> AlloyBatch : approves ReportGenerator ..> PerformanceMetric : compiles ReportGenerator ..> QualityAssurance : compiles @enduml ``` # Choices Please choose from the following 3 options based on the scoring criteria: A. Response 1 is better. B. Response 2 is better. C. Tie. Please provide criterion-by-criterion scores before the final choice. Use Tie if the total scores are equal or the meaningful quality difference is small. Also, you should pay adequate and same attention to both responses. **Important**：You should act as an IMPARTIAL judge and be as OBJECTIVE as possible. AVOID ANY POSITION BIASES and ensure that the ORDER in which the responses were presented DOES NOT influence your decision. Before choosing A/B/C, first score Model 1 and Model 2 independently against each specific instruction. If the specific instruction provides a scoring scale, use that scale; otherwise use a 1-5 score where 1 means very poor alignment and 5 means excellent alignment. Base the final choice on the independent scores and the evidence, not on which model is shown first. # Output Your output should be in the following format: ```result Scores: 1. <criterion name>: Model 1 = <score>, Model 2 = <score>; Evidence: <concrete evidence from both models> 2. <criterion name>: Model 1 = <score>, Model 2 = <score>; Evidence: <concrete evidence from both models> Total: Model 1 = <total>, Model 2 = <total> Choice: A Reason: 1. Criterion name: compare Model 1 and Model 2 using concrete evidence from both models. 2. Criterion name: compare Model 1 and Model 2 using concrete evidence from both models. 3. Rejected or checked issues: mention any tempting but unsupported issue that you did not use for the decision, if relevant. 4. Overall judgment: explain why the chosen model is better, or why it is a tie. ``` | G4: codex | H4: GLM5.2 | I4: ```result Scores: 1. Appropriate conceptual classes aligned with the domain: Model 1 = 5, Model 2 = 4; Evidence: Model 1 includes all 26 required domain classes (e.g., AlloyBatch, MaterialSpecimen, PhaseDistribution, HeatTreatmentProfile, PhaseDiagramCalculator, ThermalCycleSimulator, SafetyProtocol, MicrostructureAnalysis, StressTestRunner, OptimizationResult, ComplianceArchive, BatchRecord, QualityAssurance, ReportGenerator) plus reasonable refinements: ProcessingStep (profiles "define processing steps"), StressTestRun (tensile tests on specimens), Supplier (vendors in SupplierNetwork), QualityAssuranceReview (inspectors approve batches), SummaryReport (reports in various formats), CostEstimation. Model 2 includes all core classes but collapses several: no ProcessingStep (uses `processingSteps: List` attribute), no StressTestRun (conflates testType into StressTestRunner), no Supplier, no SummaryReport, no CostEstimation, no QualityAssuranceReview. Model 2 also lacks enums for PhaseType, TestType, QualityStatus, ReportFormat which the domain explicitly enumerates. 2. Associations/Multiplicities between classes for domain reasoning: Model 1 = 4, Model 2 = 3; Evidence: Model 1 specifies multiplicities on virtually all associations (e.g., `AlloyBatch "1" *-- "1..*" MaterialSpecimen`, `ThermalAnalysisRun "*" --> "1" HeatTreatmentProfile`, `ExperimentalDataset "1" *-- "*" SpectroscopyData`, `ComplianceArchive "1" *-- "1..*" BatchRecord`). Model 2 uses `..>` dependency arrows without multiplicities for many critical relationships (e.g., `ExperimentPlanner ..> HeatTreatmentProfile`, `MicrostructureAnalysis ..> MaterialSpecimen`, `StressTestRunner ..> MaterialSpecimen`, `ReportGenerator ..> PerformanceMetric`), losing multiplicity information the requirement specifies (e.g., "contains multiple Material Specimens"). Model 2 also assigns SafetyProtocol adherence to ThermalAnalysisRun (`ThermalAnalysisRun ..> SafetyProtocol`) whereas the requirement states the ProcessController adheres to SafetyProtocols. Model 2 does capture `OptimizationResult --> ElementComposition : recommends` which Model 1 only represents via a `recommendedComposition: String` attribute rather than an association. Model 1 also lacks an explicit link from OptimizationResult to ElementComposition. 3. Model attributes with appropriate data types: Model 1 = 5, Model 2 = 3; Evidence: Model 1 models attributes comprehensively with proper types and enums: MaterialSpecimen has `density: double`, `surfaceFinish: SurfaceFinish`, `grainStructure: String`, `defectAnnotation: String` (requirement: "classify grain structure, and annotate any defects"); SpectroscopyData has `wavelength: double`, `emissionIntensity: double`, `detectedPhase: PhaseType` (requirement: "detect phases and analyze elemental composition"); OptimizationResult has `convergenceTracked: boolean` and `recommendedComposition: String`; DesignConstraint has `limitValue: double` and `effectiveDate: Date`; StressTestRun has `testType: TestType` (DESTRUCTIVE/NON_DESTRUCTIVE). Model 2 omits critical attributes: MaterialSpecimen is missing `grainStructure` and `defectAnnotation`; ElementComposition uses vague `chemicalMakeup: Map`; SpectroscopyData is missing `detectedPhase`; OptimizationResult is missing `recommendedComposition` (only has `convergence: Float`); DesignConstraint is missing `effectiveDate`; StressTestRunner conflates `testType: String` without enum. 4. Consistencies of Terminology with given context: Model 1 = 5, Model 2 = 4; Evidence: Both models use class names directly matching the requirement (AlloyBatch, MaterialSpecimen, ElementComposition, PhaseDistribution, ExperimentPlanner, HeatTreatmentProfile, PhaseDiagramCalculator, ProcessController, ThermalAnalysisRun, ThermalCycleSimulator, SafetyProtocol, ResearchProject, ExperimentalDataset, SpectroscopyData, MicrostructureAnalysis, StressTestRunner, PerformanceMetric, OptimizationResult, DesignConstraint, RegulatoryStandard, ComplianceArchive, BatchRecord, CostEstimator, SupplierNetwork, QualityAssurance, ReportGenerator). Model 1 additionally uses domain-consistent terminology for refinement classes (ProcessingStep, QualityAssuranceReview, SummaryReport) and enum values (AUSTENITE, FERRITE, MARTENSITE, PEARLITE from the requirement). Model 2 uses `chemicalMakeup` aligning with "chemical makeup" and `integrityVerified` aligning with "verify data integrity," but introduces method names (e.g., `generateProfile()`, `correlateData()`, `refinePhases()`) that are implementation-oriented rather than domain-conceptual, slightly diluting terminology focus. 5. Adherence of UML class diagram standards: Model 1 = 5, Model 2 = 4; Evidence: Model 1 uses valid UML notation throughout: class declarations with typed attributes, enums, composition (`*--`), directed associations (`-->`) with role labels and multiplicities. No syntax violations. Model 2 also uses valid UML (classes, composition, associations, dependencies `..>`), and `skinparam`/`hide empty members` are presentation directives ignored per guidelines. However, Model 2's heavy reliance on `..>` dependency arrows for structural domain relationships (e.g., "generates," "correlates," "compiles") rather than associations reduces diagram expressiveness—dependencies do not carry multiplicities or composition semantics, making the structural relationships less precise. Both are syntactically valid, but Model 1 is more consistently modeled with appropriate UML relationship types. Total: Model 1 = 24, Model 2 = 18 Choice: A Reason: 1. Appropriate conceptual classes aligned with the domain: Model 1 is more comprehensive, introducing traceable intermediate classes (ProcessingStep for profile steps, StressTestRun for tensile tests, Supplier for vendors, QualityAssuranceReview for inspector approvals, SummaryReport for compiled reports) that directly map to requirement sentences. Model 2 collapses several of these into attributes or methods, reducing domain concept coverage. 2. Associations/Multiplicities between classes for domain reasoning: Model 1 provides explicit multiplicities on nearly all relationships, enabling precise domain reasoning (e.g., `AlloyBatch "1" *-- "1..*" MaterialSpecimen`, `ResearchProject "1" *-- "1..*" ExperimentalDataset`). Model 2 loses multiplicity information on many relationships by using `..>` dependencies, and misassigns SafetyProtocol adherence to ThermalAnalysisRun instead of ProcessController, contradicting the requirement. Model 2 does gain a point for the explicit `OptimizationResult --> ElementComposition : recommends` association that Model 1 represents only as a string attribute. 3. Model attributes with appropriate data types: Model 1 captures all critical attributes mentioned in the requirement with proper data types and enums (grainStructure, defectAnnotation, detectedPhase, effectiveDate on DesignConstraint, recommendedComposition, TestType enum). Model 2 omits several critical attributes (grainStructure, defectAnnotation, detectedPhase, recommendedComposition, effectiveDate on DesignConstraint) and uses overly generic types (`chemicalMakeup: Map`, `testType: String`). 4. Consistencies of Terminology with given context: Both models maintain strong terminology alignment with the requirement. Model 1 edges ahead by using domain-specific enums (PhaseType with AUSTENITE/FERRITE/MARTENSITE/PEARLITE, TestType with DESTRUCTIVE/NON_DESTRUCTIVE, QualityStatus, ReportFormat) that directly mirror requirement language. Model 2 introduces operation-method names that are implementation-flavored rather than domain-conceptual. 5. Rejected or checked issues: I did not penalize Model 2 for using `..>` vs `-->` as an "association style" (forbidden penalty #1 covers bidirectional vs unidirectional equivalence). The penalty here is the loss of multiplicity information and misassignment of SafetyProtocol adherence, which are domain-reasoning issues, not style preferences. I also did not penalize Model 2 for its `skinparam`/`hide empty members` directives (presentation-only, ignored per guidelines) or for using `Float` vs `double` (forbidden penalty #3 on primitive types). I did not reward Model 1 for extra identifiers/timestamps/statuses unless they covered a stated requirement fact. 6. Overall judgment: Model 1 is clearly superior across all five criteria. It provides a more complete, accurate, and standards-compliant domain model with comprehensive class coverage, explicit multiplicities, well-typed attributes, domain-faithful enums, and consistent UML notation. Model 2, while syntactically valid, suffers from missing attributes, collapsed classes, imprecise dependency-based relationships without multiplicities, and a misassigned SafetyProtocol relationship. ``` | J4: A | K4: =IF(OR(J4="",C4="",E4=""),"",IF(J4="C","D(平局)",IF(J4=IF(E4="l2r","A","B"),LEFT(C4,1),RIGHT(C4,1)))) -> A | L4: A | M4: =IF(OR(K4="",L4=""),"",--(K4=L4)) -> 1
A5: AdvancedAlloyCompositionOptimization | B5: The Advanced Alloy Composition Optimization system supports research and industrial processes for developing high-performance metal alloys. The core unit of production is an Alloy Batch, created on a specific date, which contains multiple Material Specimens. Each specimen is defined by its density and surface finish, possesses a base Element Composition describing its chemical makeup, and has a current Phase Distribution detailing the fractions of target phases such as Austenite, Ferrite, Martensite, or Pearlite. Specimens can be analyzed to determine their current phase, classify grain structure, and annotate any defects. To achieve desired material properties, the system utilizes an Experiment Planner that generates Heat Treatment Profiles. These profiles, identified by name and quenching status, define processing steps and are validated before use. The planning process relies on a Phase Diagram Calculator to identify stable phases and check for equilibrium states. During execution, a Process Controller manages Thermal Analysis Runs, utilizing a Thermal Cycle Simulator to model cooling rates and peak temperatures while adhering to strict Safety Protocols that include emergency stop capabilities and temperature limits. Each thermal analysis run applies a specific profile. Data collection is organized under Research Projects, led by a principal investigator with a defined budget and associated design constraints. Projects encompass Experimental Datasets that verify data integrity, filter results, and store generated outcomes. These datasets aggregate Spectroscopy Data, which records wavelengths and emission intensities to detect phases and analyze elemental composition. Microstructure Analysis correlates specimen samples with spectroscopic data to refine phase distributions, utilizing the Phase Diagram Calculator as a reference. Furthermore, Stress Test Runners perform destructive or non-destructive tensile tests on specimens to generate Performance Metrics regarding load and increment steps. These metrics feed into Optimization Results that track convergence and recommend optimal element compositions. The system ensures adherence to engineering and legal standards through Design Constraints and Regulatory Standards, which specify limit values and effective dates to check specimen compliance. A Compliance Archive stores Batch Records, linking regulatory standards to specific batches; each record documents the primary phase, quality status, and the associated alloy batch. Operational support includes a Cost Estimator for calculating raw material expenses based on composition, a Supplier Network for finding vendors meeting design constraints, and a Quality Assurance module where certified inspectors approve batches. Finally, a Report Generator compiles performance metrics and quality assurance sources into summary reports in various formats. | C5: A vs B | D5: five | E5: r2l | F5: You are a professional software engineer with expertise across multiple domains. You evaluate UML class diagrams from the perspective of real-world software design, applying domain knowledge and engineering best practices alongside the provided scoring criteria. Please evaluate the two diagrams (Model 1, Model 2) based on the provided requirement and scoring criteria. # Criteria **CRITICAL INSTRUCTION**: You MUST evaluate the responses against EACH AND EVERY criterion listed in the "Specific Instructions" one by one. DO NOT aggregate, summarize, or skip any criterion. **Specific Instructions**: - Appropriate conceptual classes aligned with the domain 1− Very Poor: Classes are mostly incorrect or irrelevant and do not accurately represent the domain. 2− Poor: Only a few classes are correct, but the majority of the domain concepts are missing or incorrect. 3− Fair: Some classes are correctly identified, but noticeable misalignments are still present. 4− Good: Most classes are correctly identified with only minor misalignments 5− Excellent: All classes are correctly identified, fully aligned with the domain. - Associations/Multiplicities between classes for domain reasoning 1− Very Poor: Associations/multiplicities are largely missing or incorrect, comprising domain reasoning. 2− Poor: Few correct associations/multiplicities with critical relationships missing. 3− Fair: Some associations/multiplicities are correct, but noticeable missing or misrepresentations remain. 4− Good: Most associations/multiplicities are correctly identified with only minor errors. 5− Excellent: All essential associations/multiplicities correctly applied. - Model attributes with appropriate data types 1− Very Poor: Attributes and data types are poorly identified and modeled; largely incorrect or irrelevant. 2− Poor: Few attributes are correct with proper types; critical attributes are missing. 3− Fair: Some attributes are correct with proper types, but significant attributes are still missing. 4− Good: Most attributes are appropriately modeled with proper data types; minor type issues may exist. 5− Excellent: All attributes are correctly modeled with appropriate data types. - Consistencies of Terminology with given context 1− Very Poor: Terminology is largely inconsistent with the given context 2− Poor: Frequent inconsistencies; critical terms misused or missing. 3− Fair: Some terminology is correct, but noticeable inconsistencies remain. 4− Good: Most terminology aligns with the given context, with minor inconsistencies. 5− Excellent: Terminology is fully consistent with the given context. - Adherence of UML class diagram standards 1− Very Poor: Poor diagram formation with major UML standards ignored, making it largely incomprehensible. 2− Poor: Frequent UML violations; diagram is difficult to interpret. 3− Fair: Some UML/PlantUML syntax errors, but major representations are still missing. 4− Good: Minor UML/PlantUML notation errors; overall diagram remains understandable. 5− Excellent: Fully adheres to UML/PlantUML syntax, notation, and conventions. # Evaluation Guidelines ## General Rules - Consider only UML class diagram semantics (e.g., classes, attributes, associations, multiplicities, generalisation, composition/aggregation). - Ignore layout, styling, skinparams, comments, and notes. - If the response is incomplete or misses any required key component, regard it as a bad one. - Give credit for semantic clarity, but not for layout, comments, visibility markers, or other presentation-only differences. ## Forbidden Penalties (Strictly Enforced) You MUST NOT deduct points, lower scores, or claim a model is "worse", "complex", or "less practical" based on ANY of the following: 1. **Association Styles**: Using two opposite unidirectional associations (e.g., `A --> B` and `B --> A`) instead of one single bidirectional line (e.g., `A -- B`). They are 100% semantically equivalent. Treat opposite-direction associations as equivalent unless role labels, multiplicities, or navigability contradict the requirements. 2. **PlantUML Comments**: Using single-quote comments (e.g., `'opposite bank`) at the end of lines. These are standard tooling annotations — ignore them for scoring unless they obscure or contradict the relation meaning. 3. **Primitive Types**: Using common aliases for types (e.g., `int` instead of `Integer`, `str` instead of `String`, `boolean` instead of `Boolean`). Lowercase or language-flavored spellings are acceptable. 4. **Equivalent Multiplicity Literals**: Using `*` instead of `0..*`, or `1` instead of `1..1`. These pairs are semantically identical. 5. **Optional Abstractness**: Marking or not marking a superclass as `abstract` when the requirement does not say whether direct instances are allowed. Do not reward either style without requirement evidence. These forbidden factors must not appear as negative evidence under any criterion and must not affect criterion scores or the final choice. ## Evidence & Calibration Requirements - For every criterion you discuss, cite concrete evidence from both models. Quote or closely paraphrase the relevant class, attribute, association, multiplicity, inheritance, note, or missing element. - Do not claim a class, attribute, or association is missing when a synonymous or directly related element is present. If the present element is indirect, vague, over-constrained, or semantically weak, state that precise weakness instead. - Distinguish omissions from contradictions. Missing a hard constraint is usually less severe than explicitly modeling the opposite or an invalid multiplicity. - Do not reward a simpler model merely for being shorter if the more detailed model uses traceable intermediate workflow/concept classes required for domain reasoning. - Do not penalize a detailed model merely for using transparent refinements such as `Definition`, `Placement`, `Entry`, `Session`, `State`, `Record`, `Assignment`, `Arrangement`, or `Need` when the base requirement term remains recognizable. - Do not reward extra identifiers, timestamps, statuses, classes, or implementation-oriented detail unless they improve coverage of a stated requirement fact. - Text introduced by `e.g.`, `for example`, or `such as` gives examples, not a complete enumeration, unless the requirement explicitly declares a closed list. - Keep UML/PlantUML standards separate from domain accuracy. Domain-faithfulness problems, wrong business multiplicities, missing constraints, or vague semantics belong under the domain criteria, not UML standards, unless they make the notation invalid or unreadable. - When evaluating position bias, remember that Model 1 and Model 2 may be swapped in a second pass. Use only the content under each model block, not assumptions from prior comparisons or labels. # Requirement ``` The Advanced Alloy Composition Optimization system supports research and industrial processes for developing high-performance metal alloys. The core unit of production is an Alloy Batch, created on a specific date, which contains multiple Material Specimens. Each specimen is defined by its density and surface finish, possesses a base Element Composition describing its chemical makeup, and has a current Phase Distribution detailing the fractions of target phases such as Austenite, Ferrite, Martensite, or Pearlite. Specimens can be analyzed to determine their current phase, classify grain structure, and annotate any defects. To achieve desired material properties, the system utilizes an Experiment Planner that generates Heat Treatment Profiles. These profiles, identified by name and quenching status, define processing steps and are validated before use. The planning process relies on a Phase Diagram Calculator to identify stable phases and check for equilibrium states. During execution, a Process Controller manages Thermal Analysis Runs, utilizing a Thermal Cycle Simulator to model cooling rates and peak temperatures while adhering to strict Safety Protocols that include emergency stop capabilities and temperature limits. Each thermal analysis run applies a specific profile. Data collection is organized under Research Projects, led by a principal investigator with a defined budget and associated design constraints. Projects encompass Experimental Datasets that verify data integrity, filter results, and store generated outcomes. These datasets aggregate Spectroscopy Data, which records wavelengths and emission intensities to detect phases and analyze elemental composition. Microstructure Analysis correlates specimen samples with spectroscopic data to refine phase distributions, utilizing the Phase Diagram Calculator as a reference. Furthermore, Stress Test Runners perform destructive or non-destructive tensile tests on specimens to generate Performance Metrics regarding load and increment steps. These metrics feed into Optimization Results that track convergence and recommend optimal element compositions. The system ensures adherence to engineering and legal standards through Design Constraints and Regulatory Standards, which specify limit values and effective dates to check specimen compliance. A Compliance Archive stores Batch Records, linking regulatory standards to specific batches; each record documents the primary phase, quality status, and the associated alloy batch. Operational support includes a Cost Estimator for calculating raw material expenses based on composition, a Supplier Network for finding vendors meeting design constraints, and a Quality Assurance module where certified inspectors approve batches. Finally, a Report Generator compiles performance metrics and quality assurance sources into summary reports in various formats. ``` # Model 1 ``` @startuml skinparam classAttributeIconSize 0 hide empty members class AlloyBatch { creationDate: Date } class MaterialSpecimen { density: Float surfaceFinish: String } class ElementComposition { chemicalMakeup: Map } class PhaseDistribution { austenite: Float ferrite: Float martensite: Float pearlite: Float } class ExperimentPlanner { generateProfile() } class HeatTreatmentProfile { name: String quenchingStatus: Boolean processingSteps: List isValidated: Boolean } class PhaseDiagramCalculator { identifyStablePhases() checkEquilibrium() } class ProcessController { manageRun() } class ThermalAnalysisRun { runAnalysis() } class ThermalCycleSimulator { coolingRate: Float peakTemperature: Float } class SafetyProtocol { emergencyStop: Boolean temperatureLimit: Float } class ResearchProject { principalInvestigator: String budget: Decimal } class ExperimentalDataset { integrityVerified: Boolean filterResults() } class SpectroscopyData { wavelength: Float emissionIntensity: Float } class MicrostructureAnalysis { correlateData() refinePhases() } class StressTestRunner { testType: String performTest() } class PerformanceMetric { load: Float incrementStep: Integer } class OptimizationResult { convergence: Float } class DesignConstraint { limitValue: Float } class RegulatoryStandard { limitValue: Float effectiveDate: Date } class ComplianceArchive { storeRecord() } class BatchRecord { primaryPhase: String qualityStatus: String } class CostEstimator { calculateExpenses() } class SupplierNetwork { findVendors() } class QualityAssurance { inspector: String isCertified: Boolean approveBatch() } class ReportGenerator { format: String compileReport() } AlloyBatch "1" *-- "0..*" MaterialSpecimen MaterialSpecimen "1" *-- "1" ElementComposition MaterialSpecimen "1" *-- "1" PhaseDistribution ExperimentPlanner ..> HeatTreatmentProfile : generates HeatTreatmentProfile ..> PhaseDiagramCalculator : validated by ProcessController "1" --> "0..*" ThermalAnalysisRun : manages ThermalAnalysisRun "1" --> "1" HeatTreatmentProfile : applies ThermalAnalysisRun ..> ThermalCycleSimulator : utilizes ThermalAnalysisRun ..> SafetyProtocol : adheres to ResearchProject "1" *-- "0..*" ExperimentalDataset ResearchProject "1" --> "0..*" DesignConstraint ExperimentalDataset "1" *-- "0..*" SpectroscopyData MicrostructureAnalysis ..> MaterialSpecimen : correlates MicrostructureAnalysis ..> SpectroscopyData : correlates MicrostructureAnalysis ..> PhaseDiagramCalculator : references StressTestRunner ..> MaterialSpecimen : tests StressTestRunner ..> PerformanceMetric : generates OptimizationResult ..> PerformanceMetric : fed by OptimizationResult --> ElementComposition : recommends ComplianceArchive "1" *-- "0..*" BatchRecord BatchRecord "0..*" --> "1" AlloyBatch BatchRecord "0..*" --> "1" RegulatoryStandard CostEstimator ..> ElementComposition : calculates from SupplierNetwork ..> DesignConstraint : meets QualityAssurance ..> AlloyBatch : approves ReportGenerator ..> PerformanceMetric : compiles ReportGenerator ..> QualityAssurance : compiles @enduml ``` # Model 2 ``` @startuml ' Enumerations enum SurfaceFinish { POLISHED ROUGH MACHINED AS_CAST } enum PhaseType { AUSTENITE FERRITE MARTENSITE PEARLITE } enum TestType { DESTRUCTIVE NON_DESTRUCTIVE } enum QualityStatus { APPROVED REJECTED PENDING } enum RunState { INITIALIZED HEATING HOLDING COOLING COMPLETED EMERGENCY_STOP } enum ReportFormat { PDF CSV JSON HTML } ' Domain Classes class AlloyBatch { batchId: String creationDate: Date name: String } class MaterialSpecimen { specimenId: String density: double surfaceFinish: SurfaceFinish grainStructure: String defectAnnotation: String } class ElementComposition { elementName: String percentage: double } class PhaseDistribution { phaseType: PhaseType fraction: double } class ExperimentPlanner { plannerId: String name: String } class HeatTreatmentProfile { profileId: String name: String quenchingStatus: boolean isValidated: boolean } class ProcessingStep { stepOrder: int targetTemperature: double durationMinutes: int description: String } class PhaseDiagramCalculator { calculatorId: String name: String equilibriumState: boolean stablePhases: String } class ProcessController { controllerId: String name: String } class ThermalAnalysisRun { runId: String currentState: RunState peakTemperature: double coolingRate: double startTime: Date endTime: Date } class ThermalCycleSimulator { simulatorId: String name: String } class SafetyProtocol { protocolId: String maxTemperatureLimit: double minTemperatureLimit: double emergencyStopEnabled: boolean } class ResearchProject { projectId: String projectName: String principalInvestigator: String budget: double } class ExperimentalDataset { datasetId: String name: String dataIntegrityVerified: boolean creationDate: Date filterCriteria: String resultsFiltered: boolean } class SpectroscopyData { dataId: String wavelength: double emissionIntensity: double detectedPhase: PhaseType timestamp: Date } class MicrostructureAnalysis { analysisId: String correlatedPhase: PhaseType refinedFraction: double description: String } class StressTestRunner { runnerId: String name: String } class StressTestRun { testId: String testType: TestType maxLoad: double incrementStep: double timestamp: Date } class PerformanceMetric { metricId: String loadValue: double incrementValue: double stressValue: double strainValue: double } class OptimizationResult { resultId: String convergenceTracked: boolean iterationCount: int recommendedComposition: String } class DesignConstraint { constraintId: String constraintName: String limitValue: double effectiveDate: Date } class RegulatoryStandard { standardId: String standardName: String limitValue: double effectiveDate: Date } class ComplianceArchive { archiveId: String archiveDate: Date } class BatchRecord { recordId: String primaryPhase: PhaseType qualityStatus: QualityStatus recordDate: Date } class CostEstimator { estimatorId: String name: String } class CostEstimation { estimationId: String totalCost: double currency: String calculationDate: Date } class SupplierNetwork { networkId: String name: String } class Supplier { supplierId: String name: String meetsConstraints: boolean contactInfo: String } class QualityAssurance { moduleId: String name: String } class QualityAssuranceReview { reviewId: String inspectorName: String inspectorCertified: boolean approvalDate: Date isApproved: boolean } class ReportGenerator { generatorId: String name: String } class SummaryReport { reportId: String title: String format: ReportFormat generationDate: Date } ' Associations and Compositions AlloyBatch "1" *-- "1..*" MaterialSpecimen: contains specimens MaterialSpecimen "1" *-- "1..*" ElementComposition: base composition MaterialSpecimen "1" *-- "1..*" PhaseDistribution: current phases ExperimentPlanner "1" --> "1..*" HeatTreatmentProfile: generates profiles HeatTreatmentProfile "1" *-- "1..*" ProcessingStep: defined steps PhaseDiagramCalculator "1" --> "*" HeatTreatmentProfile: references for planning PhaseDiagramCalculator "1" --> "*" MicrostructureAnalysis: references for analysis ProcessController "1" --> "1..*" ThermalAnalysisRun: manages runs ProcessController "1" --> "1" ThermalCycleSimulator: utilizes simulator ProcessController "1" --> "1..*" SafetyProtocol: adheres to protocols ThermalCycleSimulator "1" --> "*" ThermalAnalysisRun: simulates ThermalAnalysisRun "*" --> "1" HeatTreatmentProfile: applies profile ResearchProject "1" *-- "1..*" ExperimentalDataset: encompassed datasets ResearchProject "1" --> "1..*" DesignConstraint: associated constraints ExperimentalDataset "1" *-- "*" SpectroscopyData: aggregated data ExperimentalDataset "1" *-- "*" MicrostructureAnalysis: included analyses MicrostructureAnalysis "*" --> "1" MaterialSpecimen: correlates specimen MicrostructureAnalysis "*" --> "1" SpectroscopyData: correlates spectroscopic data StressTestRunner "1" --> "1..*" StressTestRun: performs tests MaterialSpecimen "1" --> "*" StressTestRun: tested in StressTestRun "1" *-- "1..*" PerformanceMetric: generated metrics PerformanceMetric "*" --> "1" OptimizationResult: feeds into ComplianceArchive "1" *-- "1..*" BatchRecord: stored records BatchRecord "*" --> "1" AlloyBatch: documents batch BatchRecord "*" --> "1..*" RegulatoryStandard: linked standards CostEstimator "1" --> "*" AlloyBatch: estimates costs for CostEstimator "1" --> "*" ElementComposition: calculates based on CostEstimator "1" --> "*" CostEstimation: produces estimations AlloyBatch "1" --> "1" CostEstimation: estimated by SupplierNetwork "1" --> "*" Supplier: finds vendors SupplierNetwork "1" --> "*" DesignConstraint: matches constraints QualityAssurance "1" --> "*" QualityAssuranceReview: conducts reviews AlloyBatch "1" --> "*" QualityAssuranceReview: reviewed in ReportGenerator "1" --> "*" SummaryReport: compiles reports ReportGenerator "*" --> "*" PerformanceMetric: compiles from metrics ReportGenerator "*" --> "*" QualityAssuranceReview: compiles from reviews @enduml ``` # Choices Please choose from the following 3 options based on the scoring criteria: A. Response 1 is better. B. Response 2 is better. C. Tie. Please provide criterion-by-criterion scores before the final choice. Use Tie if the total scores are equal or the meaningful quality difference is small. Also, you should pay adequate and same attention to both responses. **Important**：You should act as an IMPARTIAL judge and be as OBJECTIVE as possible. AVOID ANY POSITION BIASES and ensure that the ORDER in which the responses were presented DOES NOT influence your decision. Before choosing A/B/C, first score Model 1 and Model 2 independently against each specific instruction. If the specific instruction provides a scoring scale, use that scale; otherwise use a 1-5 score where 1 means very poor alignment and 5 means excellent alignment. Base the final choice on the independent scores and the evidence, not on which model is shown first. # Output Your output should be in the following format: ```result Scores: 1. <criterion name>: Model 1 = <score>, Model 2 = <score>; Evidence: <concrete evidence from both models> 2. <criterion name>: Model 1 = <score>, Model 2 = <score>; Evidence: <concrete evidence from both models> Total: Model 1 = <total>, Model 2 = <total> Choice: A Reason: 1. Criterion name: compare Model 1 and Model 2 using concrete evidence from both models. 2. Criterion name: compare Model 1 and Model 2 using concrete evidence from both models. 3. Rejected or checked issues: mention any tempting but unsupported issue that you did not use for the decision, if relevant. 4. Overall judgment: explain why the chosen model is better, or why it is a tie. ``` | G5: codex | H5: GLM5.2 | I5: ```result Scores: 1. Appropriate conceptual classes aligned with the domain: Model 1 = 4, Model 2 = 5; Evidence: Both models identify all 26 core domain classes (AlloyBatch, MaterialSpecimen, ElementComposition, PhaseDistribution, ExperimentPlanner, HeatTreatmentProfile, PhaseDiagramCalculator, ProcessController, ThermalAnalysisRun, ThermalCycleSimulator, SafetyProtocol, ResearchProject, ExperimentalDataset, SpectroscopyData, MicrostructureAnalysis, StressTestRunner, PerformanceMetric, OptimizationResult, DesignConstraint, RegulatoryStandard, ComplianceArchive, BatchRecord, CostEstimator, SupplierNetwork, QualityAssurance, ReportGenerator). Model 1 models processing steps as an attribute (`processingSteps: List` on HeatTreatmentProfile) and lacks separate classes for Supplier, SummaryReport, and ProcessingStep. Model 2 introduces ProcessingStep (matching "define processing steps"), Supplier (matching "finding vendors"), SummaryReport (matching "summary reports in various formats"), and enumerations (TestType for destructive/non-destructive, ReportFormat for various formats, PhaseType, QualityStatus), all of which improve coverage of stated requirement facts. Model 2 also adds grainStructure and defectAnnotation to MaterialSpecimen, directly matching the requirement's "classify grain structure, and annotate any defects." 2. Associations/Multiplicities between classes for domain reasoning: Model 1 = 3, Model 2 = 4; Evidence: Model 1 uses proper associations with multiplicities for structural relationships (e.g., `AlloyBatch "1" *-- "0..*" MaterialSpecimen`, `ResearchProject "1" *-- "0..*" ExperimentalDataset`, `ComplianceArchive "1" *-- "0..*" BatchRecord`), but uses dependency arrows (`..>`) without multiplicity for key persistent relationships such as `MicrostructureAnalysis ..> MaterialSpecimen : correlates` and `MicrostructureAnalysis ..> SpectroscopyData : correlates` (requirement says "correlates specimen samples with spectroscopic data" — a persistent relationship needing multiplicity), and `QualityAssurance ..> AlloyBatch : approves`. Model 1 also places `ThermalAnalysisRun ..> ThermalCycleSimulator : utilizes` and `ThermalAnalysisRun ..> SafetyProtocol : adheres to` on ThermalAnalysisRun, whereas the requirement's subject is the ProcessController ("a Process Controller manages Thermal Analysis Runs, utilizing a Thermal Cycle Simulator... while adhering to strict Safety Protocols"). Model 2 uses associations with multiplicities throughout (e.g., `MicrostructureAnalysis "*" --> "1" MaterialSpecimen`, `MicrostructureAnalysis "*" --> "1" SpectroscopyData`, `QualityAssurance "1" --> "*" QualityAssuranceReview`, `AlloyBatch "1" --> "*" QualityAssuranceReview`) and correctly places the simulator and safety protocol associations on ProcessController (`ProcessController "1" --> "1" ThermalCycleSimulator`, `ProcessController "1" --> "1..*" SafetyProtocol`). However, Model 2 reverses some directions: `PhaseDiagramCalculator "1" --> "*" HeatTreatmentProfile : references for planning` (should be profile/planner → calculator) and `PhaseDiagramCalculator "1" --> "*" MicrostructureAnalysis` (requirement says MicrostructureAnalysis uses calculator "as a reference," so direction is reversed). Overall, Model 2 has better multiplicity coverage with minor directional errors. 3. Model attributes with appropriate data types: Model 1 = 3, Model 2 = 4; Evidence: Model 1 has correct attributes for many classes (e.g., `AlloyBatch.creationDate: Date`, `HeatTreatmentProfile` with `name: String, quenchingStatus: Boolean, isValidated: Boolean`, `PerformanceMetric` with `load: Float, incrementStep: Integer`, `PhaseDistribution` with named phase fractions `austenite/ferrite/martensite/pearlite: Float`), but has notable omissions: `DesignConstraint` has only `limitValue: Float` and is missing `effectiveDate` (requirement explicitly says "limit values and effective dates" for both Design Constraints and Regulatory Standards); `MaterialSpecimen` is missing `grainStructure` and `defectAnnotation` (requirement: "classify grain structure, and annotate any defects"); `SpectroscopyData` lacks a `detectedPhase` attribute (requirement: "to detect phases"). Model 2 covers all these: `DesignConstraint` has `limitValue: double` and `effectiveDate: Date`; `MaterialSpecimen` has `grainStructure: String` and `defectAnnotation: String`; `SpectroscopyData` has `detectedPhase: PhaseType`. Model 2 also uses enumerations for type safety (SurfaceFinish, PhaseType, TestType, QualityStatus, ReportFormat). Minor issue in Model 2: `OptimizationResult.recommendedComposition: String` is less semantically rich than Model 1's association `OptimizationResult --> ElementComposition : recommends`, but the attribute is still a valid representation. 4. Consistencies of Terminology with given context: Model 1 = 5, Model 2 = 5; Evidence: Both models use terminology directly from the requirement. Model 1 class names (AlloyBatch, MaterialSpecimen, ElementComposition, PhaseDistribution, ExperimentPlanner, HeatTreatmentProfile, PhaseDiagramCalculator, ProcessController, ThermalAnalysisRun, ThermalCycleSimulator, SafetyProtocol, ResearchProject, ExperimentalDataset, SpectroscopyData, MicrostructureAnalysis, StressTestRunner, PerformanceMetric, OptimizationResult, DesignConstraint, RegulatoryStandard, ComplianceArchive, BatchRecord, CostEstimator, SupplierNetwork, QualityAssurance, ReportGenerator) all match the requirement exactly. Association labels mirror the requirement's verbs ("generates," "manages," "utilizes," "adheres to," "applies," "correlates," "references," "recommends," "compiles"). Model 2 uses the same class names plus additional refinement classes (ProcessingStep, StressTestRun, CostEstimation, Supplier, QualityAssuranceReview, SummaryReport) and enumerations (PhaseType with AUSTENITE/FERRITE/MARTENSITE/PEARLITE, TestType with DESTRUCTIVE/NON_DESTRUCTIVE, QualityStatus with APPROVED/REJECTED/PENDING) whose values directly match the requirement's terminology. Both models are fully consistent. 5. Adherence of UML class diagram standards: Model 1 = 5, Model 2 = 5; Evidence: Both models use valid PlantUML class diagram syntax with standard UML constructs. Model 1 correctly uses composition (`*--`), directed association (`-->`), dependency (`..>`), multiplicities (e.g., `"1"`, `"0..*"`), and role labels. Methods without return types (e.g., `generateProfile()`, `runAnalysis()`) are valid UML. Model 2 correctly uses composition, directed associations, multiplicities (e.g., `"1"`, `"*"`, `"1..*"`), role labels, and additionally enumerations (`enum`) which are standard UML. Both diagrams are readable and well-formed with no syntax errors. Presentation directives (`skinparam`, `hide empty members`) and comments (single-quote lines) are ignored per guidelines. Total: Model 1 = 20, Model 2 = 23 Choice: B Reason: 1. Appropriate conceptual classes: Model 2 covers more stated requirement facts through additional classes — ProcessingStep (requirement: "define processing steps"), Supplier (requirement: "finding vendors"), SummaryReport (requirement: "summary reports in various formats"), and enumerations for TestType, ReportFormat, and QualityStatus. Model 1 models processing steps as an attribute and lacks Supplier/SummaryReport classes. Model 2 also captures grainStructure and defectAnnotation on MaterialSpecimen, directly matching the requirement. 2. Associations/multiplicities: Model 2 uses associations with multiplicities consistently, including for key persistent relationships (MicrostructureAnalysis → MaterialSpecimen, MicrostructureAnalysis → SpectroscopyData, QualityAssurance → reviews) where Model 1 uses dependencies without multiplicity. Model 2 also correctly places the ThermalCycleSimulator and SafetyProtocol associations on ProcessController, matching the requirement's grammar. Both models have some directional issues (Model 2 reverses PhaseDiagramCalculator associations; Model 1 places simulator/safety on ThermalAnalysisRun), but Model 2's overall multiplicity coverage is superior. 3. Attributes with data types: Model 2 covers all required attributes including DesignConstraint.effectiveDate, MaterialSpecimen.grainStructure/defectAnnotation, and SpectroscopyData.detectedPhase, all of which Model 1 omits. Model 2's use of enumerations adds type appropriateness. Model 1's PhaseDistribution with named phase fractions is a good design choice, but the missing attributes are more impactful. 4. Terminology consistency: Both models are fully consistent with the requirement's terminology — no meaningful difference. 5. UML standards: Both models adhere fully to UML/PlantUML syntax and conventions — no meaningful difference. 6. Rejected or checked issues: I did not penalize Model 2 for extra ID attributes, timestamps, or implementation-oriented detail (e.g., stressValue/strainValue on PerformanceMetric) per the guidelines. I did not penalize Model 1 for using `int`/`String`/`Float` instead of `Integer`/`String`/`Float` type aliases. I did not penalize Model 2 for using `*` instead of `0..*`. I did not reward Model 2 merely for being more detailed — the extra classes were evaluated against whether they improve coverage of stated requirement facts. 7. Overall judgment: Model 2 is better due to more complete class coverage (ProcessingStep, Supplier, SummaryReport, enumerations), more complete attributes (effectiveDate on DesignConstraint, grainStructure/defectAnnotation on MaterialSpecimen, detectedPhase on SpectroscopyData), and better multiplicity coverage through consistent use of associations rather than dependencies. The 3-point gap (20 vs 23) reflects these substantive domain-coverage differences. ``` | J5: B | K5: =IF(OR(J5="",C5="",E5=""),"",IF(J5="C","D(平局)",IF(J5=IF(E5="l2r","A","B"),LEFT(C5,1),RIGHT(C5,1)))) -> A | L5: A | M5: =IF(OR(K5="",L5=""),"",--(K5=L5)) -> 1
A6: AdvancedAlloyCompositionOptimization | B6: The Advanced Alloy Composition Optimization system supports research and industrial processes for developing high-performance metal alloys. The core unit of production is an Alloy Batch, created on a specific date, which contains multiple Material Specimens. Each specimen is defined by its density and surface finish, possesses a base Element Composition describing its chemical makeup, and has a current Phase Distribution detailing the fractions of target phases such as Austenite, Ferrite, Martensite, or Pearlite. Specimens can be analyzed to determine their current phase, classify grain structure, and annotate any defects. To achieve desired material properties, the system utilizes an Experiment Planner that generates Heat Treatment Profiles. These profiles, identified by name and quenching status, define processing steps and are validated before use. The planning process relies on a Phase Diagram Calculator to identify stable phases and check for equilibrium states. During execution, a Process Controller manages Thermal Analysis Runs, utilizing a Thermal Cycle Simulator to model cooling rates and peak temperatures while adhering to strict Safety Protocols that include emergency stop capabilities and temperature limits. Each thermal analysis run applies a specific profile. Data collection is organized under Research Projects, led by a principal investigator with a defined budget and associated design constraints. Projects encompass Experimental Datasets that verify data integrity, filter results, and store generated outcomes. These datasets aggregate Spectroscopy Data, which records wavelengths and emission intensities to detect phases and analyze elemental composition. Microstructure Analysis correlates specimen samples with spectroscopic data to refine phase distributions, utilizing the Phase Diagram Calculator as a reference. Furthermore, Stress Test Runners perform destructive or non-destructive tensile tests on specimens to generate Performance Metrics regarding load and increment steps. These metrics feed into Optimization Results that track convergence and recommend optimal element compositions. The system ensures adherence to engineering and legal standards through Design Constraints and Regulatory Standards, which specify limit values and effective dates to check specimen compliance. A Compliance Archive stores Batch Records, linking regulatory standards to specific batches; each record documents the primary phase, quality status, and the associated alloy batch. Operational support includes a Cost Estimator for calculating raw material expenses based on composition, a Supplier Network for finding vendors meeting design constraints, and a Quality Assurance module where certified inspectors approve batches. Finally, a Report Generator compiles performance metrics and quality assurance sources into summary reports in various formats. | C6: A vs B | D6: general | E6: l2r | F6: You are a professional software engineer with expertise across multiple domains. You evaluate UML class diagrams from the perspective of real-world software design, applying domain knowledge and engineering best practices alongside the provided scoring criteria. Please evaluate the two diagrams (Model 1, Model 2) based on the provided requirement and scoring criteria. # Criteria **CRITICAL INSTRUCTION**: You MUST evaluate the responses against EACH AND EVERY criterion listed in the "Specific Instructions" one by one. DO NOT aggregate, summarize, or skip any criterion. **Specific Instructions**: - Cohesion and Decoupling: The design should aim for high cohesion within individual classes and low coupling between different classes. High cohesion ensures that each class is dedicated to a singular task or concept, enhancing clarity and functionality. Low coupling reduces dependencies among classes, facilitating easier maintenance and scalability. - Complexity: Utilize metrics such as the total number of classes, the average number of methods per class, and the depth of the inheritance tree to evaluate complexity. It's important to discern between conceptual classes and attributes; not every noun should become a class. The complexity level should be appropriately balanced, aligning with the specific requirements detailed in the project's requirement. - Practicability: A practical design should be readable and understandable, offering a clear and comprehensive representation of the software's structures, functionalities, and behaviors. This enhances ease in programming, testing, and maintenance. Modularity should be evident, with each component serving a distinct function, streamlining the development process. Interfaces need to be designed for simplicity, facilitating smooth interactions within the software and with external environments. The design must also support robust testing strategies, enabling thorough validation through unit and acceptance tests, ensuring the design's viability in real-world applications. # Evaluation Guidelines ## General Rules - Consider only UML class diagram semantics (e.g., classes, attributes, associations, multiplicities, generalisation, composition/aggregation). - Ignore layout, styling, skinparams, comments, and notes. - If the response is incomplete or misses any required key component, regard it as a bad one. - Give credit for semantic clarity, but not for layout, comments, visibility markers, or other presentation-only differences. ## Forbidden Penalties (Strictly Enforced) You MUST NOT deduct points, lower scores, or claim a model is "worse", "complex", or "less practical" based on ANY of the following: 1. **Association Styles**: Using two opposite unidirectional associations (e.g., `A --> B` and `B --> A`) instead of one single bidirectional line (e.g., `A -- B`). They are 100% semantically equivalent. Treat opposite-direction associations as equivalent unless role labels, multiplicities, or navigability contradict the requirements. 2. **PlantUML Comments**: Using single-quote comments (e.g., `'opposite bank`) at the end of lines. These are standard tooling annotations — ignore them for scoring unless they obscure or contradict the relation meaning. 3. **Primitive Types**: Using common aliases for types (e.g., `int` instead of `Integer`, `str` instead of `String`, `boolean` instead of `Boolean`). Lowercase or language-flavored spellings are acceptable. 4. **Equivalent Multiplicity Literals**: Using `*` instead of `0..*`, or `1` instead of `1..1`. These pairs are semantically identical. 5. **Optional Abstractness**: Marking or not marking a superclass as `abstract` when the requirement does not say whether direct instances are allowed. Do not reward either style without requirement evidence. These forbidden factors must not appear as negative evidence under any criterion and must not affect criterion scores or the final choice. ## Evidence & Calibration Requirements - For every criterion you discuss, cite concrete evidence from both models. Quote or closely paraphrase the relevant class, attribute, association, multiplicity, inheritance, note, or missing element. - Do not claim a class, attribute, or association is missing when a synonymous or directly related element is present. If the present element is indirect, vague, over-constrained, or semantically weak, state that precise weakness instead. - Distinguish omissions from contradictions. Missing a hard constraint is usually less severe than explicitly modeling the opposite or an invalid multiplicity. - Do not reward a simpler model merely for being shorter if the more detailed model uses traceable intermediate workflow/concept classes required for domain reasoning. - Do not penalize a detailed model merely for using transparent refinements such as `Definition`, `Placement`, `Entry`, `Session`, `State`, `Record`, `Assignment`, `Arrangement`, or `Need` when the base requirement term remains recognizable. - Do not reward extra identifiers, timestamps, statuses, classes, or implementation-oriented detail unless they improve coverage of a stated requirement fact. - Text introduced by `e.g.`, `for example`, or `such as` gives examples, not a complete enumeration, unless the requirement explicitly declares a closed list. - Keep UML/PlantUML standards separate from domain accuracy. Domain-faithfulness problems, wrong business multiplicities, missing constraints, or vague semantics belong under the domain criteria, not UML standards, unless they make the notation invalid or unreadable. - When evaluating position bias, remember that Model 1 and Model 2 may be swapped in a second pass. Use only the content under each model block, not assumptions from prior comparisons or labels. # Requirement ``` The Advanced Alloy Composition Optimization system supports research and industrial processes for developing high-performance metal alloys. The core unit of production is an Alloy Batch, created on a specific date, which contains multiple Material Specimens. Each specimen is defined by its density and surface finish, possesses a base Element Composition describing its chemical makeup, and has a current Phase Distribution detailing the fractions of target phases such as Austenite, Ferrite, Martensite, or Pearlite. Specimens can be analyzed to determine their current phase, classify grain structure, and annotate any defects. To achieve desired material properties, the system utilizes an Experiment Planner that generates Heat Treatment Profiles. These profiles, identified by name and quenching status, define processing steps and are validated before use. The planning process relies on a Phase Diagram Calculator to identify stable phases and check for equilibrium states. During execution, a Process Controller manages Thermal Analysis Runs, utilizing a Thermal Cycle Simulator to model cooling rates and peak temperatures while adhering to strict Safety Protocols that include emergency stop capabilities and temperature limits. Each thermal analysis run applies a specific profile. Data collection is organized under Research Projects, led by a principal investigator with a defined budget and associated design constraints. Projects encompass Experimental Datasets that verify data integrity, filter results, and store generated outcomes. These datasets aggregate Spectroscopy Data, which records wavelengths and emission intensities to detect phases and analyze elemental composition. Microstructure Analysis correlates specimen samples with spectroscopic data to refine phase distributions, utilizing the Phase Diagram Calculator as a reference. Furthermore, Stress Test Runners perform destructive or non-destructive tensile tests on specimens to generate Performance Metrics regarding load and increment steps. These metrics feed into Optimization Results that track convergence and recommend optimal element compositions. The system ensures adherence to engineering and legal standards through Design Constraints and Regulatory Standards, which specify limit values and effective dates to check specimen compliance. A Compliance Archive stores Batch Records, linking regulatory standards to specific batches; each record documents the primary phase, quality status, and the associated alloy batch. Operational support includes a Cost Estimator for calculating raw material expenses based on composition, a Supplier Network for finding vendors meeting design constraints, and a Quality Assurance module where certified inspectors approve batches. Finally, a Report Generator compiles performance metrics and quality assurance sources into summary reports in various formats. ``` # Model 1 ``` @startuml ' Enumerations enum SurfaceFinish { POLISHED ROUGH MACHINED AS_CAST } enum PhaseType { AUSTENITE FERRITE MARTENSITE PEARLITE } enum TestType { DESTRUCTIVE NON_DESTRUCTIVE } enum QualityStatus { APPROVED REJECTED PENDING } enum RunState { INITIALIZED HEATING HOLDING COOLING COMPLETED EMERGENCY_STOP } enum ReportFormat { PDF CSV JSON HTML } ' Domain Classes class AlloyBatch { batchId: String creationDate: Date name: String } class MaterialSpecimen { specimenId: String density: double surfaceFinish: SurfaceFinish grainStructure: String defectAnnotation: String } class ElementComposition { elementName: String percentage: double } class PhaseDistribution { phaseType: PhaseType fraction: double } class ExperimentPlanner { plannerId: String name: String } class HeatTreatmentProfile { profileId: String name: String quenchingStatus: boolean isValidated: boolean } class ProcessingStep { stepOrder: int targetTemperature: double durationMinutes: int description: String } class PhaseDiagramCalculator { calculatorId: String name: String equilibriumState: boolean stablePhases: String } class ProcessController { controllerId: String name: String } class ThermalAnalysisRun { runId: String currentState: RunState peakTemperature: double coolingRate: double startTime: Date endTime: Date } class ThermalCycleSimulator { simulatorId: String name: String } class SafetyProtocol { protocolId: String maxTemperatureLimit: double minTemperatureLimit: double emergencyStopEnabled: boolean } class ResearchProject { projectId: String projectName: String principalInvestigator: String budget: double } class ExperimentalDataset { datasetId: String name: String dataIntegrityVerified: boolean creationDate: Date filterCriteria: String resultsFiltered: boolean } class SpectroscopyData { dataId: String wavelength: double emissionIntensity: double detectedPhase: PhaseType timestamp: Date } class MicrostructureAnalysis { analysisId: String correlatedPhase: PhaseType refinedFraction: double description: String } class StressTestRunner { runnerId: String name: String } class StressTestRun { testId: String testType: TestType maxLoad: double incrementStep: double timestamp: Date } class PerformanceMetric { metricId: String loadValue: double incrementValue: double stressValue: double strainValue: double } class OptimizationResult { resultId: String convergenceTracked: boolean iterationCount: int recommendedComposition: String } class DesignConstraint { constraintId: String constraintName: String limitValue: double effectiveDate: Date } class RegulatoryStandard { standardId: String standardName: String limitValue: double effectiveDate: Date } class ComplianceArchive { archiveId: String archiveDate: Date } class BatchRecord { recordId: String primaryPhase: PhaseType qualityStatus: QualityStatus recordDate: Date } class CostEstimator { estimatorId: String name: String } class CostEstimation { estimationId: String totalCost: double currency: String calculationDate: Date } class SupplierNetwork { networkId: String name: String } class Supplier { supplierId: String name: String meetsConstraints: boolean contactInfo: String } class QualityAssurance { moduleId: String name: String } class QualityAssuranceReview { reviewId: String inspectorName: String inspectorCertified: boolean approvalDate: Date isApproved: boolean } class ReportGenerator { generatorId: String name: String } class SummaryReport { reportId: String title: String format: ReportFormat generationDate: Date } ' Associations and Compositions AlloyBatch "1" *-- "1..*" MaterialSpecimen: contains specimens MaterialSpecimen "1" *-- "1..*" ElementComposition: base composition MaterialSpecimen "1" *-- "1..*" PhaseDistribution: current phases ExperimentPlanner "1" --> "1..*" HeatTreatmentProfile: generates profiles HeatTreatmentProfile "1" *-- "1..*" ProcessingStep: defined steps PhaseDiagramCalculator "1" --> "*" HeatTreatmentProfile: references for planning PhaseDiagramCalculator "1" --> "*" MicrostructureAnalysis: references for analysis ProcessController "1" --> "1..*" ThermalAnalysisRun: manages runs ProcessController "1" --> "1" ThermalCycleSimulator: utilizes simulator ProcessController "1" --> "1..*" SafetyProtocol: adheres to protocols ThermalCycleSimulator "1" --> "*" ThermalAnalysisRun: simulates ThermalAnalysisRun "*" --> "1" HeatTreatmentProfile: applies profile ResearchProject "1" *-- "1..*" ExperimentalDataset: encompassed datasets ResearchProject "1" --> "1..*" DesignConstraint: associated constraints ExperimentalDataset "1" *-- "*" SpectroscopyData: aggregated data ExperimentalDataset "1" *-- "*" MicrostructureAnalysis: included analyses MicrostructureAnalysis "*" --> "1" MaterialSpecimen: correlates specimen MicrostructureAnalysis "*" --> "1" SpectroscopyData: correlates spectroscopic data StressTestRunner "1" --> "1..*" StressTestRun: performs tests MaterialSpecimen "1" --> "*" StressTestRun: tested in StressTestRun "1" *-- "1..*" PerformanceMetric: generated metrics PerformanceMetric "*" --> "1" OptimizationResult: feeds into ComplianceArchive "1" *-- "1..*" BatchRecord: stored records BatchRecord "*" --> "1" AlloyBatch: documents batch BatchRecord "*" --> "1..*" RegulatoryStandard: linked standards CostEstimator "1" --> "*" AlloyBatch: estimates costs for CostEstimator "1" --> "*" ElementComposition: calculates based on CostEstimator "1" --> "*" CostEstimation: produces estimations AlloyBatch "1" --> "1" CostEstimation: estimated by SupplierNetwork "1" --> "*" Supplier: finds vendors SupplierNetwork "1" --> "*" DesignConstraint: matches constraints QualityAssurance "1" --> "*" QualityAssuranceReview: conducts reviews AlloyBatch "1" --> "*" QualityAssuranceReview: reviewed in ReportGenerator "1" --> "*" SummaryReport: compiles reports ReportGenerator "*" --> "*" PerformanceMetric: compiles from metrics ReportGenerator "*" --> "*" QualityAssuranceReview: compiles from reviews @enduml ``` # Model 2 ``` @startuml skinparam classAttributeIconSize 0 hide empty members class AlloyBatch { creationDate: Date } class MaterialSpecimen { density: Float surfaceFinish: String } class ElementComposition { chemicalMakeup: Map } class PhaseDistribution { austenite: Float ferrite: Float martensite: Float pearlite: Float } class ExperimentPlanner { generateProfile() } class HeatTreatmentProfile { name: String quenchingStatus: Boolean processingSteps: List isValidated: Boolean } class PhaseDiagramCalculator { identifyStablePhases() checkEquilibrium() } class ProcessController { manageRun() } class ThermalAnalysisRun { runAnalysis() } class ThermalCycleSimulator { coolingRate: Float peakTemperature: Float } class SafetyProtocol { emergencyStop: Boolean temperatureLimit: Float } class ResearchProject { principalInvestigator: String budget: Decimal } class ExperimentalDataset { integrityVerified: Boolean filterResults() } class SpectroscopyData { wavelength: Float emissionIntensity: Float } class MicrostructureAnalysis { correlateData() refinePhases() } class StressTestRunner { testType: String performTest() } class PerformanceMetric { load: Float incrementStep: Integer } class OptimizationResult { convergence: Float } class DesignConstraint { limitValue: Float } class RegulatoryStandard { limitValue: Float effectiveDate: Date } class ComplianceArchive { storeRecord() } class BatchRecord { primaryPhase: String qualityStatus: String } class CostEstimator { calculateExpenses() } class SupplierNetwork { findVendors() } class QualityAssurance { inspector: String isCertified: Boolean approveBatch() } class ReportGenerator { format: String compileReport() } AlloyBatch "1" *-- "0..*" MaterialSpecimen MaterialSpecimen "1" *-- "1" ElementComposition MaterialSpecimen "1" *-- "1" PhaseDistribution ExperimentPlanner ..> HeatTreatmentProfile : generates HeatTreatmentProfile ..> PhaseDiagramCalculator : validated by ProcessController "1" --> "0..*" ThermalAnalysisRun : manages ThermalAnalysisRun "1" --> "1" HeatTreatmentProfile : applies ThermalAnalysisRun ..> ThermalCycleSimulator : utilizes ThermalAnalysisRun ..> SafetyProtocol : adheres to ResearchProject "1" *-- "0..*" ExperimentalDataset ResearchProject "1" --> "0..*" DesignConstraint ExperimentalDataset "1" *-- "0..*" SpectroscopyData MicrostructureAnalysis ..> MaterialSpecimen : correlates MicrostructureAnalysis ..> SpectroscopyData : correlates MicrostructureAnalysis ..> PhaseDiagramCalculator : references StressTestRunner ..> MaterialSpecimen : tests StressTestRunner ..> PerformanceMetric : generates OptimizationResult ..> PerformanceMetric : fed by OptimizationResult --> ElementComposition : recommends ComplianceArchive "1" *-- "0..*" BatchRecord BatchRecord "0..*" --> "1" AlloyBatch BatchRecord "0..*" --> "1" RegulatoryStandard CostEstimator ..> ElementComposition : calculates from SupplierNetwork ..> DesignConstraint : meets QualityAssurance ..> AlloyBatch : approves ReportGenerator ..> PerformanceMetric : compiles ReportGenerator ..> QualityAssurance : compiles @enduml ``` # Choices Please choose from the following 3 options based on the scoring criteria: A. Response 1 is better. B. Response 2 is better. C. Tie. Please provide criterion-by-criterion scores before the final choice. Use Tie if the total scores are equal or the meaningful quality difference is small. Also, you should pay adequate and same attention to both responses. **Important**：You should act as an IMPARTIAL judge and be as OBJECTIVE as possible. AVOID ANY POSITION BIASES and ensure that the ORDER in which the responses were presented DOES NOT influence your decision. Before choosing A/B/C, first score Model 1 and Model 2 independently against each specific instruction. If the specific instruction provides a scoring scale, use that scale; otherwise use a 1-5 score where 1 means very poor alignment and 5 means excellent alignment. Base the final choice on the independent scores and the evidence, not on which model is shown first. # Output Your output should be in the following format: ```result Scores: 1. <criterion name>: Model 1 = <score>, Model 2 = <score>; Evidence: <concrete evidence from both models> 2. <criterion name>: Model 1 = <score>, Model 2 = <score>; Evidence: <concrete evidence from both models> Total: Model 1 = <total>, Model 2 = <total> Choice: A Reason: 1. Criterion name: compare Model 1 and Model 2 using concrete evidence from both models. 2. Criterion name: compare Model 1 and Model 2 using concrete evidence from both models. 3. Rejected or checked issues: mention any tempting but unsupported issue that you did not use for the decision, if relevant. 4. Overall judgment: explain why the chosen model is better, or why it is a tie. ``` | G6: codex | H6: GLM5.2 | I6: ```result Scores: 1. Cohesion and Decoupling: Model 1 = 4, Model 2 = 3; Evidence: Model 1 maintains high cohesion through dedicated single-responsibility classes such as `StressTestRunner` (executor) vs. `StressTestRun` (execution record) vs. `PerformanceMetric` (output), and `QualityAssurance` (module) vs. `QualityAssuranceReview` (review record), each with focused attributes. Model 2 merges concepts: `StressTestRunner` carries `testType` and `performTest()` directly, conflating runner and run; `QualityAssurance` bundles `inspector`, `isCertified`, and `approveBatch()` into one class, mixing module and inspector roles. Model 2's `ElementComposition` uses a single `chemicalMakeup: Map` attribute, reducing cohesion by dumping all composition data into one generic field, whereas Model 1's `ElementComposition` with `elementName` and `percentage` has a clear singular purpose. Both models avoid deep inheritance (depth 0), but Model 1's richer composition structure (e.g., `AlloyBatch *-- MaterialSpecimen`, `ResearchProject *-- ExperimentalDataset`) provides cleaner containment boundaries. 2. Complexity: Model 1 = 4, Model 2 = 3; Evidence: Model 1 has 32 domain classes plus 6 enums, which is high but traceable to requirement concepts: `ProcessingStep` maps to "define processing steps," `StressTestRun` maps to "perform destructive or non-destructive tensile tests," `SummaryReport` maps to "summary reports in various formats." Extra classes like `CostEstimation` and `Supplier` are not strictly required but don't cause harm. Model 2 has 26 classes with no enums; it collapses `ProcessingStep` into `processingSteps: List` on `HeatTreatmentProfile`, omits a separate `StressTestRun` class, and lacks `SummaryReport` entirely. Model 2's `PhaseDistribution` hardcodes four float fields (`austenite`, `ferrite`, `martensite`, `pearlite`) rather than using a flexible PhaseType+fraction approach — the requirement uses "such as," indicating these are examples, making Model 2's approach over-constrained. Model 1's complexity is better balanced against the detailed requirement, while Model 2 under-models key concepts. 3. Practicability: Model 1 = 4, Model 2 = 3; Evidence: Model 1 provides practical type-safety via six enums (`SurfaceFinish`, `PhaseType`, `TestType`, `QualityStatus`, `RunState`, `ReportFormat`) enabling validation and clear interfaces. `MaterialSpecimen` includes `grainStructure` and `defectAnnotation` matching the requirement's "classify grain structure, and annotate any defects" — Model 2 omits both. `DesignConstraint` in Model 1 includes `effectiveDate` per the requirement "specify limit values and effective dates" — Model 2's `DesignConstraint` has only `limitValue`, missing `effectiveDate`. Model 1's `ThermalAnalysisRun` carries `currentState`, `peakTemperature`, `coolingRate`, `startTime`, `endTime` for execution state tracking — Model 2's `ThermalAnalysisRun` has only a `runAnalysis()` method with no state attributes. Model 1 correctly places `ProcessController --> ThermalCycleSimulator` and `ProcessController --> SafetyProtocol` per the requirement "a Process Controller... utilizing a Thermal Cycle Simulator... adhering to strict Safety Protocols," while Model 2 places these as dependencies of `ThermalAnalysisRun` instead. Model 2 also uses `..>` (dependency) for many structural relationships (e.g., `ExperimentPlanner ..> HeatTreatmentProfile`, `CostEstimator ..> ElementComposition`) which lack multiplicity precision and are semantically weaker for a class diagram. Both models support the major workflows, but Model 1's richer typing, complete attributes, and proper association semantics make it more practical for implementation and testing. Total: Model 1 = 12, Model 2 = 9 Choice: A Reason: 1. Cohesion and Decoupling: Model 1 separates concerns more effectively — e.g., `StressTestRunner`/`StressTestRun`/`PerformanceMetric` are three distinct concepts in the requirement (runner, test, metrics), and Model 1 gives each its own class; Model 2 merges runner and test into one class with `testType` and `performTest()`. Similarly, Model 1's `QualityAssurance`/`QualityAssuranceReview` separation mirrors the requirement's "Quality Assurance module where certified inspectors approve batches," whereas Model 2 collapses both into a single class. Model 1's `ElementComposition(elementName, percentage)` is more cohesive than Model 2's `chemicalMakeup: Map`. 2. Complexity: Model 1's larger class count (32 + 6 enums) is justified by the requirement's breadth — most classes map to explicitly named concepts (`ProcessingStep`, `StressTestRun`, `SummaryReport`, `BatchRecord`). Model 2's reduction to 26 classes drops key concepts: no `ProcessingStep` class, no `StressTestRun` class, no `SummaryReport` class, no `Supplier` class. Model 2's hardcoded phase fields in `PhaseDistribution` conflict with the requirement's "such as" language indicating a non-exhaustive list. Model 1's enum-based `PhaseDistribution(phaseType, fraction)` is more appropriately complex. 3. Rejected or checked issues: I did not penalize Model 2 for using `Float`/`Boolean`/`Integer` instead of `double`/`boolean`/`int` (primitive type aliases are allowed). I did not penalize Model 1 for its PlantUML comments or for using `1..*` vs `0..*` multiplicities as a forbidden style difference — the multiplicity difference is a domain-accuracy matter (requirement says "contains multiple" implying ≥1, favoring Model 1's `1..*`). I did not reward Model 1 for the `ExperimentalDataset *-- MicrostructureAnalysis` composition, since the requirement does not explicitly state datasets aggregate microstructure analyses. I did not penalize Model 2 for omitting `abstract` markers, as the requirement doesn't specify abstractness. 4. Overall judgment: Model 1 is clearly stronger across all three criteria. It covers more requirement concepts as explicit classes, provides better type safety through enums, includes all required attributes (grainStructure, defectAnnotation, effectiveDate on DesignConstraint), correctly places ProcessController's relationships to ThermalCycleSimulator and SafetyProtocol, and uses proper associations with multiplicities rather than vague dependency arrows. Model 2's compactness comes at the cost of missing concepts, merged responsibilities, and less precise relationship semantics. ``` | J6: A | K6: =IF(OR(J6="",C6="",E6=""),"",IF(J6="C","D(平局)",IF(J6=IF(E6="l2r","A","B"),LEFT(C6,1),RIGHT(C6,1)))) -> A | L6: A | M6: =IF(OR(K6="",L6=""),"",--(K6=L6)) -> 1
A7: AdvancedAlloyCompositionOptimization | B7: The Advanced Alloy Composition Optimization system supports research and industrial processes for developing high-performance metal alloys. The core unit of production is an Alloy Batch, created on a specific date, which contains multiple Material Specimens. Each specimen is defined by its density and surface finish, possesses a base Element Composition describing its chemical makeup, and has a current Phase Distribution detailing the fractions of target phases such as Austenite, Ferrite, Martensite, or Pearlite. Specimens can be analyzed to determine their current phase, classify grain structure, and annotate any defects. To achieve desired material properties, the system utilizes an Experiment Planner that generates Heat Treatment Profiles. These profiles, identified by name and quenching status, define processing steps and are validated before use. The planning process relies on a Phase Diagram Calculator to identify stable phases and check for equilibrium states. During execution, a Process Controller manages Thermal Analysis Runs, utilizing a Thermal Cycle Simulator to model cooling rates and peak temperatures while adhering to strict Safety Protocols that include emergency stop capabilities and temperature limits. Each thermal analysis run applies a specific profile. Data collection is organized under Research Projects, led by a principal investigator with a defined budget and associated design constraints. Projects encompass Experimental Datasets that verify data integrity, filter results, and store generated outcomes. These datasets aggregate Spectroscopy Data, which records wavelengths and emission intensities to detect phases and analyze elemental composition. Microstructure Analysis correlates specimen samples with spectroscopic data to refine phase distributions, utilizing the Phase Diagram Calculator as a reference. Furthermore, Stress Test Runners perform destructive or non-destructive tensile tests on specimens to generate Performance Metrics regarding load and increment steps. These metrics feed into Optimization Results that track convergence and recommend optimal element compositions. The system ensures adherence to engineering and legal standards through Design Constraints and Regulatory Standards, which specify limit values and effective dates to check specimen compliance. A Compliance Archive stores Batch Records, linking regulatory standards to specific batches; each record documents the primary phase, quality status, and the associated alloy batch. Operational support includes a Cost Estimator for calculating raw material expenses based on composition, a Supplier Network for finding vendors meeting design constraints, and a Quality Assurance module where certified inspectors approve batches. Finally, a Report Generator compiles performance metrics and quality assurance sources into summary reports in various formats. | C7: A vs B | D7: general | E7: r2l | F7: You are a professional software engineer with expertise across multiple domains. You evaluate UML class diagrams from the perspective of real-world software design, applying domain knowledge and engineering best practices alongside the provided scoring criteria. Please evaluate the two diagrams (Model 1, Model 2) based on the provided requirement and scoring criteria. # Criteria **CRITICAL INSTRUCTION**: You MUST evaluate the responses against EACH AND EVERY criterion listed in the "Specific Instructions" one by one. DO NOT aggregate, summarize, or skip any criterion. **Specific Instructions**: - Cohesion and Decoupling: The design should aim for high cohesion within individual classes and low coupling between different classes. High cohesion ensures that each class is dedicated to a singular task or concept, enhancing clarity and functionality. Low coupling reduces dependencies among classes, facilitating easier maintenance and scalability. - Complexity: Utilize metrics such as the total number of classes, the average number of methods per class, and the depth of the inheritance tree to evaluate complexity. It's important to discern between conceptual classes and attributes; not every noun should become a class. The complexity level should be appropriately balanced, aligning with the specific requirements detailed in the project's requirement. - Practicability: A practical design should be readable and understandable, offering a clear and comprehensive representation of the software's structures, functionalities, and behaviors. This enhances ease in programming, testing, and maintenance. Modularity should be evident, with each component serving a distinct function, streamlining the development process. Interfaces need to be designed for simplicity, facilitating smooth interactions within the software and with external environments. The design must also support robust testing strategies, enabling thorough validation through unit and acceptance tests, ensuring the design's viability in real-world applications. # Evaluation Guidelines ## General Rules - Consider only UML class diagram semantics (e.g., classes, attributes, associations, multiplicities, generalisation, composition/aggregation). - Ignore layout, styling, skinparams, comments, and notes. - If the response is incomplete or misses any required key component, regard it as a bad one. - Give credit for semantic clarity, but not for layout, comments, visibility markers, or other presentation-only differences. ## Forbidden Penalties (Strictly Enforced) You MUST NOT deduct points, lower scores, or claim a model is "worse", "complex", or "less practical" based on ANY of the following: 1. **Association Styles**: Using two opposite unidirectional associations (e.g., `A --> B` and `B --> A`) instead of one single bidirectional line (e.g., `A -- B`). They are 100% semantically equivalent. Treat opposite-direction associations as equivalent unless role labels, multiplicities, or navigability contradict the requirements. 2. **PlantUML Comments**: Using single-quote comments (e.g., `'opposite bank`) at the end of lines. These are standard tooling annotations — ignore them for scoring unless they obscure or contradict the relation meaning. 3. **Primitive Types**: Using common aliases for types (e.g., `int` instead of `Integer`, `str` instead of `String`, `boolean` instead of `Boolean`). Lowercase or language-flavored spellings are acceptable. 4. **Equivalent Multiplicity Literals**: Using `*` instead of `0..*`, or `1` instead of `1..1`. These pairs are semantically identical. 5. **Optional Abstractness**: Marking or not marking a superclass as `abstract` when the requirement does not say whether direct instances are allowed. Do not reward either style without requirement evidence. These forbidden factors must not appear as negative evidence under any criterion and must not affect criterion scores or the final choice. ## Evidence & Calibration Requirements - For every criterion you discuss, cite concrete evidence from both models. Quote or closely paraphrase the relevant class, attribute, association, multiplicity, inheritance, note, or missing element. - Do not claim a class, attribute, or association is missing when a synonymous or directly related element is present. If the present element is indirect, vague, over-constrained, or semantically weak, state that precise weakness instead. - Distinguish omissions from contradictions. Missing a hard constraint is usually less severe than explicitly modeling the opposite or an invalid multiplicity. - Do not reward a simpler model merely for being shorter if the more detailed model uses traceable intermediate workflow/concept classes required for domain reasoning. - Do not penalize a detailed model merely for using transparent refinements such as `Definition`, `Placement`, `Entry`, `Session`, `State`, `Record`, `Assignment`, `Arrangement`, or `Need` when the base requirement term remains recognizable. - Do not reward extra identifiers, timestamps, statuses, classes, or implementation-oriented detail unless they improve coverage of a stated requirement fact. - Text introduced by `e.g.`, `for example`, or `such as` gives examples, not a complete enumeration, unless the requirement explicitly declares a closed list. - Keep UML/PlantUML standards separate from domain accuracy. Domain-faithfulness problems, wrong business multiplicities, missing constraints, or vague semantics belong under the domain criteria, not UML standards, unless they make the notation invalid or unreadable. - When evaluating position bias, remember that Model 1 and Model 2 may be swapped in a second pass. Use only the content under each model block, not assumptions from prior comparisons or labels. # Requirement ``` The Advanced Alloy Composition Optimization system supports research and industrial processes for developing high-performance metal alloys. The core unit of production is an Alloy Batch, created on a specific date, which contains multiple Material Specimens. Each specimen is defined by its density and surface finish, possesses a base Element Composition describing its chemical makeup, and has a current Phase Distribution detailing the fractions of target phases such as Austenite, Ferrite, Martensite, or Pearlite. Specimens can be analyzed to determine their current phase, classify grain structure, and annotate any defects. To achieve desired material properties, the system utilizes an Experiment Planner that generates Heat Treatment Profiles. These profiles, identified by name and quenching status, define processing steps and are validated before use. The planning process relies on a Phase Diagram Calculator to identify stable phases and check for equilibrium states. During execution, a Process Controller manages Thermal Analysis Runs, utilizing a Thermal Cycle Simulator to model cooling rates and peak temperatures while adhering to strict Safety Protocols that include emergency stop capabilities and temperature limits. Each thermal analysis run applies a specific profile. Data collection is organized under Research Projects, led by a principal investigator with a defined budget and associated design constraints. Projects encompass Experimental Datasets that verify data integrity, filter results, and store generated outcomes. These datasets aggregate Spectroscopy Data, which records wavelengths and emission intensities to detect phases and analyze elemental composition. Microstructure Analysis correlates specimen samples with spectroscopic data to refine phase distributions, utilizing the Phase Diagram Calculator as a reference. Furthermore, Stress Test Runners perform destructive or non-destructive tensile tests on specimens to generate Performance Metrics regarding load and increment steps. These metrics feed into Optimization Results that track convergence and recommend optimal element compositions. The system ensures adherence to engineering and legal standards through Design Constraints and Regulatory Standards, which specify limit values and effective dates to check specimen compliance. A Compliance Archive stores Batch Records, linking regulatory standards to specific batches; each record documents the primary phase, quality status, and the associated alloy batch. Operational support includes a Cost Estimator for calculating raw material expenses based on composition, a Supplier Network for finding vendors meeting design constraints, and a Quality Assurance module where certified inspectors approve batches. Finally, a Report Generator compiles performance metrics and quality assurance sources into summary reports in various formats. ``` # Model 1 ``` @startuml skinparam classAttributeIconSize 0 hide empty members class AlloyBatch { creationDate: Date } class MaterialSpecimen { density: Float surfaceFinish: String } class ElementComposition { chemicalMakeup: Map } class PhaseDistribution { austenite: Float ferrite: Float martensite: Float pearlite: Float } class ExperimentPlanner { generateProfile() } class HeatTreatmentProfile { name: String quenchingStatus: Boolean processingSteps: List isValidated: Boolean } class PhaseDiagramCalculator { identifyStablePhases() checkEquilibrium() } class ProcessController { manageRun() } class ThermalAnalysisRun { runAnalysis() } class ThermalCycleSimulator { coolingRate: Float peakTemperature: Float } class SafetyProtocol { emergencyStop: Boolean temperatureLimit: Float } class ResearchProject { principalInvestigator: String budget: Decimal } class ExperimentalDataset { integrityVerified: Boolean filterResults() } class SpectroscopyData { wavelength: Float emissionIntensity: Float } class MicrostructureAnalysis { correlateData() refinePhases() } class StressTestRunner { testType: String performTest() } class PerformanceMetric { load: Float incrementStep: Integer } class OptimizationResult { convergence: Float } class DesignConstraint { limitValue: Float } class RegulatoryStandard { limitValue: Float effectiveDate: Date } class ComplianceArchive { storeRecord() } class BatchRecord { primaryPhase: String qualityStatus: String } class CostEstimator { calculateExpenses() } class SupplierNetwork { findVendors() } class QualityAssurance { inspector: String isCertified: Boolean approveBatch() } class ReportGenerator { format: String compileReport() } AlloyBatch "1" *-- "0..*" MaterialSpecimen MaterialSpecimen "1" *-- "1" ElementComposition MaterialSpecimen "1" *-- "1" PhaseDistribution ExperimentPlanner ..> HeatTreatmentProfile : generates HeatTreatmentProfile ..> PhaseDiagramCalculator : validated by ProcessController "1" --> "0..*" ThermalAnalysisRun : manages ThermalAnalysisRun "1" --> "1" HeatTreatmentProfile : applies ThermalAnalysisRun ..> ThermalCycleSimulator : utilizes ThermalAnalysisRun ..> SafetyProtocol : adheres to ResearchProject "1" *-- "0..*" ExperimentalDataset ResearchProject "1" --> "0..*" DesignConstraint ExperimentalDataset "1" *-- "0..*" SpectroscopyData MicrostructureAnalysis ..> MaterialSpecimen : correlates MicrostructureAnalysis ..> SpectroscopyData : correlates MicrostructureAnalysis ..> PhaseDiagramCalculator : references StressTestRunner ..> MaterialSpecimen : tests StressTestRunner ..> PerformanceMetric : generates OptimizationResult ..> PerformanceMetric : fed by OptimizationResult --> ElementComposition : recommends ComplianceArchive "1" *-- "0..*" BatchRecord BatchRecord "0..*" --> "1" AlloyBatch BatchRecord "0..*" --> "1" RegulatoryStandard CostEstimator ..> ElementComposition : calculates from SupplierNetwork ..> DesignConstraint : meets QualityAssurance ..> AlloyBatch : approves ReportGenerator ..> PerformanceMetric : compiles ReportGenerator ..> QualityAssurance : compiles @enduml ``` # Model 2 ``` @startuml ' Enumerations enum SurfaceFinish { POLISHED ROUGH MACHINED AS_CAST } enum PhaseType { AUSTENITE FERRITE MARTENSITE PEARLITE } enum TestType { DESTRUCTIVE NON_DESTRUCTIVE } enum QualityStatus { APPROVED REJECTED PENDING } enum RunState { INITIALIZED HEATING HOLDING COOLING COMPLETED EMERGENCY_STOP } enum ReportFormat { PDF CSV JSON HTML } ' Domain Classes class AlloyBatch { batchId: String creationDate: Date name: String } class MaterialSpecimen { specimenId: String density: double surfaceFinish: SurfaceFinish grainStructure: String defectAnnotation: String } class ElementComposition { elementName: String percentage: double } class PhaseDistribution { phaseType: PhaseType fraction: double } class ExperimentPlanner { plannerId: String name: String } class HeatTreatmentProfile { profileId: String name: String quenchingStatus: boolean isValidated: boolean } class ProcessingStep { stepOrder: int targetTemperature: double durationMinutes: int description: String } class PhaseDiagramCalculator { calculatorId: String name: String equilibriumState: boolean stablePhases: String } class ProcessController { controllerId: String name: String } class ThermalAnalysisRun { runId: String currentState: RunState peakTemperature: double coolingRate: double startTime: Date endTime: Date } class ThermalCycleSimulator { simulatorId: String name: String } class SafetyProtocol { protocolId: String maxTemperatureLimit: double minTemperatureLimit: double emergencyStopEnabled: boolean } class ResearchProject { projectId: String projectName: String principalInvestigator: String budget: double } class ExperimentalDataset { datasetId: String name: String dataIntegrityVerified: boolean creationDate: Date filterCriteria: String resultsFiltered: boolean } class SpectroscopyData { dataId: String wavelength: double emissionIntensity: double detectedPhase: PhaseType timestamp: Date } class MicrostructureAnalysis { analysisId: String correlatedPhase: PhaseType refinedFraction: double description: String } class StressTestRunner { runnerId: String name: String } class StressTestRun { testId: String testType: TestType maxLoad: double incrementStep: double timestamp: Date } class PerformanceMetric { metricId: String loadValue: double incrementValue: double stressValue: double strainValue: double } class OptimizationResult { resultId: String convergenceTracked: boolean iterationCount: int recommendedComposition: String } class DesignConstraint { constraintId: String constraintName: String limitValue: double effectiveDate: Date } class RegulatoryStandard { standardId: String standardName: String limitValue: double effectiveDate: Date } class ComplianceArchive { archiveId: String archiveDate: Date } class BatchRecord { recordId: String primaryPhase: PhaseType qualityStatus: QualityStatus recordDate: Date } class CostEstimator { estimatorId: String name: String } class CostEstimation { estimationId: String totalCost: double currency: String calculationDate: Date } class SupplierNetwork { networkId: String name: String } class Supplier { supplierId: String name: String meetsConstraints: boolean contactInfo: String } class QualityAssurance { moduleId: String name: String } class QualityAssuranceReview { reviewId: String inspectorName: String inspectorCertified: boolean approvalDate: Date isApproved: boolean } class ReportGenerator { generatorId: String name: String } class SummaryReport { reportId: String title: String format: ReportFormat generationDate: Date } ' Associations and Compositions AlloyBatch "1" *-- "1..*" MaterialSpecimen: contains specimens MaterialSpecimen "1" *-- "1..*" ElementComposition: base composition MaterialSpecimen "1" *-- "1..*" PhaseDistribution: current phases ExperimentPlanner "1" --> "1..*" HeatTreatmentProfile: generates profiles HeatTreatmentProfile "1" *-- "1..*" ProcessingStep: defined steps PhaseDiagramCalculator "1" --> "*" HeatTreatmentProfile: references for planning PhaseDiagramCalculator "1" --> "*" MicrostructureAnalysis: references for analysis ProcessController "1" --> "1..*" ThermalAnalysisRun: manages runs ProcessController "1" --> "1" ThermalCycleSimulator: utilizes simulator ProcessController "1" --> "1..*" SafetyProtocol: adheres to protocols ThermalCycleSimulator "1" --> "*" ThermalAnalysisRun: simulates ThermalAnalysisRun "*" --> "1" HeatTreatmentProfile: applies profile ResearchProject "1" *-- "1..*" ExperimentalDataset: encompassed datasets ResearchProject "1" --> "1..*" DesignConstraint: associated constraints ExperimentalDataset "1" *-- "*" SpectroscopyData: aggregated data ExperimentalDataset "1" *-- "*" MicrostructureAnalysis: included analyses MicrostructureAnalysis "*" --> "1" MaterialSpecimen: correlates specimen MicrostructureAnalysis "*" --> "1" SpectroscopyData: correlates spectroscopic data StressTestRunner "1" --> "1..*" StressTestRun: performs tests MaterialSpecimen "1" --> "*" StressTestRun: tested in StressTestRun "1" *-- "1..*" PerformanceMetric: generated metrics PerformanceMetric "*" --> "1" OptimizationResult: feeds into ComplianceArchive "1" *-- "1..*" BatchRecord: stored records BatchRecord "*" --> "1" AlloyBatch: documents batch BatchRecord "*" --> "1..*" RegulatoryStandard: linked standards CostEstimator "1" --> "*" AlloyBatch: estimates costs for CostEstimator "1" --> "*" ElementComposition: calculates based on CostEstimator "1" --> "*" CostEstimation: produces estimations AlloyBatch "1" --> "1" CostEstimation: estimated by SupplierNetwork "1" --> "*" Supplier: finds vendors SupplierNetwork "1" --> "*" DesignConstraint: matches constraints QualityAssurance "1" --> "*" QualityAssuranceReview: conducts reviews AlloyBatch "1" --> "*" QualityAssuranceReview: reviewed in ReportGenerator "1" --> "*" SummaryReport: compiles reports ReportGenerator "*" --> "*" PerformanceMetric: compiles from metrics ReportGenerator "*" --> "*" QualityAssuranceReview: compiles from reviews @enduml ``` # Choices Please choose from the following 3 options based on the scoring criteria: A. Response 1 is better. B. Response 2 is better. C. Tie. Please provide criterion-by-criterion scores before the final choice. Use Tie if the total scores are equal or the meaningful quality difference is small. Also, you should pay adequate and same attention to both responses. **Important**：You should act as an IMPARTIAL judge and be as OBJECTIVE as possible. AVOID ANY POSITION BIASES and ensure that the ORDER in which the responses were presented DOES NOT influence your decision. Before choosing A/B/C, first score Model 1 and Model 2 independently against each specific instruction. If the specific instruction provides a scoring scale, use that scale; otherwise use a 1-5 score where 1 means very poor alignment and 5 means excellent alignment. Base the final choice on the independent scores and the evidence, not on which model is shown first. # Output Your output should be in the following format: ```result Scores: 1. <criterion name>: Model 1 = <score>, Model 2 = <score>; Evidence: <concrete evidence from both models> 2. <criterion name>: Model 1 = <score>, Model 2 = <score>; Evidence: <concrete evidence from both models> Total: Model 1 = <total>, Model 2 = <total> Choice: A Reason: 1. Criterion name: compare Model 1 and Model 2 using concrete evidence from both models. 2. Criterion name: compare Model 1 and Model 2 using concrete evidence from both models. 3. Rejected or checked issues: mention any tempting but unsupported issue that you did not use for the decision, if relevant. 4. Overall judgment: explain why the chosen model is better, or why it is a tie. ``` | G7: codex | H7: GLM5.2 | I7: Now let me evaluate both models criterion by criterion based on all the evidence gathered. ```result Scores: 1. Cohesion and Decoupling: Model 1 = 3, Model 2 = 3; Evidence: Model 1 keeps classes focused with singular responsibilities (e.g., `StressTestRunner` with `performTest()`, `CostEstimator` with `calculateExpenses()`), and uses loose dependency arrows (`..>`) for cross-cutting relationships like `OptimizationResult ..> PerformanceMetric : fed by` and `ReportGenerator ..> PerformanceMetric / QualityAssurance`. Coupling is moderate — `ThermalAnalysisRun` depends on both `ThermalCycleSimulator` and `SafetyProtocol` directly. Model 2 similarly separates concerns but introduces intermediaries like `CostEstimation`, `StressTestRun`, `QualityAssuranceReview`, and `SummaryReport` as separate classes, which adds indirection that can reduce coupling between the orchestrator and data (e.g., `QualityAssurance --> QualityAssuranceReview` instead of directly to `AlloyBatch`). However, Model 2 also creates tighter coupling webs: `ProcessController --> ThermalCycleSimulator`, `ThermalCycleSimulator --> ThermalAnalysisRun`, AND `ThermalAnalysisRun --> HeatTreatmentProfile`, distributing the thermal-run logic across three classes with bidirectional-ish links. Both models are comparable — Model 1 is slightly more direct with fewer hops, Model 2 uses intermediaries but adds some circular-ish paths. Net: roughly tied. 2. Complexity: Model 1 = 4, Model 2 = 3; Evidence: Model 1 has 26 classes, no enums, and keeps attribute lists concise (e.g., `PhaseDistribution` with 4 float fields, `SafetyProtocol` with 2 fields). It models `processingSteps: List` as an attribute of `HeatTreatmentProfile` rather than a separate class — reasonable for the requirement which says "define processing steps" without elaborating. Model 2 has 32 classes + 6 enums = 38 total classifiers, with extra classes like `ProcessingStep`, `StressTestRun`, `CostEstimation`, `Supplier`, `QualityAssuranceReview`, `SummaryReport` beyond what the requirement explicitly demands. Some additions are reasonable refinements (e.g., `ProcessingStep` for "processing steps"), but others like `CostEstimation` (with `currency`, `totalCost`) and `Supplier` (with `contactInfo`) add implementation detail not stated in the requirement. The inheritance tree depth is 0 in both (no inheritance used). Model 1's complexity is better balanced to the requirement scope; Model 2 is somewhat over-engineered with extra identifiers (`plannerId`, `controllerId`, `simulatorId`, etc.) and timestamp/status fields on nearly every class. 3. Practicability: Model 1 = 3, Model 2 = 4; Evidence: Model 1 provides a compact, readable diagram where each class maps to a requirement concept and methods are minimal but clear (`generateProfile()`, `manageRun()`, `runAnalysis()`, `correlateData()`, `refinePhases()`, `compileReport()`). However, some key domain semantics are under-modeled: `ElementComposition` has only `chemicalMakeup: Map` — vague; `PhaseDistribution` hardcodes the four phases as attributes (`austenite`, `ferrite`, `martensite`, `pearlite`) rather than modeling them as instances, which is less flexible; `StressTestRunner` has `testType: String` rather than destruct/non-destruct distinction; specimen analysis (grain structure, defects) is missing as attributes or methods on `MaterialSpecimen`. Model 2 is more practically implementable: it uses enums for `TestType` (DESTRUCTIVE/NON_DESTRUCTIVE), `PhaseType`, `QualityStatus`, `RunState`, `ReportFormat`, and `SurfaceFinish`, making the design more testable and type-safe. `MaterialSpecimen` includes `grainStructure` and `defectAnnotation` per the requirement. `SpectroscopyData` includes `detectedPhase: PhaseType` matching "detect phases." `BatchRecord` uses `qualityStatus: QualityStatus` enum. These make Model 2 more directly translatable to code and more testable. Model 2's `ProcessingStep` class with `stepOrder`, `targetTemperature`, `durationMinutes` is more practically usable than Model 1's `processingSteps: List`. Model 2 wins on practicability despite higher complexity. Total: Model 1 = 10, Model 2 = 10 Choice: C Reason: 1. Cohesion and Decouption: Both models achieve similar cohesion/decoupling levels. Model 1 uses fewer intermediary classes and relies on dependency relationships (`..>`) for cross-cutting concerns. Model 2 introduces intermediary data classes (`CostEstimation`, `QualityAssuranceReview`, `SummaryReport`, `StressTestRun`) that can reduce direct coupling between orchestrators and domain entities, but also creates denser relationship webs around `ProcessController`/`ThermalCycleSimulator`/`ThermalAnalysisRun`. Neither is clearly superior — the trade-offs balance out. 2. Complexity: Model 1 is better calibrated — 26 classes with concise attributes map tightly to the requirement without over-elaboration. Model 2 has 38 classifiers (32 classes + 6 enums) with many extra IDs, timestamps, and helper classes (e.g., `CostEstimation` with `currency`, `Supplier` with `contactInfo`) that go beyond the stated requirement. Model 1 scores higher here for appropriate complexity balance. However, some of Model 2's additions (enums, `ProcessingStep`) genuinely aid clarity, so the gap is not large. 3. Practicability: Model 2 is clearly stronger here — it uses typed enums for `PhaseType`, `TestType`, `QualityStatus`, `RunState`, `ReportFormat`, and `SurfaceFinish`; includes `grainStructure` and `defectAnnotation` on `MaterialSpecimen` (which Model 1 omits entirely); models `detectedPhase` on `SpectroscopyData`; and decomposes `ProcessingStep` with concrete attributes. These make Model 2 more directly implementable and testable. Model 1's `chemicalMakeup: Map` and hardcoded phase attributes are vaguer and less type-safe. 4. Rejected or checked issues: I did not penalize Model 1 for using `Float`/`Boolean`/`String` instead of `double`/`boolean` (forbidden — primitive type aliases). I did not penalize either model for association style differences (Model 1 uses `..>` dependency arrows extensively; Model 2 uses `-->` navigable associations — both are semantically valid). I did not reward Model 2 merely for extra ID fields (`plannerId`, `controllerId`, etc.) since these are implementation detail not required. I did not penalize Model 2 for the extra helper classes like `CostEstimation` and `SummaryReport` as "transparent refinements" per the calibration guidance, but noted that some add unrequired detail. 5. Overall judgment: The two models are complementary in strengths — Model 1 is leaner and better complexity-calibrated, while Model 2 is more practically implementable with richer typing and better domain coverage (specimen analysis fields, enums, processing step decomposition). Model 1 loses points for omitting specimen grain structure/defect annotation entirely and using vague attribute types (`chemicalMakeup: Map`); Model 2 loses points for over-engineering with unrequired classes and fields. The total scores are equal (10 vs 10), and the meaningful quality difference is small — both models adequately cover the requirement with different trade-offs. A tie is the fair outcome. ``` | J7: C | K7: =IF(OR(J7="",C7="",E7=""),"",IF(J7="C","D(平局)",IF(J7=IF(E7="l2r","A","B"),LEFT(C7,1),RIGHT(C7,1)))) -> D(平局) | L7: A | M7: =IF(OR(K7="",L7=""),"",--(K7=L7)) -> 0
